Workbook

Sheet Home
C1: Welcome to Destiny 2: Quantum Damage-ics
B2: =image("https://www.bungie.net/common/destiny2_content/icons/f385fda03b8ab139f6c2179844685fcf.jpg", 4, 65, 65) | D2: Game version: 8.2.6 >>> 9.5.6.3 | F2: =image("https://www.bungie.net/common/destiny2_content/icons/a93e3f872c8e0af699f09d59e09603c6.jpg", 4, 65, 65)
D3: Want to invest in the spreadsheet? Ko-fi
C4: Purpose
C5: The purpose of this spreadsheet is to showcase the absolute maximization of raw weapon DPS on boss-tier combatants; It serves as a reference of where weapons stand in comparison to other weapons in the context of boss DPS phases. The spreadsheet provides raw values that the user can process to compare DPS or manipulate on their own means to compare damage multipliers.
C6: Assumptions Made
C7: To make data comparison between weapons more fair: > All weapons are normalized, i.e. the new weapon bonus is removed > The only exception to this rule is exotics, as they all have an innate +5% > All weapons assume the effects of Rally barricade/Lunafactions reload speed boosting to minimize reload speeds to a consistent amount. > All weapons assume Extended Mag (or similar) and Backup Mag (whenever applicable), unless otherwise stated, to keep magazine sizes at a consistent amount. > Changing the magazine capacity may affect the total reserves of a weapon; see the Inventory and Mag Database below for further information. > Note: some weapons may be able to maximize the magazine stat through means other than Backup Mag, see Inventory and Mag Database below. > All legendary weapons exclude perks unless otherwise stated. > All weapons assume depleting the entire magazine before reloading unless otherwise stated. > All weapons assume reloading the instant the final round of the magazine is fired (hitting the reload context button at the same time the final round is fired). > All weapon DPS calculations assume precision hits whenever applicable or unless otherwise stated. > All pellet shotguns DPS calculations assume body shots, unless otherwise stated, to make comparison more realistic.
C8: Methods and Calculations
B9: =image("https://www.bungie.net/common/destiny2_content/icons/f87eddefbcbc59f22ba3cb8c4af7c824.jpg", 4, 65, 65) | C9: Method of DPS calculation: (damage sum of individual attacks) / (time sum of individual attacks) note that this is not (measured total damage) / (measured total time) The total damage over total time is the Average DPS, and will likely be higher if not equal to the Sustained DPS because the time span measured is relatively small. As you increase time (and assume infinite ammo) you will approach the actual Sustained DPS figure. To get a better visual, visit the Equations page and see the graph for DPS as a function of time. All timings are done at 60 fps. | F9: =image("https://www.bungie.net/common/destiny2_content/icons/73819c52be4d6d983470c16141d4ea59.jpg", 4, 65, 65)
C10: Other Notes
C11: As you navigate this spreadsheet, take note: > If a cell has a hyperlink, you can double-click on the cell to be able to directly click on the hyperlink. > If you wish to inspect how DPS values were calculated, you can double-click on a cell to see the exact formula. > Some cells make use of custom-defined formulas which are scripted and aren't viewable in read-only mode. > Some of these formulas are defined in the Equations page. > Other formulas may require you to download a copy of this spreasheet and open Extensions -> Apps Script to view them as they are programmed functions. > Color-gradient columns are meant to compare values to other members within the same column. > More green is bettter, within the same respective column (e.g.: more damage or better sustained DPS). > Certain fields may contain a note on them for more information. Expand these notes by dragging the bottom-right corner for better readability. > If you wish to sort everything, see "All Weapons" and its associated page header. > The Weapon Change Log page is to keep track of when weapons were last tested and their respective data points were modified. > Any cells highlighted in red are considered to be outdated/bad/to-be-determined and subject to change. Remember: this spreadsheet is meant to represent frame-perfect DPS scenarios. The data is intended to explore the best potential of weapons on their own and serve as a comparison tool when it comes to choosing your next DPS option. Do not expect to hit the DPS values provided. These values are for ultra-tier (boss) enemies only. They may or may not apply to other-tiered enemies, such as minibosses, champions, majors, and minors. For more context, see this.
C12: Contact
B13: =image("https://www.bungie.net/common/destiny2_content/icons/ef22dad66075d196eb70d63b553bbc37.jpg", 4, 65, 65) | C13: If you have any questions, comments, concerns, or would simply like to make contributions, you have a few methods of contact: > Google Form: use this Google form if you prefer to stay anonymous or do not want to use Reddit > Private Message: send a private message u/XboxUser123 > Reddit comment (fallback): make a comment on this Reddit post Please let me know of any potential issues, I am a one-man army (with some helpers) and keeping this spreadsheet as accurate as possible is the priority! | F13: =image("https://www.bungie.net/common/destiny2_content/icons/d0757ce420245c12bd9e57d2e7a1f3bc.jpg", 4, 65, 65)
C14: Definitions
B15: =image("https://www.bungie.net/common/destiny2_content/icons/0f4ca23c2d932ed784c7710a5b1c37d7.jpg", 4, 65, 65) | C15: Some definitions on words, phrases, and acronyms used: 1-Mag DPS or "True DPS" > The amount of DPS while not considering reloading, or equivalently (if applicable) of a single magazine. > The DPS of a single magazine and the DPS of omitting reloads entirely and focusing solely on damage and fire rate are identical. > Note that some weapons have a unique 1-mag DPS compared to their theoretical "True DPS" counterpart due to how they work (such as Merciless). Sustained DPS > The amount of DPS while also considering reloading. > This is the DPS you would expect to have for DPS phases, assuming you had infinite reserves and infinite time. > Note that this also assumes you hit the reload context as soon as you fire your final round. > If the data entry is for a single magazine, the Sustained DPS and True DPS will be equivalent. > A way to guage the difference between Sustained DPS and True DPS is to look it as minimums and maximums. > Sustained DPS is the minimum DPS expected, while 1-mag or "True DPS" is the maximum DPS expected. Average DPS > The amount of total damage divided by the total time. Although it is not considered in this spreadsheet, it can be easily calculated using existing values. > For more context, dividing the total damage over the time to empty should yield a result between the sustained and true DPS figures. > Average DPS should be closer to the sustained DPS than the true DPS. > If this average figure appears off, let me know as there may be a problem with how the time to empty is set up. For a more visual representation between the three DPS types, see the Equations page and the associated Desmos graph. The sloping lines in that graph represent the average DPS at an instant of time. cata > Stands for "catalyst," meaning the data row assumes an exotic weapon catalyst is used. DOT > Stands for "Damage Over Time," refers to passive damage sources, such as Witherhoard blights, that passively deal damage without your interaction over time. "w/" or "w/o" > Stands for "with" or "without," respectively. DDC > Stands for "Destiny Data Compendium," implies that the data was sourced from the Destiny Data Compendium Weapon damage is "normalized" > Weapons do not assume "new gear" bonus > Exotic weapons do not assume "featured gear" bonus | F15: =image("https://www.bungie.net/common/destiny2_content/icons/e55041686045a487bc46bc3f4cf0fe0f.jpg", 4, 65, 65)
B16: =image("https://www.bungie.net/common/destiny2_content/icons/2e3161404a48ca6f7326d4010f79bc13.jpg", 4, 65, 65) | F16: =image("https://www.bungie.net/common/destiny2_content/icons/940fbc426dcd7048d31160c92d5d5708.jpg", 4, 65, 65)
C17: Testing is done on the Dummy of Practice in the new shooting range, Normal difficulty (no modifiers)
C18: All damage testing is done on Barry in "The Investigation" mission of the Witch Queen campaign on legendary difficulty.
C20: References & Links
B21: =image("https://www.bungie.net/common/destiny2_content/icons/96fa99298a501e77a4f51337d3c12867.jpg", 4, 65, 65) | C21: External data used: D2Foundry/D2Gunsmith for some reload timings Destiny Data Compendium for certain multipliers and miscellaneous data Destiny 2 Inventory and Mag Database for reserves and magazine stats See Also: destiny2.science for other scientific research into Destiny 2 Inspired by: Damage Chart Madness | F21: =image("https://www.bungie.net/common/destiny2_content/icons/41b410dbf888f3256867c011a4e955e5.jpg", 4, 65, 65)

Sheet Bounty Board (1)
A1: Bounty Board
A2: Date Issued | B2: What is Needed | C2: Description | D2: Reward
A3: No bounties are present at this time
A4: 46004 | B4: Data! Data! Data! | C4: Need to retest entire suites of weapons. Simplest being the legendaries. See the TODO page for more specifics on what needs to be retested. Note: make sure to turn off the special surge that is going on this week if you decide to test the special weapons Note: don't forget, weapon stat will affect your damage output, make sure to minimize it to 0 or 1 | D4: The high ground

Sheet Primaries
A1: Note: all weapons assume Backup Mag whenever applicable; All weapon damage (except exotics) is normalized. Want to contribute? Have questions, comments, or concerns? See Home page contact information.
B2: Frame/Weapon | C2: 1-Mag Burst or "True" DPS | D2: Sustained DPS | F2: Theoretical Total Damage | G2: 1-Mag Damage | H2: Magazine Capacity | I2: Reserves + Magazine | J2: Fire rate (rpm) | K2: Reload Speed (s) | L2: Time to Empty (s) | M2: Body Damage | N2: Precision Damage
A3: Auto Rifles | B3: Rapid-Fire | C3: =(G3)/(H3 * 1/J3 * 60/1) -> 276 | D3: =(G3)/((H3-1) * 1/J3 * 60/1 + K3) -> 242.25098 | F3: inf | G3: =N3 * H3 -> 1610 | H3: 70 | I3: inf | J3: 720 | K3: =1.12*0.8 -> 0.896 | L3: inf | M3: 14 | N3: 23
B4: Adaptive | C4: =(G4)/(H4 * 1/J4 * 60/1) -> 260 | D4: =(G4)/((H4-1) * 1/J4 * 60/1 + K4) -> 220.53571 | F4: inf | G4: =N4 * H4 -> 1482 | H4: 57 | I4: inf | J4: 600 | K4: 1.12 | L4: inf | M4: 15 | N4: 26
B5: Support | C5: =(G5)/(H5 * 1/J5 * 60/1) -> 260 | D5: =(G5)/((H5-1) * 1/J5 * 60/1 + K5) -> 222.22222 | F5: inf | G5: =N5 * H5 -> 1560 | H5: 60 | I5: inf | J5: 600 | K5: 1.12 | L5: inf | M5: 19 | N5: =N4 -> 26
B6: Precision | C6: =(G6)/(H6 * 1/J6 * 60/1) -> 247.5 | D6: =(G6)/((H6-1) * 1/J6 * 60/1 + K6) -> 212.54771 | F6: inf | G6: =N6 * H6 -> 1485 | H6: 45 | I6: inf | J6: 450 | K6: 1.12 | L6: inf | M6: 20 | N6: 33
B7: High-Impact | C7: =(G7)/(H7 * 1/J7 * 60/1) -> 252 | D7: =(G7)/((H7-1) * 1/J7 * 60/1 + K7) -> 223.58044 | F7: inf | G7: =N7 * H7 -> 1890 | H7: 45 | I7: inf | J7: 360 | K7: 1.12 | L7: inf | M7: 24 | N7: 42
A8: average per mag | B8: Sweet Business | C8: =(G8)/(H8 * 1/J8 * 60/1) -> 471.68675 | D8: =(G8)/((H8-1) * 1/J8 * 60/1 + K8) -> 398.5295 | F8: inf | G8: =N8 * H8 + ('Weapon Specifics'!D64*4 + floor(108/8,1)*'Weapon Specifics'!D64) -> 4959 | H8: 150 | I8: inf | J8: =150/(1.38 * 1/60 + (150-13) * 1/900) -> 856.0558 | K8: 2 | L8: inf | M8: 20 | N8: 30
A9: Spinning Up | B9: Suros Regime | C9: =(G9)/(H9 * 1/J9 * 60/1) -> 332.24128 | D9: =(G9)/((H9-1) * 1/J9 * 60/1 + K9) -> 244.06429 | F9: inf | G9: =H9/2 * N9 + H9/2 * N9 * (1.05+1.1)/2 -> 952.425 | H9: 34 | I9: inf | J9: =H9/(12 * 1/600 + 12 * 1/720 + (H9-24) * 1/900) -> 711.62791 | K9: =K10 -> 1.12 | L9: inf | M9: 16 | N9: 27
A10: Dual Speed Receiver | B10: Suros Regime | C10: =(G10)/(H10 * 1/J10 * 60/1) -> 273.9 | D10: =(G10)/((H10-1) * 1/J10 * 60/1 + K10) -> 234.45619 | F10: inf | G10: =H10/2 * N10 + H10/2 * N10 * (1.05+1.1)/2 -> 1552.1 | H10: 34 | I10: inf | J10: 360 | K10: 1.12 | L10: inf | M10: 25 | N10: 44 | O10: Aiming-down-sights only
B11: Tommy's Matchbook | C11: =(G11)/(H11 * 1/J11 * 60/1) + 'Elemental Effects'!E13 -> 711.84143 | D11: =(G11)/((H11-1) * 1/J11 * 60/1 + K11) + 'Elemental Effects'!E13 -> 648.24735 | F11: inf | G11: =(20 * 'Weapon Specifics'!D76) + N11*(H11-20) + ('Elemental Effects'!$E$4)*(2) -> 5746 | H11: 100 | I11: inf | J11: 720 | K11: 0.93 | L11: inf | M11: 28 | N11: 47 | O11: Assumes normal 20 bullets + 80 buffed while burning; considers ignitions and approx. scorch
A12: Ember of Ashes | B12: Tommy's Matchbook | C12: =(G12)/(H12 * 1/J12 * 60/1) + 'Elemental Effects'!E13 -> 801.00143 | D12: =(G12)/((H12-1) * 1/J12 * 60/1 + K12) + 'Elemental Effects'!E13 -> 729.18417 | F12: inf | G12: =(20 * 'Weapon Specifics'!D76) + N12*(H12-20) + ('Elemental Effects'!$E$4)*(3) -> 6489 | H12: 100 | I12: inf | J12: 720 | K12: 0.93 | L12: inf | M12: =M11 -> 28 | N12: =N11 -> 47 | O12: Assumes normal 20 bullets + 80 buffed while burning; considers ignitions and approx. scorch
B13: Quicksilver Storm | C13: =(G13)/(H13 * 1/J13 * 60/1) -> 367.05882 | D13: =(G13)/((H13-1) * 1/J13 * 60/1 + K13) -> 296.20253 | F13: inf | G13: =H13*N13 + FLOOR(H13/'Weapon Specifics'!D48,1) * ('Weapon Specifics'!D49) -> 1560 | H13: 51 | I13: inf | J13: 720 | K13: 1.1 | L13: inf | M13: 14 | N13: 24 | O13: DPS assumes bullets + rockets.
A14: mixed modes | B14: Quicksilver Storm | C14: =D14 -> 445.46763 | D14: =(N14*22 + ('Weapon Specifics'!D49)*2 + ('Weapon Specifics'!D50)*2)/(('Weapon Specifics'!D48*2) * 1/J14 * 60/1 + 1.1 + 1.1 + 0.6) -> 445.46763 | F14: inf | G14: N/A | H14: 51 | I14: inf | J14: 720 | K14: 1.1 | L14: inf | M14: =M13 -> 14 | N14: =N13 -> 24 | O14: DPS assumes 22 rounds + 2 rockets > grenade > grenade > repeat; an extra grenade is held
B15: Necrochasm | C15: =(G15)/(H15 * 1/J15 * 60/1) -> 288 | D15: =(G15)/((H15-1) * 1/J15 * 60/1 + K15) -> 228.86205 | F15: inf | G15: =N15 * H15 -> 1200 | H15: 50 | I15: inf | J15: 720 | K15: 1.16 | L15: inf | M15: =M13 -> 14 | N15: =N13 -> 24
B16: Vex Mythoclast | C16: =(G16)/(H16 * 1/J16 * 60/1) -> 612 | D16: =(G16)/((H16-1) * 1/J16 * 60/1 + K16) -> 498.04688 | F16: inf | G16: =N16 * H16 -> 2550 | H16: 25 | I16: inf | J16: 360 | K16: 1.12 | L16: inf | M16: 57 | N16: 102 | O16: Excludes linear shots
B17: Hard Light | C17: =(G17)/(H17 * 1/J17 * 60/1) -> 270 | D17: =(G17)/((H17-1) * 1/J17 * 60/1 + K17) -> 223.47973 | F17: inf | G17: =N17 * H17 -> 1323 | H17: 49 | I17: inf | J17: 600 | K17: 1.12 | L17: inf | M17: 16 | N17: 27
B18: Khvostov 7G-0X | C18: =(N18*6 + 'Weapon Specifics'!D33)/(7 * 1/J18 * 60/1) -> 304.28571 | D18: =((H18-7)*N18 + 7*'Weapon Specifics'!D33)/((H18-1) * 1/J18 * 60/1 + K18) -> 249.81203 | F18: inf | G18: =N18 * (H18 - floor(H18/7,1)) + FLOOR(H18/7,1) * N18*(1+2.52) -> 1569.24 | H18: 43 | I18: inf | J18: 600 | K18: 1.12 | L18: inf | M18: =M17 -> 16 | N18: =N17 -> 27 | O18: with ricochet rounds
B19: Monte Carlo | C19: =(G19)/(H19 * 1/J19 * 60/1) -> 270 | D19: =(G19)/((H19-1) * 1/J19 * 60/1 + K19) -> 219.18819 | F19: inf | G19: =N19 * H19 -> 1188 | H19: 44 | I19: inf | J19: 600 | K19: 1.12 | L19: inf | M19: =M17 -> 16 | N19: =N17 -> 27 | O19: =CONCAT("Bayonet does ", 'Weapon Specifics'!$D$40) -> Bayonet does 2913
B20: Centrifuse | C20: =(G20)/(H20 * 1/J20 * 60/1) -> 262.5 | D20: =(G20)/((H20-1) * 1/J20 * 60/1 + K20) -> 247.3822 | F20: inf | G20: =N20 * H20 -> 1575 | H20: 45 | I20: inf | J20: 450 | K20: 0.5 | L20: inf | M20: 21 | N20: 35
A21: normal, close range | B21: Cerberus+1 | C21: =(G21)/(H21 * 1/J21 * 60/1) -> 312 | D21: =(G21)/((H21-1) * 1/J21 * 60/1 + K21) -> 263.39869 | F21: inf | G21: =M21 * H21 -> 1612 | H21: 31 | I21: inf | J21: 360 | K21: 1.12 | L21: inf | M21: =13*4 -> 52 | N21: 93 | O21: Body damage DPS
A22: normal, close range | B22: Cerberus+1 | C22: =(G22)/(H22 * 1/J22 * 60/1) -> 558 | D22: =(G22)/((H22-1) * 1/J22 * 60/1 + K22) -> 471.07843 | F22: inf | G22: =N22 * H22 -> 2883 | H22: 31 | I22: inf | J22: =J21 -> 360 | K22: 1.12 | L22: inf | M22: =M21 -> 52 | N22: =N21 -> 93 | O22: Precision damage DPS
A23: normal, far range | B23: Cerberus+1 | C23: =(G23)/(H23 * 1/J23 * 60/1) -> 384 | D23: =(G23)/((H23-1) * 1/J23 * 60/1 + K23) -> 324.18301 | F23: inf | G23: =M23 * H23 -> 1984 | H23: 31 | I23: inf | J23: =J21 -> 360 | K23: 1.12 | L23: inf | M23: =16*4 -> 64 | N23: =28*4 -> 112 | O23: Reverse damage fall-off; body damage DPS
A24: normal, far range | B24: Cerberus+1 | C24: =(G24)/(H24 * 1/J24 * 60/1) -> 672 | D24: =(G24)/((H24-1) * 1/J24 * 60/1 + K24) -> 567.32026 | F24: inf | G24: =N24 * H24 -> 3472 | H24: 31 | I24: inf | J24: =J21 -> 360 | K24: 1.12 | L24: inf | M24: =M23 -> 64 | N24: =N23 -> 112 | O24: Reverse damage fall-off; all precision shots land for precision damage DPS (if it's even possible)
A25: cata, close range | B25: Cerberus+1 | C25: =(G25)/(H25 * 1/J25 * 60/1) -> 468 | D25: N/A | F25: inf | G25: =M25 * H25 -> 2418 | H25: 31 | I25: inf | J25: =J21 -> 360 | K25: 1.12 | L25: inf | M25: =M21*1.5 -> 78 | N25: =N21*1.5 -> 139.5 | O25: Body damage DPS; requires a kill before reload, buff lasts for ~8 seconds
A26: cata, close range | B26: Cerberus+1 | C26: =(G26)/(H26 * 1/J26 * 60/1) -> 837 | D26: N/A | F26: inf | G26: =N26 * H26 -> 4324.5 | H26: 31 | I26: inf | J26: =J21 -> 360 | K26: 1.12 | L26: inf | M26: =M25 -> 78 | N26: =N25 -> 139.5 | O26: Precision damage DPS; requires a kill before reload, buff lasts for ~8 seconds
A27: cata, far range | B27: Cerberus+1 | C27: =(G27)/(H27 * 1/J27 * 60/1) -> 576 | D27: N/A | F27: inf | G27: =M27 * H27 -> 2976 | H27: 31 | I27: inf | J27: =J21 -> 360 | K27: 1.12 | L27: inf | M27: =M23*1.5 -> 96 | N27: =N23*1.5 -> 168 | O27: Body damage DPS; requires a kill before reload, buff lasts for ~8 seconds
A28: cata, far range | B28: Cerberus+1 | C28: =(G28)/(H28 * 1/J28 * 60/1) -> 1008 | D28: N/A | F28: inf | G28: =N28 * H28 -> 5208 | H28: 31 | I28: inf | J28: =J21 -> 360 | K28: 1.12 | L28: inf | M28: =M27 -> 96 | N28: =N27 -> 168 | O28: Precision damage DPS; requires a kill before reload, buff lasts for ~8 seconds
A29: SMGs | B29: Precision | C29: =(G29)/(H29 * 1/J29 * 60/1) -> 370 | D29: =(G29)/((H29-1) * 1/J29 * 60/1 + K29) -> 271.39364 | F29: inf | G29: =N29 * H29 -> 1110 | H29: 30 | I29: inf | J29: 600 | K29: 1.19 | L29: inf | M29: 23 | N29: 37
B30: Aggressive | C30: =(G30)/(H30 * 1/J30 * 60/1) -> 396 | D30: =(G30)/((H30-1) * 1/J30 * 60/1 + K30) -> 274.49168 | F30: inf | G30: =N30 * H30 -> 990 | H30: 30 | I30: inf | J30: 720 | K30: 1.19 | L30: inf | M30: 19 | N30: 33
B31: Adaptive | C31: =(G31)/(H31 * 1/J31 * 60/1) -> 390 | D31: =(G31)/((H31-1) * 1/J31 * 60/1 + K31) -> 276.40449 | F31: inf | G31: =N31 * H31 -> 1066 | H31: 41 | I31: inf | J31: 900 | K31: 1.19 | L31: inf | M31: 16 | N31: 26
B32: Lightweight | C32: =(G32)/(H32 * 1/J32 * 60/1) -> 420 | D32: =(G32)/((H32-1) * 1/J32 * 60/1 + K32) -> 295.51451 | F32: inf | G32: =N32 * H32 -> 1120 | H32: 40 | I32: inf | J32: 900 | K32: 1.19 | L32: inf | M32: 15 | N32: 28
B33: Riskrunner | C33: =(G33)/(H33 * 1/J33 * 60/1) -> 420 | D33: =(G33)/((H33-1) * 1/J33 * 60/1 + K33) -> 309.1621 | F33: inf | G33: =N33 * H33 -> 1316 | H33: 47 | I33: inf | J33: 900 | K33: 1.19 | L33: inf | M33: 17 | N33: 28
A34: Arc Conductor | B34: Riskrunner | C34: =(G34)/(H34 * 1/J34 * 60/1) -> 462 | D34: =(G34)/((H34-1) * 1/J34 * 60/1 + K34) -> 340.07831 | F34: inf | G34: =N34 * H34 -> 1447.6 | H34: =H33 -> 47 | I34: inf | J34: 900 | K34: 1.19 | L34: inf | M34: =M33*1.1 -> 18.7 | N34: =N33*1.1 -> 30.8
A35: Grounded | B35: The Manticore | C35: =(G35)/(H35 * 1/J35 * 60/1) -> 435 | D35: =(G35)/((H35-1) * 1/J35 * 60/1 + K35) -> 310.4503 | F35: inf | G35: =N35 * H35 -> 1218 | H35: 42 | I35: inf | J35: 900 | K35: 1.19 | L35: inf | M35: 16 | N35: 29
A36: Airborne | B36: The Manticore | C36: =(67*N36 * (1 + 2))/(67*2 * 1/J36 * 60/1 + 0.5) -> 617.91519 | D36: =(67*N36 * (1 + 2))/((67-1)*1/J36*60/1 + E36*2 + 0.5 + (67-1)*1/J36*60/1 + K36) -> 555.67207 | F36: inf | G36: =N36 * H36 -> 1218 | H36: =H35 -> 42 | I36: inf | J36: 900 | K36: =K35 -> 1.19 | L36: inf | M36: =M35 -> 16 | N36: =N35 -> 29 | O36: 67 shots to fill (37 + reload + 30 + reload) > jump > 67 airborne shots
A37: Ride the Bull average | B37: Huckleberry | C37: =(G37)/(H37 * 1/J37 * 60/1) + ('Weapon Specifics'!$D$66*3)/(3+0.285+2) -> 567.3536 | D37: =(G37 + 'Weapon Specifics'!$D$66*3)/((H37-1) * 1/J37 * 60/1 + K37) -> 464.63688 | F37: inf | G37: =N37 * H37 -> 1428 | H37: 42 | I37: inf | J37: =H37/(10 * 1/750 + 10 * 1/810 + (H37-20) * 1/900) -> 837.93103 | K37: 1.19 | L37: inf | M37: 20 | N37: 34
A38: Ride the Bullx2 + Rmpgx3 | B38: Huckleberry | C38: =(G38 + 'Weapon Specifics'!$D$66*3)/(H38 * 1/J38 * 60/1) -> 1021.2429 | D38: N/A | F38: inf | G38: =N38 * H38 -> 2370.48 | H38: =H37 -> 42 | I38: inf | J38: 900 | K38: N/A | L38: inf | M38: =M37*1.66 -> 33.2 | N38: =N37*1.66 -> 56.44 | O38: This assumes 3 kills have been made
B39: Tarrabah | C39: =(G39)/(H39 * 1/J39 * 60/1) -> 408 | D39: =(G39)/((H39-1) * 1/J39 * 60/1 + K39) -> 295.77465 | F39: inf | G39: =N39 * H39 -> 1190 | H39: 35 | I39: inf | J39: 720 | K39: 1.19 | L39: inf | M39: =M37 -> 20 | N39: =N37 -> 34
A40: Ravenous Beast | B40: Tarrabah | C40: =(G40)/(H40 * 1/J40 * 60/1) -> 855 | D40: =(G40)/((H40-1) * 1/J40 * 60/1 + K40) -> 619.82187 | F40: inf | G40: =N40 * H40 -> 1995 | H40: =H39 -> 35 | I40: inf | J40: 900 | K40: =K39*0.8 -> 0.952 | L40: inf | M40: 56 | N40: 57
B41: Barrow Dyad | C41: =(G41)/(H41 * 1/J41 * 60/1) -> 396 | D41: =(G41)/((H41-1) * 1/J41 * 60/1 + K41) -> 287.7907 | F41: inf | G41: =N41 * H41 -> 1155 | H41: 35 | I41: inf | J41: 720 | K41: 1.18 | L41: inf | M41: =M30 -> 19 | N41: =N30 -> 33
B42: Osteo Striga | C42: =(G42)/(H42 * 1/J42 * 60/1) -> 420 | D42: =(G42)/((H42-1) * 1/J42 * 60/1 + K42) -> 305.26316 | F42: inf | G42: =N42 * H42 -> 1218 | H42: 29 | I42: inf | J42: 600 | K42: 1.19 | L42: inf | M42: 27 | N42: 42
A43: w/ poison DoT | B43: Osteo Striga | C43: =(G43 + ('Weapon Specifics'!D44))/(H43 * 1/J43 * 60/1) -> 521.03448 | D43: =(G43 + ('Weapon Specifics'!D44))/((H43-1) * 1/J43 * 60/1 + K43) -> 378.69674 | F43: inf | G43: =N43 * H43 -> 1218 | H43: =H42 -> 29 | I43: inf | J43: 600 | K43: 1.19 | L43: inf | M43: =M42 -> 27 | N43: =N42 -> 42 | O43: Poison DoT ramp-up is reset every re-proc,
A44: only poison DoT | B44: Osteo Striga | C44: =('Weapon Specifics'!D45)/10 -> 135.4 | D44: N/A | F44: inf | G44: ='Weapon Specifics'!D25 -> 470 | H44: N/A | I44: N/A | J44: N/A | K44: N/A | L44: N/A | M44: N/A | N44: N/A | O44: Poison DoT ramps up over time
A45: Pulse Rifles | B45: Rapid-Fire | C45: =(G45)/(H45 * 1/J45 * 60/1) -> 261 | D45: =(G45)/((H45-1) * 1/J45 * 60/1 + K45) -> 226.33329 | F45: inf | G45: =N45 * H45 -> 1392 | H45: 48 | I45: inf | J45: 540 | K45: =1.16*0.8 -> 0.928 | L45: inf | M45: 16 | N45: 29
B46: Lightweight | C46: =(G46)/(H46 * 1/J46 * 60/1) -> 240 | D46: =(G46)/((H46-1) * 1/J46 * 60/1 + K46) -> 206.82226 | F46: inf | G46: =N46 * H46 -> 1536 | H46: 48 | I46: inf | J46: 450 | K46: 1.16 | L46: inf | M46: 20 | N46: 32
B47: Legacy PR-55 | C47: =(G47)/(H47 * 1/J47 * 60/1) -> 240 | D47: =(G47)/((H47-1) * 1/J47 * 60/1 + K47) -> 204.93359 | F47: inf | G47: =N47 * H47 -> 1440 | H47: 45 | I47: inf | J47: 450 | K47: 1.16 | L47: inf | M47: =M46 -> 20 | N47: =N46 -> 32 | O47: Exclusive frame to BXR-55 Battler
B48: Adaptive | C48: =(G48)/(H48 * 1/J48 * 60/1) -> 240.5 | D48: =(G48)/((H48-1) * 1/J48 * 60/1 + K48) -> 211.66117 | F48: inf | G48: =N48 * H48 -> 1776 | H48: 48 | I48: inf | J48: 390 | K48: 1.16 | L48: inf | M48: 23 | N48: 37
B49: High-Impact | C49: =(G49)/(H49 * 1/J49 * 60/1) -> 221 | D49: =(G49)/((H49-1) * 1/J49 * 60/1 + K49) -> 197.11737 | F49: inf | G49: =N49 * H49 -> 1794 | H49: 46 | I49: inf | J49: 340 | K49: 1.16 | L49: inf | M49: 22 | N49: 39
B50: Aggressive Burst | C50: =(G50)/(H50 * 1/J50 * 60/1) -> 232.5 | D50: =(G50)/((H50-1) * 1/J50 * 60/1 + K50) -> 207.53138 | F50: inf | G50: =N50 * H50 -> 1984 | H50: 64 | I50: inf | J50: 450 | K50: 1.16 | L50: inf | M50: 16 | N50: 31
B51: Heavy Burst | C51: =(G51)/(H51 * 1/J51 * 60/1) -> 270 | D51: =(G51)/((H51-1) * 1/J51 * 60/1 + K51) -> 229.69601 | F51: inf | G51: =N51 * H51 -> 1500 | H51: 30 | I51: inf | J51: 324 | K51: 1.16 | L51: inf | M51: 27 | N51: 50
B52: Vigilance Wing | C52: =(G52)/(H52 * 1/J52 * 60/1) -> 309.16667 | D52: =(G52)/((H52-1) * 1/J52 * 60/1 + K52) -> 260.91482 | F52: inf | G52: =N52 * H52 -> 1750 | H52: 50 | I52: inf | J52: 530 | K52: 1.16 | L52: inf | M52: 22 | N52: 35
B53: Bad Juju | C53: =(G53)/(H53 * 1/J53 * 60/1) -> 255 | D53: =(G53)/((H53-1) * 1/J53 * 60/1 + K53) -> 204.26357 | F53: inf | G53: =N53 * H53 -> 1054 | H53: 31 | I53: inf | J53: 450 | K53: 1.16 | L53: inf | M53: 21 | N53: 34
A54: String of Curses x5 | B54: Bad Juju | C54: =(G54)/(H54 * 1/J54 * 60/1) -> 510 | D54: N/A | F54: inf | G54: =N54 * H54 -> 2108 | H54: 31 | I54: inf | J54: 450 | K54: 1.16 | L54: inf | M54: =M53*2 -> 42 | N54: =N53*2 -> 68
B55: Outbreak Perfected | C55: =(G55)/(H55 * 1/J55 * 60/1) + 'Weapon Specifics'!D46*4/(12*1/J55*60/1) -> 355 | D55: =(G55)/((H55-1) * 1/J55 * 60/1 + K55) + (FLOOR(H55/12,1) * 'Weapon Specifics'!D46*4)/((H55-1)*1/J55*60/1 + K55) -> 292.44851 | F55: inf | G55: =N55 * H55 -> 1224 | H55: 36 | I55: inf | J55: 450 | K55: 1.16 | L55: inf | M55: =M53 -> 21 | N55: =N53 -> 34 | O55: Collections roll
A56: x5 nanites | B56: Outbreak Perfected | C56: =(G56)/(H56 * 1/J56 * 60/1) + 'Weapon Specifics'!D46*4/(12*1/J55*60/1) -> 737.5 | D56: =(G56)/((H56-1) * 1/J56 * 60/1 + K56) + (FLOOR(H56/12,1) * 'Weapon Specifics'!D46*4)/((H56-1)*1/J56*60/1 + K56) -> 607.55149 | F56: inf | G56: =N56 * H56 -> 3060 | H56: =H55 -> 36 | I56: inf | J56: 450 | K56: 1.16 | L56: inf | M56: =M55*2.5 -> 52.5 | N56: =N55*2.5 -> 85 | O56: Collections roll; Assumes 4 nanites spawn every 12 shots.
A57: max nanites (x100) | B57: Outbreak Perfected | C57: =(G57)/(H57 * 1/J57 * 60/1) + 'Weapon Specifics'!D46*4/(12*1/J55*60/1) -> 1502.5 | D57: =(G57)/((H57-1) * 1/J57 * 60/1 + K57) + (FLOOR(H57/12,1) * 'Weapon Specifics'!D46*4)/((H57-1)*1/J57*60/1 + K57) -> 1237.7574 | F57: inf | G57: =N57 * H57 -> 6732 | H57: =H55 -> 36 | I57: inf | J57: =J55 -> 450 | K57: =K55 -> 1.16 | L57: inf | M57: =M55*5.5 -> 115.5 | N57: =N55*5.5 -> 187 | O57: Collections roll; Assumes 4 nanites spawn every 12 shots.
B58: Outbreak Perfected | C58: =(G58)/(H58 * 1/J58 * 60/1) + 'Weapon Specifics'!D46*4/(12*1/J58*60/1) -> 355 | D58: =(G58)/((H58-1) * 1/J58 * 60/1 + K58) + (FLOOR(H58/12,1) * 'Weapon Specifics'!D46*4)/((H58-1)*1/J58*60/1 + K58) -> 305.71676 | F58: inf | G58: =N58 * H58 -> 1224 | H58: 36 | I58: inf | J58: 450 | K58: =$K$55*0.92*0.85 -> 0.90712 | L58: inf | M58: =M55 -> 21 | N58: =N55 -> 34 | O58: Rapid Hit + Alloy Magazine
A59: x5 nanites | B59: Outbreak Perfected | C59: =(G59)/(H59 * 1/J59 * 60/1) + 'Weapon Specifics'!D46*4/(12*1/J58*60/1) -> 737.5 | D59: =(G59)/((H59-1) * 1/J59 * 60/1 + K59) + (FLOOR(H59/12,1) * 'Weapon Specifics'!D46*4)/((H59-1)*1/J59*60/1 + K59) -> 635.1158 | F59: inf | G59: =N59 * H59 -> 3060 | H59: =H58 -> 36 | I59: inf | J59: 450 | K59: =K58 -> 0.90712 | L59: inf | M59: =M58*2.5 -> 52.5 | N59: =N58*2.5 -> 85 | O59: Rapid Hit + Alloy Magazine; Assumes 4 nanites spawn every 12 shots.
A60: max nanites (x100) | B60: Outbreak Perfected | C60: =(G60)/(H60 * 1/J60 * 60/1) + 'Weapon Specifics'!D46*4/(12*1/J59*60/1) -> 1502.5 | D60: =(G60)/((H60-1) * 1/J60 * 60/1 + K60) + (FLOOR(H60/12,1) * 'Weapon Specifics'!D46*4)/((H60-1)*1/J60*60/1 + K60) -> 1293.9139 | F60: inf | G60: =N60 * H60 -> 6732 | H60: =H58 -> 36 | I60: inf | J60: =J58 -> 450 | K60: =K58 -> 0.90712 | L60: inf | M60: =M58*5.5 -> 115.5 | N60: =N58*5.5 -> 187 | O60: Rapid Hit + Alloy Magazine; Assumes 4 nanites spawn every 12 shots.
B61: Outbreak Perfected | C61: =(G61)/(H61 * 1/J61 * 60/1) + 'Weapon Specifics'!D46*4/(12*1/J60*60/1) -> 355 | D61: =(G61)/((H61-1) * 1/J61 * 60/1 + K61) + (FLOOR(H61/12,1) * 'Weapon Specifics'!D46*4)/((H61-1)*1/J61*60/1 + K61) -> 333.59436 | F61: inf | G61: =N61 * H61 -> 4080 | H61: =45+33+24+18 -> 120 | I61: inf | J61: 450 | K61: 1.16 | L61: inf | M61: =M55 -> 21 | N61: =N55 -> 34 | O61: Rewind Rounds + Extended Magazine
A62: x5 nanites | B62: Outbreak Perfected | C62: =(G62)/(H62 * 1/J62 * 60/1) + 'Weapon Specifics'!D46*4/(12*1/J61*60/1) -> 737.5 | D62: =(G62)/((H62-1) * 1/J62 * 60/1 + K62) + (FLOOR(H62/12,1) * 'Weapon Specifics'!D46*4)/((H62-1)*1/J62*60/1 + K62) -> 693.03054 | F62: inf | G62: =N62 * H62 -> 10200 | H62: =H61 -> 120 | I62: inf | J62: 450 | K62: 1.16 | L62: inf | M62: =M61*2.5 -> 52.5 | N62: =N61*2.5 -> 85 | O62: Rewind Rounds + Extended Magazine; Assumes 4 nanites spawn every 12 shots.
A63: max nanites (x100) | B63: Outbreak Perfected | C63: =(G63)/(H63 * 1/J63 * 60/1) + 'Weapon Specifics'!D46*4/(12*1/J62*60/1) -> 1502.5 | D63: =(G63)/((H63-1) * 1/J63 * 60/1 + K63) + (FLOOR(H63/12,1) * 'Weapon Specifics'!D46*4)/((H63-1)*1/J63*60/1 + K63) -> 1411.9029 | F63: inf | G63: =N63 * H63 -> 22440 | H63: =H61 -> 120 | I63: inf | J63: =J61 -> 450 | K63: =K61 -> 1.16 | L63: inf | M63: =M61*5.5 -> 115.5 | N63: =N61*5.5 -> 187 | O63: Rewind Rounds + Extended Magazine; Assumes 4 nanites spawn every 12 shots.
B64: Collective Obligation | C64: =(G64)/(H64 * 1/J64 * 60/1) -> 253.5 | D64: =(G64)/((H64-1) * 1/J64 * 60/1 + K64) -> 214.5275 | F64: inf | G64: =N64 * H64 -> 1404 | H64: 36 | I64: inf | J64: 390 | K64: 1.16 | L64: inf | M64: 24 | N64: 39
B65: Red Death Reformed | C65: =(G65)/(H65 * 1/J65 * 60/1) -> 232.33333 | D65: =(G65)/((H65-1) * 1/J65 * 60/1 + K65) -> 197.18974 | F65: inf | G65: =N65 * H65 -> 1230 | H65: 30 | I65: inf | J65: 340 | K65: 1.12 | L65: inf | M65: 23 | N65: 41
A66: 4-burst | B66: Revision Zero | C66: =(G66)/(H66 * 1/J66 * 60/1) -> 247.5 | D66: =(G66)/((H66-1) * 1/J66 * 60/1 + K66) -> 215.57789 | F66: inf | G66: =N66 * H66 -> 1716 | H66: 52 | I66: inf | J66: =J50 -> 450 | K66: 1.16 | L66: inf | M66: 17 | N66: 33
A67: 2-burst | B67: Revision Zero | C67: =(G67)/(H67 * 1/J67 * 60/1) -> 345.6 | D67: =(G67)/((H67-1) * 1/J67 * 60/1 + K67) -> 287.41044 | F67: inf | G67: =N67 * H67 -> 1664 | H67: 26 | I67: inf | J67: =J51 -> 324 | K67: =K66 -> 1.16 | L67: inf | M67: 35 | N67: 64
A68: 4-burst, mix, FTTC | B68: Revision Zero | C68: =D68 -> 657.44681 | D68: =(48*N68 + fourthTimesTheCharm(4) * ('Weapon Specifics'!D52 + 'Weapon Specifics'!D53))/(48 * 1/J68 * 60/1 + 0.6 + fourthTimesTheCharm(4) * 1/72 * 60/1 + K68) -> 657.44681 | F68: inf | G68: =N68 * H68 -> 3366 | H68: =fourthTimesTheCharm(H66) -> 102 | I68: inf | J68: =J66 -> 450 | K68: =K66 -> 1.16 | L68: inf | M68: =M66 -> 17 | N68: =N66 -> 33 | O68: Expend 48 rounds (get 4x Hunter's Trace) > Hunter's Trace
A69: 2-burst, mix, FTTC | B69: Revision Zero | C69: =D69 -> 647.96933 | D69: =(48*N69 + fourthTimesTheCharm(4) * ('Weapon Specifics'!D52 + 'Weapon Specifics'!D53))/(48 * 1/J69 * 60/1 + 0.6 + fourthTimesTheCharm(4) * 1/72 * 60/1 + K69) -> 647.96933 | F69: inf | G69: =N69 * H69 -> 3200 | H69: =fourthTimesTheCharm(H67) -> 50 | I69: inf | J69: =J67 -> 324 | K69: =K66 -> 1.16 | L69: inf | M69: =M67 -> 35 | N69: =N67 -> 64 | O69: Expend 48 rounds (get 4x Hunter's Trace) > Hunter's Trace
A70: w/ Time-Slip Portal,cata | B70: No Time To Explain | C70: =N70*J70*1/60 + ('Weapon Specifics'!D42 * 3)/(3 * 1/340 * 60/1 + 0.85) -> 288.87918 | D70: =C70 -> 288.87918 | F70: inf | G70: inf | H70: 24 | I70: inf | J70: 340 | K70: 1.16 | L70: inf | M70: 23 | N70: 41 | O70: This assumes precisions-only.
B71: Graviton Lance | C71: =(G71)/(H71 * 1/J71 * 60/1) -> 352.5 | D71: =(G71)/((H71-1) * 1/J71 * 60/1 + K71) -> 303.87931 | F71: inf | G71: =N71 * H71 -> 2115 | H71: 30 | I71: inf | J71: 300 | K71: 1.16 | L71: inf | M71: =(32+44)/2 -> 38 | N71: =(60+81)/2 -> 70.5
A72: Scout Rifles | B72: Rapid-Fire | C72: =(G72)/(H72 * 1/J72 * 60/1) -> 260 | D72: =(G72)/((H72-1) * 1/J72 * 60/1 + K72) -> 223.18874 | F72: inf | G72: =N72 * H72 -> 1200 | H72: 20 | I72: inf | J72: 260 | K72: =1.24*0.8 -> 0.992 | L72: inf | M72: 31 | N72: 60
B73: Lightweight | C73: =(G73)/(H73 * 1/J73 * 60/1) -> 236.66667 | D73: =(G73)/((H73-1) * 1/J73 * 60/1 + K73) -> 204.61095 | F73: inf | G73: =N73 * H73 -> 1420 | H73: 20 | I73: inf | J73: 200 | K73: 1.24 | L73: inf | M73: 42 | N73: 71
B74: Precision | C74: =(G74)/(H74 * 1/J74 * 60/1) -> 228 | D74: =(G74)/((H74-1) * 1/J74 * 60/1 + K74) -> 200.70423 | F74: inf | G74: =N74 * H74 -> 1520 | H74: 20 | I74: inf | J74: 180 | K74: 1.24 | L74: inf | M74: 42 | N74: 76
B75: High-Impact | C75: =(G75)/(H75 * 1/J75 * 60/1) -> 230 | D75: =(G75)/((H75-1) * 1/J75 * 60/1 + K75) -> 208.1448 | F75: inf | G75: =N75 * H75 -> 1840 | H75: 20 | I75: inf | J75: 150 | K75: 1.24 | L75: inf | M75: 46 | N75: 92
B76: Aggressive | C76: =(G76)/(H76 * 1/J76 * 60/1) -> 262 | D76: =(G76)/((H76-1) * 1/J76 * 60/1 + 0.58+K76*(H76/2-1)) -> 194.07407 | F76: inf | G76: =N76 * H76 -> 2620 | H76: 20 | I76: inf | J76: 120 | K76: =0.38 -> 0.38 | L76: inf | M76: 77 | N76: 131
B77: Symmetry | C77: =(G77)/(H77 * 1/J77 * 60/1) -> 273 | D77: =(G77)/((H77-1) * 1/J77 * 60/1 + K77) -> 234.34817 | F77: inf | G77: =N77 * H77 -> 1260 | H77: 20 | I77: inf | J77: 260 | K77: =1.24*0.8 -> 0.992 | L77: inf | M77: 33 | N77: 63
A78: x1 Revolution | B78: Symmetry | C78: =M78*J78*1/60 -> 70.617284 | D78: =C78 -> 70.617284 | F78: inf | G78: inf | H78: 20 | I78: inf | J78: =J77/2.7 -> 96.296296 | K78: =1.24*0.8 -> 0.992 | L78: inf | M78: 44 | N78: N/A | O78: spam 1x revolution
A79: x5 Revolution mix | B79: Symmetry | C79: =(G79)/(((5-1)*1/J79*60 + 0.6 + (5-1)*1/J78*60 + 0.6)*4) -> 185.25 | D79: =(G79)/(((5-1)*1/J79*60 + 0.6 + (5-1)*1/J78*60 + 0.6)*4 + K79) -> 175.80349 | F79: inf | G79: =(5*M79 + 5*N77)*4 -> 3420 | H79: 20 | I79: inf | J79: 260 | K79: =1.24*0.8 -> 0.992 | L79: inf | M79: 108 | N79: N/A | O79: build stacks -> swap firing modes > expend stacks > swap firing modes
A80: x10 Revolution mix | B80: Symmetry | C80: =(G80)/(((10-1)*1/J80*60 + 0.6 + (10-1)*1/J78*60 + 0.6)*2) -> 265.62771 | D80: =(G80)/(((10-1)*1/J80*60 + 0.6 + (10-1)*1/J78*60 + 0.6)*2 + K80) -> 251.58264 | F80: inf | G80: =(10*M80 + 10*N77)*2 -> 4720 | H80: 20 | I80: inf | J80: 260 | K80: =1.24*0.8 -> 0.992 | L80: inf | M80: 173 | N80: N/A | O80: build stacks -> swap firing modes > expend stacks > swap firing modes
A81: x15 Revolution mix | B81: Symmetry | C81: =(G81)/(((10-1)*1/J81*60 + 0.6 + (10-1)*1/J78*60 + 0.6)*2) -> 338.78788 | D81: =(G81)/(((10-1)*1/J81*60 + 0.6 + (10-1)*1/J78*60 + 0.6)*2 + K81) -> 320.87447 | F81: inf | G81: =(10*M81 + 10*N77)*2 -> 6020 | H81: 20 | I81: inf | J81: 260 | K81: =1.24*0.8 -> 0.992 | L81: inf | M81: 238 | N81: N/A | O81: build stacks -> swap firing modes > expend stacks > swap firing modes
A82: x20 Revolution mix | B82: Symmetry | C82: =(G82)/(((20-1)*1/J82*60 + 0.6 + (20-1)*1/J78*60 + 0.6)) -> 418.98455 | D82: =(G82)/(((20-1)*1/J82*60 + 0.6 + (20-1)*1/J78*60 + 0.6) + K82) -> 396.41431 | F82: inf | G82: =20*M82 + 20*N77 -> 7300 | H82: 20 | I82: inf | J82: 260 | K82: =1.24*0.8 -> 0.992 | L82: inf | M82: 302 | N82: N/A | O82: build stacks -> swap firing modes > expend stacks > swap firing modes
A83: Touch of Malice (ToM) | B83: Touch of Malice | C83: =N83*J83/60 -> 598 | D83: =C83 -> 598 | F83: inf | G83: inf | H83: 11 | I83: inf | J83: 260 | K83: 1.24 | L83: inf | M83: 71 | N83: 138 | O83: This assumes always at 1 round
A84: ToM+CwB | B84: Touch of Malice | C84: =(N84*FLOOR(J84 * 1/60 * (3.5-(0.53)),1) + 'Weapon Specifics'!D77+'Weapon Specifics'!D78) / (FLOOR(J84 * 1/60 * (3.5-(0.53)),1)*1/J84*60/1 + 1.1+0.53) -> 672.61759 | D84: =C84 -> 672.61759 | F84: inf | G84: inf | H84: 11 | I84: inf | J84: 260 | K84: 1.24 | L84: inf | M84: =M83*1.5 -> 106.5 | N84: =N83*1.5 -> 207 | O84: This assumes always at 1 round; fire 12 rounds > re-blight, 100% CwB uptime
B85: Wicked Implement | C85: =(3*N85 + 6*'Weapon Specifics'!D89 + 'Elemental Effects'!$E$9 + 1*N85)/(10 * 1/J85 * 60/1) -> 421.24333 | D85: =(G85)/((H85-1) * 1/J85 * 60/1 + K85) -> 326.7779 | F85: inf | G85: =(3*N85 + 6*'Weapon Specifics'!$D$33 + 'Elemental Effects'!$E$9 + 1*N85)*FLOOR(H85/10,1) -> 1838 | H85: 20 | I85: inf | J85: =$J$72 -> 260 | K85: 1.24 | L85: inf | M85: =M77 -> 33 | N85: =N77 -> 63 | O85: Assumes Creeping Attrition from beginning shot, solo setting
A86: Whisper of Rending | B86: Wicked Implement | C86: =(3*N86 + 4*'Weapon Specifics'!$D$91 + 'Elemental Effects'!$E$9 + 1*N86)/(8 * 1/J86 * 60/1) -> 526.55417 | D86: =(G86)/((H86-1) * 1/J86 * 60/1 + K86) -> 365.18053 | F86: inf | G86: =(3*N86 + 4*'Weapon Specifics'!$D$35 + 'Elemental Effects'!$E$9 + 1*N86)*FLOOR(H86/8,1) + 3*N86 + 1*'Weapon Specifics'!$D$35 -> 2054 | H86: =H85 -> 20 | I86: inf | J86: =$J$72 -> 260 | K86: =K85 -> 1.24 | L86: inf | M86: =M85 -> 33 | N86: =N85 -> 63 | O86: Assumes Creeping Attrition from beginning shot, solo setting
B87: Wicked Implement | C87: =(3*N87 + 'Elemental Effects'!$E$9 + N87)/(4 * 1/J87 * 60/1) -> 664.08333 | D87: =(G87)/((H87-1) * 1/J87 * 60/1 + K87) -> 544.92615 | F87: inf | G87: =(3*N87 + 'Elemental Effects'!$E$9 + 1*N87)*FLOOR(H87/4,1) -> 3065 | H87: =H86 -> 20 | I87: inf | J87: =$J$72 -> 260 | K87: 1.24 | L87: inf | M87: =M85 -> 33 | N87: =N85 -> 63 | O87: Assumes Creeping Attrition from beginning shot, group setting
A88: Whisper of Rending | B88: Wicked Implement | C88: =(3*N88 + 'Elemental Effects'!$E$9 + N88)/(4 * 1/J88 * 60/1) -> 664.08333 | D88: =(G88)/((H88-1) * 1/J88 * 60/1 + K88) -> 544.92615 | F88: inf | G88: =(3*N88 + 'Elemental Effects'!$E$9 + 1*N88)*FLOOR(H88/4,1) -> 3065 | H88: =H87 -> 20 | I88: inf | J88: =$J$72 -> 260 | K88: =K87 -> 1.24 | L88: inf | M88: =M87 -> 33 | N88: =N87 -> 63 | O88: Assumes Creeping Attrition from beginning shot, group setting
B89: MIDA Multi-Tool | C89: =(G89)/(H89 * 1/J89 * 60/1) -> 246.66667 | D89: =(G89)/((H89-1) * 1/J89 * 60/1 + K89) -> 206.27178 | F89: inf | G89: =N89 * H89 -> 1184 | H89: 16 | I89: inf | J89: 200 | K89: 1.24 | L89: inf | M89: 44 | N89: 74
A90: Base | B90: Third Iteration | C90: =(G90)/(H90 * 1/J90 * 60/1) -> 376.66667 | D90: =(G90)/((H90-1) * 1/J90 * 60/1 + K90) -> 228.57143 | F90: inf | G90: =N90 * H90 -> 1808 | H90: 16 | I90: inf | J90: 200 | K90: =0.65+0.92*3 -> 3.41 | L90: inf | M90: =17+17+17+16 -> 67 | N90: 113 | O90: Only base rounds
A91: Base, buffed | B91: Third Iteration | C91: =(G91)/(H91 * 1/J91 * 60/1) -> 733.33333 | D91: =(G91)/((H91-1) * 1/J91 * 60/1 + K91) -> 445.00632 | F91: inf | G91: =N91 * H91 -> 3520 | H91: 16 | I91: inf | J91: 200 | K91: =$K$90 -> 3.41 | L91: inf | M91: =32+33+33+33 -> 131 | N91: 220 | O91: Only base rounds, buffed by Amalgamation Rounds
A92: Amalgamation Round | B92: Third Iteration | C92: =(G92)/(H92 * 1/J92 * 60/1) -> 495.65217 | D92: =((H92-1)*N92 + $N$91)/((H92-1) * 1/J92 * 60 + K92) -> 424.49177 | F92: inf | G92: =N92 * H92 -> 9120 | H92: 16 | I92: inf | J92: =1/1.15 * 60 -> 52.173913 | K92: =$K$90 -> 3.41 | L92: inf | M92: =84+84+84+85 -> 337 | N92: 570 | O92: Only Amalgamation rounds, buffed by Amalgamation Rounds
A93: Base | B93: Dead Man's Tale | C93: =(G93)/(H93 * 1/J93 * 60/1) -> 316 | D93: =(G93)/((H93-1) * 1/J93 * 60/1 + 0.58+K93*(CEILING(H93/2,1)-1)) -> 243.61233 | F93: inf | G93: =N93 * H93 -> 2212 | H93: 14 | I93: inf | J93: =120 -> 120 | K93: =10/30 -> 0.33333333 | L93: inf | M93: 93 | N93: 158
A94: cata, x5 Cranial Spike | B94: Dead Man's Tale | C94: =(G94)/(H94 * 1/J94 * 60/1) -> 532 | D94: =(G94)/((H94-1) * 1/J94 * 60/1 + 0.58+K94*(ceiling(H94/7,1)-1-1)) -> 518.90386 | F94: inf | G94: =N94 * H94 -> 3192 | H94: 14 | I94: inf | J94: =140 -> 140 | K94: =$K$93 * 0.86 -> 0.28666667 | L94: inf | M94: 135 | N94: 228 | O94: Hip-fire, reload full magazine
A95: cata, x5 Cranial Spike | B95: Dead Man's Tale | C95: =(G95)/(H95 * 1/J95 * 60/1) -> 532 | D95: =(G95)/((H95-1) * 1/J95 * 60/1 + 0.58) -> 506.43699 | F95: inf | G95: =N95 * H95 -> 1596 | H95: 7 | I95: inf | J95: =140 -> 140 | K95: =$K$93 * 0.86 -> 0.28666667 | L95: inf | M95: =$M$94 -> 135 | N95: =$N$94 -> 228 | O95: Hip-fire, one reload on empty
A96: cata, x5 Cranial Spike, RH | B96: Dead Man's Tale | C96: =(G96)/(H96 * 1/J96 * 60/1) -> 532 | D96: =(G96)/((H96-1) * 1/J96 * 60/1 + 0.58+K96*(CEILING(H96/7,1)-1)) -> 497.57123 | F96: inf | G96: =N96 * H96 -> 3192 | H96: 14 | I96: inf | J96: =140 -> 140 | K96: =$K$93 * 0.86 * 0.92 -> 0.26373333 | L96: inf | M96: =$M$94 -> 135 | N96: =$N$94 -> 228 | O96: Hip-fire
A97: cata, x5 Cranial Spike, FTTC | B97: Dead Man's Tale | C97: =(G97)/(H97 * 1/J97 * 60/1) -> 532 | D97: =(G97)/((H97-1) * 1/J97 * 60/1 + 0.58+K97*(ceiling($H$94/7,1)-1)) -> 511.875 | F97: inf | G97: =N97 * H97 -> 5928 | H97: =fourthTimesTheCharm($H$93) -> 26 | I97: inf | J97: =140 -> 140 | K97: =$K$93 * 0.86 -> 0.28666667 | L97: inf | M97: =$M$94 -> 135 | N97: =$N$94 -> 228 | O97: Hip-fire, reload full magazine
A98: cata, x5 Cranial Spike, FTTC | B98: Dead Man's Tale | C98: =(G98)/(H98 * 1/J98 * 60/1) -> 532 | D98: =(G98)/((H98-1) * 1/J98 * 60/1 + 0.58) -> 506.43699 | F98: inf | G98: =N98 * H98 -> 1596 | H98: 7 | I98: inf | J98: =140 -> 140 | K98: =$K$93 * 0.86 -> 0.28666667 | L98: inf | M98: =$M$94 -> 135 | N98: =$N$94 -> 228 | O98: Hip-fire, one reload on empty
B99: Polaris Lance | C99: =N99*J99*1/60 + ('Elemental Effects'!$E$4 + 'Weapon Specifics'!$D$47*3)/(15 * 1/J99 * 60/1) + 'Elemental Effects'!$E$13 -> 435.65476 | D99: =C99 -> 435.65476 | F99: inf | G99: inf | H99: 14 | I99: inf | J99: 150 | K99: 1.24 | L99: inf | M99: 49 | N99: 97
A100: Ember of Ashes | B100: Polaris Lance | C100: =N100*J100*1/60 + ('Elemental Effects'!$E$4 + 'Weapon Specifics'!$D$47*3)/(10 * 1/J100 * 60/1) + 'Elemental Effects'!$E$13 -> 521.07143 | D100: =C100 -> 521.07143 | F100: inf | G100: inf | H100: 14 | I100: inf | J100: 150 | K100: 1.24 | L100: inf | M100: =M99 -> 49 | N100: =N99 -> 97 | O100: This assumes precision-only. Factors in scorch; considers ignitions
...

Sheet Specials
A1: Note: all weapons assume Backup Mag whenever applicable; All weapon damage (except exotics) is normalized. Want to contribute? Have questions, comments, or concerns? See Home page contact information.
B2: Frame/Weapon | C2: 1-Mag Burst or "True" DPS | D2: Sustained DPS | F2: Theoretical Total Damage | G2: 1-Mag Damage | H2: Magazine Capacity | I2: Reserves + Magazine | J2: Fire rate (rpm) | K2: Reload Speed (s) | L2: Time to Empty (s) | M2: Body Damage | N2: Precision Damage
A3: Sniper Rifles | B3: Rapid-Fire | C3: =(G3)/(H3 * 1/J3 * 60/1) -> 1050 | D3: =(G3)/((H3-1) * 1/J3 * 60/1 + K3) -> 758.04455 | F3: =I3*N3 -> 13950 | G3: =N3 * H3 -> 3150 | H3: 7 | I3: ='Reserves Data (Reference)'!$D$3 -> 31 | J3: 140 | K3: =1.98*0.8 -> 1.584 | L3: =timeToEmpty(H3,I3,J3,K3) -> 17.478857 | M3: 131 | N3: 450
A4: Triple Tap | B4: Rapid-Fire | C4: =(G4)/(H4 * 1/J4 * 60/1) -> 1050 | D4: =(G4)/((H4-1) * 1/J4 * 60/1 + K4) -> 827.03214 | F4: =I4*N4 -> 19800 | G4: =N4 * H4 -> 4500 | H4: =tripleTap($H$3) -> 10 | I4: =floor(I3/H3,1)*H4+tripleTap(mod(I3, H3)) -> 44 | J4: 140 | K4: =1.98*0.8 -> 1.584 | L4: =timeToEmpty(H4,I4,J4,K4) -> 23.050286 | M4: =M3 -> 131 | N4: =N3 -> 450 | O4: Assumes precision hit counter is reset on every reload
A5: Fourth Time's the Charm | B5: Rapid-Fire | C5: =(G5)/(H5 * 1/J5 * 60/1) -> 1050 | D5: =(G5)/((H5-1) * 1/J5 * 60/1 + K5) -> 843.31192 | F5: =I5*N5 -> 21150 | G5: =N5 * H5 -> 4950 | H5: =fourthTimesTheCharm(H3) -> 11 | I5: =floor(I3/H3,1)*H5+fourthtimesthecharm(mod(I3, H3)) -> 47 | J5: 140 | K5: =1.98*0.8 -> 1.584 | L5: =timeToEmpty(H5,I5,J5,K5) -> 24.336 | M5: =M3 -> 131 | N5: =N3 -> 450 | O5: Assumes precision hit counter is reset on every reload
A6: FTTC + Rewind Round | B6: Rapid-Fire | C6: =(N6)/(1/J6 * 60/1) -> 1050 | D6: =C6 -> 1050 | F6: =I6*N6 -> 26550 | G6: N/A | H6: =I6 -> 59 | I6: =fourthTimesTheCharm(I3) -> 59 | J6: 140 | K6: =1.98*0.8 -> 1.584 | L6: =timeToEmpty(H6,I6,J6,K6) -> 24.857143 | M6: =M4 -> 131 | N6: =N4 -> 450 | O6: Assumes being able to fire all rounds without reloading due to perk interactions
B7: Adaptive | C7: =(G7)/(H7 * 1/J7 * 60/1) -> 891 | D7: =(G7)/((H7-1) * 1/J7 * 60/1 + K7) -> 695.31773 | F7: =I7*N7 -> 14256 | G7: =N7 * H7 -> 4158 | H7: 7 | I7: ='Reserves Data (Reference)'!$D$4 -> 24 | J7: 90 | K7: 1.98 | L7: =timeToEmpty(H7,I7,J7,K7) -> 19.273333 | M7: 183 | N7: 594
A8: Triple Tap | B8: Adaptive | C8: =(G8)/(H8 * 1/J8 * 60/1) -> 891 | D8: =(G8)/((H8-1) * 1/J8 * 60/1 + K8) -> 744.3609 | F8: =I8*N8 -> 20196 | G8: =N8 * H8 -> 5940 | H8: =tripleTap(H7) -> 10 | I8: =floor(I7/H7,1)*H8+tripletap(mod(I7, H7)) -> 34 | J8: 90 | K8: 1.98 | L8: =timeToEmpty(H8,I8,J8,K8) -> 25.94 | M8: =M7 -> 183 | N8: =N7 -> 594 | O8: Assumes precision hit counter is reset on every reload
A9: Fourth Time's the Charm | B9: Adaptive | C9: =(G9)/(H9 * 1/J9 * 60/1) -> 891 | D9: =(G9)/((H9-1) * 1/J9 * 60/1 + K9) -> 755.66692 | F9: =I9*N9 -> 21384 | G9: =N9 * H9 -> 6534 | H9: =fourthTimesTheCharm($H$7) -> 11 | I9: =floor(I7/H7,1)*H9+fourthtimesthecharm(mod(I7, H7)) -> 36 | J9: 90 | K9: 1.98 | L9: =timeToEmpty(H9,I9,J9,K9) -> 27.273333 | M9: =M7 -> 183 | N9: =N7 -> 594 | O9: Assumes precision hit counter is reset on every reload
B10: Aggressive | C10: =(G10)/(H10 * 1/J10 * 60/1) -> 871.2 | D10: =(G10)/((H10-1) * 1/J10 * 60/1 + K10) -> 683.18695 | F10: =I10*N10 -> 14520 | G10: =N10 * H10 -> 3630 | H10: 5 | I10: ='Reserves Data (Reference)'!$D$5 -> 20 | J10: 72 | K10: 1.98 | L10: =timeToEmpty(H10,I10,J10,K10) -> 19.273333 | M10: 208 | N10: 726
A11: Triple Tap | B11: Aggressive | C11: =(G11)/(H11 * 1/J11 * 60/1) -> 871.2 | D11: =(G11)/((H11-1) * 1/J11 * 60/1 + K11) -> 728.08023 | F11: =I11*N11 -> 20328 | G11: =N11 * H11 -> 5082 | H11: =tripleTap(H10) -> 7 | I11: =floor(I10/H10,1)*H11+tripletap(mod(I10, H10)) -> 28 | J11: 72 | K11: 1.98 | L11: =timeToEmpty(H11,I11,J11,K11) -> 25.94 | M11: =M10 -> 208 | N11: =N10 -> 726 | O11: Assumes precision hit counter is reset on every reload
A12: Fourth Time's the Charm | B12: Aggressive | C12: =(G12)/(H12 * 1/J12 * 60/1) -> 871.2 | D12: =(G12)/((H12-1) * 1/J12 * 60/1 + K12) -> 728.08023 | F12: =I12*N12 -> 20328 | G12: =N12 * H12 -> 5082 | H12: =fourthTimesTheCharm(H10) -> 7 | I12: =floor(I10/H10,1)*H12+fourthtimesthecharm(mod(I10, H10)) -> 28 | J12: 72 | K12: 1.98 | L12: =timeToEmpty(H12,I12,J12,K12) -> 25.94 | M12: =M10 -> 208 | N12: =N10 -> 726 | O12: Assumes precision hit counter is reset on every reload
B13: Cloudstrike | C13: =N13*J13/60 + ('Weapon Specifics'!$D$10)/(3*1/J13*60/1) -> 1552.4444 | D13: =(G13)/((H13-1) * 1/J13 * 60/1 + K13) -> 1195.9303 | F13: =I13*N13 + floor(I13/3,1)*('Weapon Specifics'!$D$10) -> 20410 | G13: =N13 * H13 + CEILING(H13/3,1)*('Weapon Specifics'!$D$10) -> 5088 | H13: 7 | I13: ='Reserves Data (Reference)'!$D$6 -> 31 | J13: 140 | K13: =1.98*0.85 -> 1.683 | L13: =timeToEmpty(H13,I13,J13,K13) -> 17.874857 | M13: =M3 -> 131 | N13: =N3 -> 450 | O13: Assumes precision hit counter is reset on every reload; Strikes occur every three precision hits
A14: cata | B14: Cloudstrike | C14: =N14*J14/60 + ('Weapon Specifics'!$D$10)/(3*1/J14*60/1) -> 1552.4444 | D14: =(G14)/((H14-1) * 1/J14 * 60/1 + K14) -> 1278.6674 | F14: =I14*N14 + floor(I14/3,1)*('Weapon Specifics'!$D$10) -> 28844 | G14: =N14 * H14 + CEILING(H14/3,1)*('Weapon Specifics'!$D$10) -> 7084 | H14: =tripleTap(H13) -> 10 | I14: =FLOOR(I13/H13,1)*H14+tripleTap(MOD(I13,H13)) -> 44 | J14: 140 | K14: =K13 -> 1.683 | L14: =timeToEmpty(H14,I14,J14,K14) -> 23.446286 | M14: =M13 -> 131 | N14: =N13 -> 450 | O14: Assumes precision hit counter is reset on every reload; Strikes occur every three precision hits
B15: Izanagi's Burden | C15: =(G15)/(H15 * 1/J15 * 60/1) -> 891 | D15: =(G15)/((H15-1) * 1/J15 * 60/1 + K15) -> 596.98492 | F15: =I15*N15 -> 11880 | G15: =N15 * H15 -> 2376 | H15: 4 | I15: ='Reserves Data (Reference)'!$D$7 -> 20 | J15: 90 | K15: 1.98 | L15: =timeToEmpty(H15,I15,J15,K15) -> 17.92 | M15: =M7 -> 183 | N15: =N7 -> 594
A16: cata, 4x Honed Edge | B16: Izanagi's Burden | C16: =D16 -> 515 | D16: =(G16)/((H16-1) * 1/J16 * 60/1 + K16) -> 515 | F16: =N16*floor(I16/4,1) +if(mod(I16, 4)=3, N15*2.31, if(mod(I16, 4)=2, N15*1.79, if(mod(I16, 4)=1, N15, 0))) -> 13390 | G16: =N16*floor(H16/4,1) -> 2678 | H16: =H15 -> 4 | I16: =I15 -> 20 | J16: 90 | K16: 3.2 | L16: =timeToEmpty(H16,I16,J16,K16) -> 22.8 | M16: 466 | N16: 2678
B17: Still Hunt | C17: =(G17)/((H17+3) * 1/J17 * 60/1 + 'Weapon Specifics'!$D$59) -> 1140.8031 | D17: =(G17)/((H17+3-1) * 1/J17 * 60/1 + K17 + 'Weapon Specifics'!$D$59) -> 974.94465 | F17: =I17*N17 + floor(I17/6+1,1)*('Weapon Specifics'!$D$61) -> 32852 | G17: =N17 * H17 + ('Weapon Specifics'!$D$61) -> 8807 | H17: 6 | I17: ='Reserves Data (Reference)'!D8 -> 20 | J17: 90 | K17: 1.98 | L17: =3*1/J17*60 + floor(I17/H17,1)*(6*1/J17*60 + 'Weapon Specifics'!$D$59 + 3*1/J17*60 + K17) + (mod(I17, H17)-1)*1/J17*60 -> 31.766667 | M17: =M7 -> 183 | N17: =N7 -> 594 | O17: Magazine is reloaded on cast, but golden gun shots are from the magazine
A18: Celestial | B18: Still Hunt | C18: =(G18)/((H18+1) * 1/J18 * 60/1 + 'Weapon Specifics'!$D$59) -> 1358.2985 | D18: =(G18)/((H18+1-1) * 1/J18 * 60/1 + K18 + 'Weapon Specifics'!$D$59) -> 1126.6234 | F18: =I18*N18 + floor(I18/6+1,1)*'Weapon Specifics'!$D$63 -> 32324 | G18: =N18 * H18 + 'Weapon Specifics'!$D$63 -> 8675 | H18: 6 | I18: =I17 -> 20 | J18: 90 | K18: 1.98 | L18: =1*1/J18*60 + floor(I18/H18,1)*(6*1/J18*60 + 'Weapon Specifics'!$D$59 + 1*1/J18*60 + K18) + (mod(I18, H18)-1)*1/J18*60 -> 26.433333 | M18: =M17 -> 183 | N18: =N17 -> 594 | O18: Magazine is reloaded on cast, but golden gun shots are from the magazine
B19: Borealis | C19: =(G19)/(H19 * 1/J19 * 60/1) -> 871.2 | D19: =(G19)/((H19-1) * 1/J19 * 60/1 + K19) -> 683.18695 | F19: =I19*N19 -> 14520 | G19: =N19 * H19 -> 3630 | H19: 5 | I19: ='Reserves Data (Reference)'!$D$9 -> 20 | J19: 72 | K19: 1.98 | L19: =timeToEmpty(H19,I19,J19,K19) -> 19.273333 | M19: =M10 -> 208 | N19: =N10 -> 726
A20: Ionic Return | B20: Borealis | C20: =(G20)/((H20-1) * 1/J20 * 60/1) -> 1524.6 | D20: N/A | F20: =I20*N20 -> 20328 | G20: =N20 * H20 -> 5082 | H20: 5 | I20: ='Reserves Data (Reference)'!$D$9 -> 20 | J20: 72 | K20: 1.98 | L20: =timeToEmpty(H20,I20,J20,K20) -> 19.273333 | M20: =M19*1.4 -> 291.2 | N20: =N19*1.4 -> 1016.4
A21: The Master 0x | B21: New Land Beyond | C21: =(G21)/(H21 * 1/J21 * 60/1) -> 556.21622 | D21: =(G21)/((H21-1) * 1/J21 * 60/1 + K21) -> 551.37307 | F21: =I21*N21 -> 41160 | G21: =N21 * H21 -> 8232 | H21: 8 | I21: ='Reserves Data (Reference)'!D10 -> 40 | J21: =1/(1.85 * 1/60) -> 32.432432 | K21: 1.98 | L21: =timeToEmpty(H21,I21,J21,K21) -> 72.67 | M21: 374 | N21: 1029 | O21: Base damage, The Master 0x, without any stat buffs
A22: The Master 0x | B22: New Land Beyond | C22: =(G22)/(H22 * 1/J22 * 60/1) -> 751.09489 | D22: =(G22)/((H22-1) * 1/J22 * 60/1 + K22) -> 711.49525 | F22: =I22*N22 -> 41160 | G22: =N22 * H22 -> 8232 | H22: =H21 -> 8 | I22: =I21 -> 40 | J22: =1/(1.37 * 1/60) -> 43.79562 | K22: =K21 -> 1.98 | L22: =timeToEmpty(H22,I22,J22,K22) -> 55.87 | M22: =M21 -> 374 | N22: =N21 -> 1029 | O22: Base damage, The Master 0x, with a Rally Barricade
A23: The Master 10x | B23: New Land Beyond | C23: =(G23)/(H23 * 1/J23 * 60/1) -> 1123.3577 | D23: =(G23)/((H23-1) * 1/J23 * 60/1 + K23) -> 1064.1314 | F23: =I23*N23 -> 61560 | G23: =N23 * H23 -> 12312 | H23: =H21 -> 8 | I23: =I21 -> 40 | J23: =J22 -> 43.79562 | K23: =K21 -> 1.98 | L23: =L22 -> 55.87 | M23: =M21 -> 374 | N23: 1539 | O23: The Master 10x, with a Rally Barricade
A24: The Master 20x | B24: New Land Beyond | C24: =(G24)/(H24 * 1/J24 * 60/1) -> 1276.6423 | D24: =(G24)/((H24-1) * 1/J24 * 60/1 + K24) -> 1209.3345 | F24: =I24*N24 -> 69960 | G24: =N24 * H24 -> 13992 | H24: =H21 -> 8 | I24: =I21 -> 40 | J24: =J23 -> 43.79562 | K24: =K21 -> 1.98 | L24: =L22 -> 55.87 | M24: =M21 -> 374 | N24: 1749 | O24: The Master 20x, with a Rally Barricade
B25: Ice Breaker | C25: =G25/L25 -> 871.38333 | D25: =C25 -> 871.38333 | F25: =G25 -> 10670 | G25: =H25*N25 -> 10670 | H25: 10 | I25: N/A | J25: 49 | K25: N/A | L25: =H25*1/J25*60 -> 12.244898 | M25: 305 | N25: 1067
A26: Trace Rifles | B26: Adaptive | C26: =(G26)/(H26 * 1/J26 * 60/1) -> 420 | D26: =(G26)/((H26-1) * 1/J26 * 60/1 + K26) -> 350.5618 | F26: =I26*N26 -> 14560 | G26: =N26 * H26 -> 2912 | H26: 104 | I26: ='Reserves Data (Reference)'!$D$11 -> 520 | J26: 900 | K26: 1.44 | L26: =timeToEmpty(H26,I26,J26,K26) -> 40.093333 | M26: 21 | N26: 28
B27: Ruinous Effigy | C27: =(G27)/(H27 * 1/J27 * 60/1) -> 615 | D27: =(G27)/((H27-1) * 1/J27 * 60/1 + K27) -> 504.45026 | F27: =I27*N27 -> 19270 | G27: =N27 * H27 -> 3854 | H27: 94 | I27: ='Reserves Data (Reference)'!$D$12 -> 470 | J27: 900 | K27: 1.44 | L27: =timeToEmpty(H27,I27,J27,K27) -> 36.76 | M27: 30 | N27: 41
A28: cata | B28: Ruinous Effigy | C28: =(G28)/(H28 * 1/J28 * 60/1) -> 799.5 | D28: =(G28)/((H28-1) * 1/J28 * 60/1 + K28) -> 655.78534 | F28: =I28*N28 -> 25051 | G28: =N28 * H28 -> 5010.2 | H28: =H27 -> 94 | I28: =I27 -> 470 | J28: =J27 -> 900 | K28: 1.44 | L28: =timeToEmpty(H28,I28,J28,K28) -> 36.76 | M28: =M27*1.3 -> 39 | N28: =N27*1.3 -> 53.3 | O28: Assumes 100% uptime on enemy debuffed from being hit by the orb
A29: Transmutation Sphere | B29: Ruinous Effigy | C29: =(G29)/((H29-1) * 1/J29 * 60/1 + 48/60) -> 601.89542 | D29: N/A | F29: =G29 -> 9209 | G29: =M29 * (H29-1) + 'Weapon Specifics'!$D$54 -> 9209 | H29: 30 | I29: 30 | J29: =1/(30/60*1/60) -> 120 | K29: N/A | L29: =I29*1/J29*60/1 -> 15 | M29: 271 | N29: 203 | O29: One swing is barely faster than the other, assumes melee spam and slam on final ammo
A30: T-Sphere blocking field | B30: Ruinous Effigy | C30: =(G30)/(L30+0.8) -> 238.59649 | D30: N/A | F30: =G30 -> 2040 | G30: =M30 * H30 + 'Weapon Specifics'!$D$54 -> 2040 | H30: 30 | I30: 30 | J30: =1/(0.25*1/60) -> 240 | K30: N/A | L30: =(I30-3)*1/J30*60/1 + (3-1)*0.5 -> 7.75 | M30: 23 | N30: =M30 -> 23 | O30: Assumes you slam on 1 ammo, uses the full 30 ammo before slamming
A31: base damage, no buffs | B31: Divinity | C31: =(H31*N31)/(H31 * 1/J31 * 60/1) + 'Weapon Specifics'!$D$16/1.3/((17+60)*1/J31*60) -> 335.58941 | D31: =(G31)/((H31-1) * 1/J31 * 60/1 + K31) -> 282.76221 | F31: =I31*N31 -> 7050 | G31: =N31 * H31 + FLOOR((H32-17)/60,1)*('Weapon Specifics'!$D$16*1/1.3) -> 4045.3846 | H31: 194 | I31: ='Reserves Data (Reference)'!$D$13 -> 470 | J31: 900 | K31: 1.44 | L31: =timeToEmpty(H31,I31,J31,K31) -> 34.013333 | M31: 11 | N31: 15 | O31: Still assumes Penance; Penance will benefit from any buffs or debuffs applied
A32: with Judgement | B32: Divinity | C32: =(H32*N32)/(H32 * 1/J32 * 60/1) + 'Weapon Specifics'!$D$16/((17+60)*1/J32*60) -> 436.26623 | D32: =(G32)/((H32-1) * 1/J32 * 60/1 + K32) -> 413.82805 | F32: =I32*N32 -> 9165 | G32: =17*N31 + N32 * (H32-17) + FLOOR((H32-10)/60,1)*'Weapon Specifics'!$D$16 -> 5920.5 | H32: =H31 -> 194 | I32: =I31 -> 470 | J32: =J31 -> 900 | K32: =K31 -> 1.44 | L32: =L31 -> 34.013333 | M32: =N32 -> 19.5 | N32: =N31*1.3 -> 19.5 | O32: Judgement activates after ~17 rounds, Penance every 60 on Judgement and deals 24794
B33: Coldheart | C33: =(G33)/(H33 * 1/J33 * 60/1) -> 709.97525 | D33: =(G33)/((H33-1) * 1/J33 * 60/1 + K33) -> 589.69984 | F33: =I33*N33 -> 14645 | G33: =((N33+'Weapon Specifics'!$D$11)/2 * 41) + 'Weapon Specifics'!$D$11*(H33-41) -> 4780.5 | H33: 101 | I33: ='Reserves Data (Reference)'!$D$14 -> 505 | J33: 900 | K33: 1.44 | L33: =timeToEmpty(H33,I33,J33,K33) -> 39.093333 | M33: 22 | N33: 29
A34: after Ionic Trace pickup | B34: Coldheart | C34: =(G34)/(H34 * 1/J34 * 60/1) -> 723.63861 | D34: =(G34)/((H34-1) * 1/J34 * 60/1 + K34) -> 601.04852 | F34: =I34*N34 -> 14645 | G34: =((N34+'Weapon Specifics'!$D$11)/2 * 33) + 'Weapon Specifics'!$D$11*(H34-33) -> 4872.5 | H34: =H33 -> 101 | I34: =I33 -> 505 | J34: =J33 -> 900 | K34: 1.44 | L34: =timeToEmpty(H34,I34,J34,K34) -> 39.093333 | M34: =M33 -> 22 | N34: =N33 -> 29 | O34: Picking up an Ionic Trace reduces number of hits requires to cap damage to 33 rounds
B35: Prometheous Lens | C35: =(G35)/(H35 * 1/J35 * 60/1) + 'Elemental Effects'!$E$13 -> 412.32143 | D35: =(G35)/((H35-1) * 1/J35 * 60/1 + K35) + 'Elemental Effects'!$E$13 -> 345.70451 | F35: =I35*N35 -> 13000 | G35: =N35 * H35 -> 2600 | H35: 100 | I35: ='Reserves Data (Reference)'!$D$15 -> 500 | J35: 900 | K35: 1.44 | L35: =timeToEmpty(H35,I35,J35,K35) -> 38.76 | M35: 19 | N35: 26 | O35: Without ignitions
B36: Prometheous Lens | C36: =(G36)/(H36 * 1/J36 * 60/1) + 'Elemental Effects'!$E$13 + 'Elemental Effects'!$E$4 / (150*1/J37*60) -> 486.62143 | D36: =(G36)/((H36-1) * 1/J36 * 60/1 + K36) + 'Elemental Effects'!$E$13 -> 345.70451 | F36: =I36*N36 + 3*'Elemental Effects'!$E$4 -> 15229 | G36: =N36 * H36 -> 2600 | H36: 100 | I36: ='Reserves Data (Reference)'!$D$15 -> 500 | J36: 900 | K36: 1.44 | L36: =timeToEmpty(H36,I36,J36,K36) -> 38.76 | M36: =M35 -> 19 | N36: =N35 -> 26 | O36: With ignitions
A37: Ember of Ashes | B37: Prometheous Lens | C37: =(G37)/(H37 * 1/J37 * 60/1) + 'Elemental Effects'!$E$13 + 'Elemental Effects'!$E$4 / (100*1/J37*60) -> 523.77143 | D37: =(G37)/((H37-1) * 1/J37 * 60/1 + K37) + 'Elemental Effects'!$E$13 -> 345.70451 | F37: =I37*N37 + floor(I37/H37,1) * 'Elemental Effects'!$E$4 -> 16715 | G37: =N37 * H37 -> 2600 | H37: 100 | I37: ='Reserves Data (Reference)'!$D$15 -> 500 | J37: 900 | K37: 1.44 | L37: =timeToEmpty(H37,I37,J37,K37) -> 38.76 | M37: =M35 -> 19 | N37: =N35 -> 26 | O37: With ignitions, Ember of Ashes
B38: The Navigator | C38: =(G38)/(H38 * 1/J38 * 60/1) -> 435 | D38: =(G38)/((H38-1) * 1/J38 * 60/1 + K38) -> 358.80102 | F38: =I38*N38 -> 14065 | G38: =N38 * H38 -> 2813 | H38: 97 | I38: ='Reserves Data (Reference)'!$D$16 -> 485 | J38: 900 | K38: 1.44 | L38: =timeToEmpty(H38,I38,J38,K38) -> 37.76 | M38: =M33 -> 22 | N38: =N33 -> 29
A39: average | B39: Wavesplitter | C39: =(G39)/(H39 * 1/J39 * 60/1) -> 580 | D39: =(G39)/((H39-1) * 1/J39 * 60/1 + K39) -> 480.92869 | F39: =I39*N39 -> 19333.333 | G39: =N39 * H39 -> 3866.6667 | H39: 100 | I39: ='Reserves Data (Reference)'!$D$17 -> 500 | J39: 900 | K39: 1.44 | L39: =timeToEmpty(H39,I39,J39,K39) -> 38.76 | M39: =AVERAGE('Weapon Specifics'!$D$82,'Weapon Specifics'!$D$83,'Weapon Specifics'!$D$84) -> 29 | N39: =AVERAGE('Weapon Specifics'!$D$85,'Weapon Specifics'!$D$86,'Weapon Specifics'!$D$87) -> 38.666667
A40: power level III | B40: Wavesplitter | C40: =(G40)/(H40 * 1/J40 * 60/1) -> 735 | D40: =(G40)/((H40-1) * 1/J40 * 60/1 + K40) -> 609.45274 | F40: =I40*N40 -> 24500 | G40: =N40 * H40 -> 4900 | H40: =H39 -> 100 | I40: =I39 -> 500 | J40: =J39 -> 900 | K40: =K39 -> 1.44 | L40: =L39 -> 38.76 | M40: ='Weapon Specifics'!D84 -> 36 | N40: ='Weapon Specifics'!D87 -> 49 | O40: Orbs crank the power level up to III for a duration
B41: Ager's Scepter | C41: =(G41)/(H41 * 1/J41 * 60/1) -> 570 | D41: =(G41)/((H41-1) * 1/J41 * 60/1 + K41) -> 470.15306 | F41: =I41*N41 -> 18430 | G41: =N41 * H41 -> 3686 | H41: 97 | I41: ='Reserves Data (Reference)'!$D$18 -> 485 | J41: 900 | K41: 1.44 | L41: =timeToEmpty(H41,I41,J41,K41) -> 37.76 | M41: 28 | N41: 38
A42: cata | B42: Ager's Scepter | C42: =(G42)/((H42-1) * 1/J42 * 60/1) -> 1311.6839 | D42: N/A | F42: =G42 -> 16877 | G42: =FLOOR(H42/20,1)*(10*N42 + 10*'Weapon Specifics'!D4 + 'Elemental Effects'!$E$9) + MOD(H42, 20)*N42 -> 16877 | H42: 194 | I42: =I41 -> 485 | J42: 900 | K42: 1.44 | L42: =H42*1/J42*60 -> 12.933333 | M42: 50 | N42: 67 | O42: Single super DPS
A43: Fusion Rifles | B43: Rapid-Fire | C43: =(G43)/(H43 * 1/J43 * 60/1) -> 645.13274 | D43: =(G43)/(H43 * 1/J43 * 60/1 + K43 - (0.63 - 9*2 * 1/60)) -> 597.17387 | F43: =I43*M43 -> 16038 | G43: =M43 * H43 -> 5832 | H43: 8 | I43: ='Reserves Data (Reference)'!$D$19 -> 22 | J43: =1/((500/1000 + 0.63) * 1/60) -> 53.097345 | K43: =1.32*0.8 -> 1.056 | L43: =timeToEmpty_fusions(H43, I43, 0.02, 9, 0.5, 0.63, K43) -> 25.562 | M43: =81*9 -> 729 | N43: N/A
A44: Controlled Burst | B44: Rapid-Fire | C44: =(G44)/(H44 * 1/J44 * 60/1) -> 810 | D44: =(G44)/(H44 * 1/J44 * 60/1 + K44 - (0.63 - 9*2 * 1/60)) -> 747.21332 | F44: =I44*M44 -> 19245.6 | G44: =M44 * H44 -> 6998.4 | H44: 8 | I44: ='Reserves Data (Reference)'!$D$19 -> 22 | J44: =1/((500/1000*0.9 + 0.63) * 1/60) -> 55.555556 | K44: =K43 -> 1.056 | L44: =timeToEmpty_fusions(H44, I44, 0.02, 9, 0.5*0.9, 0.63, K44) -> 24.462 | M44: =M43*1.2 -> 874.8 | N44: N/A
B45: Adaptive | C45: =(G45)/(H45 * 1/J45 * 60/1) -> 671.07438 | D45: =(G45)/(H45 * 1/J45 * 60/1 + K45 - (0.55 - 7*2 * 1/60)) -> 608.04992 | F45: =I45*M45 -> 15428 | G45: =M45 * H45 -> 6496 | H45: 8 | I45: ='Reserves Data (Reference)'!$D$20 -> 19 | J45: =1/((660/1000 + 0.55) * 1/60) -> 49.586777 | K45: 1.32 | L45: =timeToEmpty_fusions(H45, I45, 0.02, 7, 0.66, 0.55, K45) -> 24.34 | M45: =116*7 -> 812 | N45: N/A
B46: Aggressive | C46: =(G46)/(H46 * 1/J46 * 60/1) -> 734.48276 | D46: =(G46)/(H46 * 1/J46 * 60/1 + K46 - 0.5) -> 674.85149 | F46: =I46*M46 -> 18744 | G46: =M46 * H46 -> 6816 | H46: 8 | I46: ='Reserves Data (Reference)'!$D$21 -> 22 | J46: =1/((660/1000 + 0.5) * 1/60) -> 51.724138 | K46: 1.32 | L46: =timeToEmpty_fusions(H46, I46, 0, 12, 660/1000, 0.5, K46) -> 26.66 | M46: =71*12 -> 852 | N46: N/A
B47: Precision | C47: =(G47)/(H47 * 1/J47 * 60/1) -> 616.41791 | D47: =(G47)/(H47 * 1/J47 * 60/1 + K47 - (0.52 - 7*2 * 1/60)) -> 562.22348 | F47: =I47*M47 -> 15694 | G47: =M47 * H47 -> 6608 | H47: 8 | I47: ='Reserves Data (Reference)'!$D$22 -> 19 | J47: =1/((780/1000 + 0.56) * 1/60) -> 44.776119 | K47: 1.32 | L47: =timeToEmpty_fusions(H47, I47, 0.02, 7, 0.78, 0.56, K47) -> 26.78 | M47: =118*7 -> 826 | N47: N/A
B48: High-Impact | C48: =(G48)/(H48 * 1/J48 * 60/1) -> 692.05298 | D48: =(G48)/(H48 * 1/J48 * 60/1 + K48 - (0.55 - 5*2 * 1/60)) -> 642.25352 | F48: =I48*M48 -> 19855 | G48: =M48 * H48 -> 8360 | H48: 8 | I48: ='Reserves Data (Reference)'!$D$23 -> 19 | J48: =1/((960/1000 + 0.55) * 1/60) -> 39.735099 | K48: 1.32 | L48: =timeToEmpty_fusions(H48, I48, 0.02, 5, 0.96, 0.55, K48) -> 29.92 | M48: =209*5 -> 1045 | N48: N/A
B49: Merciless | C49: =G49/( (1000+472 + 755+388 + 492+309)/1000 + (216+286)/1000 * (H49-3) ) -> 259.19676 | D49: =F49/L49 -> 328.0684 | F49: ='Weapon Specifics'!$D$74 + 'Weapon Specifics'!$D$75 + 'Weapon Specifics'!$D$76 + (I49-3)*M49 -> 4528 | G49: ='Weapon Specifics'!$D$74 + 'Weapon Specifics'!$D$75 + 'Weapon Specifics'!$D$76 + (H49-3)*M49 -> 1536 | H49: 8 | I49: ='Reserves Data (Reference)'!$D$24 -> 19 | J49: =1/((1000/1000 + 0.53) * 1/60) -> 39.215686 | K49: 1.32 | L49: =(1000+472 + 755+388 + 492+309)/1000 + (216+286)/1000 * (I49-3) + floor(I49/H49,1)*K49 - 286/1000 -> 13.802 | M49: ='Weapon Specifics'!D77 -> 272 | N49: N/A | O49: Damage decreases per bolt at higher stacks of Conserve Momentum
A50: Impetus | B50: Merciless | C50: =G50/( (755+388 + 492+309)/1000 + (216+286)/1000 * (H50-2-1) ) -> 471.4863 | D50: =F50/L50 -> 478.23688 | F50: =('Weapon Specifics'!$D$75 + 'Weapon Specifics'!$D$76)*1.5 + M50*(I50 - 1 - floor((I50-1)/(H50),1)) -> 6588 | G50: =('Weapon Specifics'!$D$75 + 'Weapon Specifics'!$D$76)*1.5 + (H50-2-1)*M50 -> 2100 | H50: =H49 -> 8 | I50: =I49 -> 19 | J50: =1/((1000/1000 + 0.53) * 1/60) -> 39.215686 | K50: =1.32*0.66 -> 0.8712 | L50: =(1000+472)/1000 + K50 + (755+388 + 492+309)/1000 + (216+286)/1000 * (I50-2-1) + floor((I50-1)/H50,1)*K50 - 286/1000 -> 13.7756 | M50: =M49*1.5 -> 408 | N50: N/A | O50: Assumes you use 1 burst to kill an add for Impetus; kill an add and reload on final burst
B51: Jotunn | C51: =(G51)/(H51 * 1/J51 * 60/1) -> 1664.6154 | D51: =(G51)/(H51 * 1/J51 * 60/1 + K51 - 0.48) -> 1438.8298 | F51: =I51*M51 -> 17832 | G51: =(M51 + ('Weapon Specifics'!$D$78*7)) * H51 -> 10820 | H51: 5 | I51: ='Reserves Data (Reference)'!$D$25 -> 24 | J51: =1/((820/1000 + 0.48) * 1/60) -> 46.153846 | K51: =45/30 -> 1.5 | L51: =timeToEmpty_fusions(H51, I51, 0, 1, 0.82, 0.48, K51) -> 34.8 | M51: =164+579 -> 743 | N51: N/A | O51: Creates a small field of fire
A52: cata, Cornered | B52: Jotunn | C52: =(G52)/(H52 * 1/J52 * 60/1) -> 1838.5726 | D52: =(G52)/(H52 * 1/J52 * 60/1 + K52 - 0.48) -> 1566.9804 | F52: =I52*M52 -> 17832 | G52: =(M52 + ('Weapon Specifics'!$D$78*7)) * H52 -> 10820 | H52: =H51 -> 5 | I52: =I51 -> 24 | J52: =1/((820/1000 * 0.85 + 0.48) * 1/60) -> 50.97706 | K52: =45/30 -> 1.5 | L52: =timeToEmpty_fusions(H52, I52, 0, 1, 0.82 * 0.85, 0.48, K52) -> 31.848 | M52: =M51 -> 743 | N52: N/A | O52: Creates a small field of fire
B53: Tesselation | C53: =(G53)/(H53 * 1/J53 * 60/1) -> 647.05882 | D53: =(G53)/(H53 * 1/J53 * 60/1 + K53 - (0.53 - 7*2 * 1/60)) -> 553.73552 | F53: =I53*M53 -> 16940 | G53: =M53 * H53 -> 4620 | H53: 6 | I53: ='Reserves Data (Reference)'!$D$26 -> 22 | J53: =1/((0.66+0.53)*1/60) -> 50.420168 | K53: 1.5 | L53: =timeToEmpty_fusions(H53, I53, 0.02, 7, 0.66, 0.53, K53) -> 29.04 | M53: =110*7 -> 770 | N53: N/A
A54: Hip-fire | B54: Delicate Tomb | C54: =(G54)/(H54 * 1/J54 * 60/1) -> 740.74074 | D54: =(G54)/(H54 * 1/J54 * 60/1 + K54 - (0.58 - 16/2*2 * 1/60)) -> 641.1398 | F54: =I54*M54 -> 20800 | G54: =M54 * H54 -> 4800 | H54: 6 | I54: ='Reserves Data (Reference)'!$D$27 -> 26 | J54: =1/((500/1000 + 0.58) * 1/60) -> 55.555556 | K54: =1.32 -> 1.32 | L54: =timeToEmpty_fusions(H54, I54, 0.02, 16, 0.5, 0.58, K54) -> 31.96 | M54: =50*16 -> 800 | N54: N/A | O54: Does not consider Jolt. Fires 16 bolts in a wide line, 2 bolts at a time
A55: ADS | B55: Delicate Tomb | C55: =(G55)/(H55 * 1/J55 * 60/1) -> 607.40741 | D55: =(G55)/(H55 * 1/J55 * 60/1 + K55 - (0.58 - 16/2*2 * 1/60)) -> 525.73464 | F55: =I55*M55 -> 17056 | G55: =M55 * H55 -> 3936 | H55: 6 | I55: =I54 -> 26 | J55: =J54 -> 55.555556 | K55: =1.32 -> 1.32 | L55: =timeToEmpty_fusions(H56, I56, 0.02, 8, 0.5, 0.58, K56) -> 21.84 | M55: =41*2*8 -> 656 | N55: N/A | O55: Does not consider Jolt. Fires 16 bolts total, vertically: 8 bolts with 2 instances of damage each
A56: cata | B56: Telesto | C56: =(G56)/(H56 * 1/J56 * 60/1) -> 750.72464 | D56: =(G56)/(H56 * 1/J56 * 60/1 + K56 - (0.56 - 7*2 * 1/60)) -> 680.72591 | F56: =I56*M56 -> 19684 | G56: =M56 * H56 -> 7252 | H56: 7 | I56: ='Reserves Data (Reference)'!$D$28 -> 19 | J56: =1/((820/1000 + 0.56) * 1/60) -> 43.478261 | K56: 1.32 | L56: =timeToEmpty_fusions(H56, I56, 0.02, 7, 0.82, 0.56, K56) -> 27.54 | M56: =(144+4)*7 -> 1036 | N56: N/A
B57: Bastion | C57: =(G57)/(H57 * 1/J57 * 60/1) -> 813.75 | D57: =(G57)/(H57 * 1/J57 * 60/1 + K57 - (0.82 - 3*0.18)) -> 700 | F57: =I57*M57 -> 27342 | G57: =M57 * H57 -> 5208 | H57: 4 | I57: ='Reserves Data (Reference)'!$D$29 -> 21 | J57: =1/((780/1000 + 0.82) * 1/60) -> 37.5 | K57: 1.32 | L57: =timeToEmpty_fusions(H57, I57, 0.18, 3, 0.78, 0.82, K57) -> 37.44 | M57: =62*7*3 -> 1302 | N57: N/A
A58: melee combo | B58: Bastion | C58: =(G58 + 'Elemental Effects'!$E$3*4)/(H58 * 1/J58 * 60/1) -> 1400.604 | D58: =(G58 + 'Elemental Effects'!$E$3*4)/(H58 * 1/J58 * 60/1 + K58 - (0.82 - 3*0.18) + 1) -> 1043.45 | F58: =I58*M58 -> 39645.9 | G58: =M58 * H58 -> 7551.6 | H58: 4 | I58: ='Reserves Data (Reference)'!$D$29 -> 21 | J58: =1/((670/1000 + 0.82) * 1/60) -> 40.268456 | K58: 1.32 | L58: =timeToEmpty_fusions(H58, I58, 0.18, 3, 0.67, 0.82, K58) + 1 * floor(I58/H58,1) -> 40.13 | M58: =M57*1.45 -> 1887.9 | N58: N/A | O58: fire magazine, melee, reload
A59: Shotguns | B59: Rapid-Fire | C59: =(G59)/(H59 * 1/J59 * 60/1) -> 1204 | D59: =(G59)/((H59-1) * 1/J59 * 60/1 + 0.68+K59*(H59-1)) -> 700.05653 | F59: =I59*M59 -> 12900 | G59: =M59 * H59 -> 4128 | H59: 8 | I59: ='Reserves Data (Reference)'!$D$30 -> 25 | J59: 140 | K59: =19/60 -> 0.31666667 | L59: =timeToEmpty_shotgun(H59,I59,J59,K59) -> 17.69 | M59: =43*12 -> 516 | N59: 567
A60: Cascade Point | B60: Rapid-Fire | C60: =(G60)/(H60 * 1/J60 * 60/1) -> 2006.6667 | D60: =(G60)/((H60-1) * 1/J60 * 60/1 + 0.68+K60*(H60-1)) -> 878.92122 | F60: =I60*M60 -> 12900 | G60: =M60 * H60 -> 4128 | H60: 8 | I60: =I59 -> 25 | J60: =J59*5/3 -> 233.33333 | K60: =19/60 -> 0.31666667 | L60: =timeToEmpty_shotgun(H60,I60,J60,K60) -> 14.09 | M60: =M59 -> 516 | N60: =N59 -> 567
B61: Rapid-Fire Slug | C61: =(G61)/(H61 * 1/J61 * 60/1) -> 967.14286 | D61: =(G61)/((H61-1) * 1/J61 * 60/1 + 0.68+K61*(H61-1)) -> 681.98703 | F61: =I61*N61 -> 15474.286 | G61: =N61 * H61 -> 5158.0952 | H61: 8 | I61: ='Reserves Data (Reference)'!$D$31 -> 24 | J61: 90 | K61: =19/60 -> 0.31666667 | L61: =timeToEmpty_shotgun(H61,I61,J61,K61) -> 22.01 | M61: =386/1.05 -> 367.61905 | N61: =677/1.05 -> 644.7619
B62: Lightweight | C62: =(G62)/(H62 * 1/J62 * 60/1) -> 880 | D62: =(G62)/((H62-1) * 1/J62 * 60/1 + 0.68+K62*(H62-1)) -> 590.60403 | F62: =I62*M62 -> 11880 | G62: =M62 * H62 -> 5280 | H62: 8 | I62: ='Reserves Data (Reference)'!$D$32 -> 18 | J62: 80 | K62: 0.43 | L62: =timeToEmpty_shotgun(H62,I62,J62,K62) -> 19.06 | M62: =55*12 -> 660 | N62: 727
A63: Trench Barrel | B63: Lightweight | C63: =D63 -> 913.84615 | D63: =(M63*3)/(3*1/J63*60 + 1) -> 913.84615 | F63: =I63*M63 -> 17820 | G63: =M63 * H63 -> 7920 | H63: 8 | I63: =I62 -> 18 | J63: 80 | K63: 0.43 | L63: =I63*1/J63*60 -> 13.5 | M63: =M62*1.5 -> 990 | N63: =N62*1.5 -> 1090.5 | O63: Assumes reload-cancelling
B64: Precision | C64: =(G64)/(H64 * 1/J64 * 60/1) -> 715 | D64: =(G64)/((H64-1) * 1/J64 * 60/1 + 0.68+K64*(H64-1)) -> 525.0918 | F64: =I64*M64 -> 11880 | G64: =M64 * H64 -> 4620 | H64: 7 | I64: ='Reserves Data (Reference)'!$D$33 -> 18 | J64: 65 | K64: 0.43 | L64: =timeToEmpty_shotgun(H64,I64,J64,K64) -> 21.656154 | M64: =55*12 -> 660 | N64: 727
B65: Pinpoint Slug | C65: =(G65)/(H65 * 1/J65 * 60/1) -> 768.08333 | D65: =(G65)/((H65-1) * 1/J65 * 60/1 + 0.68+K65*(H65-1)) -> 558.73305 | F65: =I65*N65 -> 12762 | G65: =N65 * H65 -> 5672 | H65: 8 | I65: ='Reserves Data (Reference)'!$D$34 -> 18 | J65: 65 | K65: 0.43 | L65: =timeToEmpty_shotgun(H65,I65,J65,K65) -> 21.656154 | M65: 404 | N65: 709 | O65: Assumes precision hits
B66: Aggressive | C66: =(G66)/(H66 * 1/J66 * 60/1) -> 770 | D66: =(G66)/((H66-1) * 1/J66 * 60/1 + 0.68+K66*(H66-1)) -> 608.36168 | F66: =I66*M66 -> 15960 | G66: =M66 * H66 -> 5040 | H66: 6 | I66: ='Reserves Data (Reference)'!$D$35 -> 19 | J66: 55 | K66: 0.43 | L66: =timeToEmpty_shotgun(H66,I66,J66,K66) -> 24.853636 | M66: =70*12 -> 840 | N66: 930
A67: Trench Barrel | B67: Aggressive | C67: =D67 -> 884.68085 | D67: =(M67*3)/(3*1/J67*60 + 1) -> 884.68085 | F67: =I67*M67 -> 23940 | G67: =M67 * H67 -> 7560 | H67: 6 | I67: =I66 -> 19 | J67: 55 | K67: 0.43 | L67: =I67*1/J67*60 -> 20.727273 | M67: =M66*1.5 -> 1260 | N67: =N66*1.5 -> 1395 | O67: Assumes reload-cancelling; Baby Legend of Acrius
B68: Heavy Burst | C68: =(G68)/(H68 * 1/J68 * 60/1) -> 2069.7674 | D68: =(G68)/((H68-1) * 1/J68 * 60/1 + 0.68+K68*(H68-1)) -> 1021.7773 | F68: =I68*N68 -> 28819.048 | G68: =N68 * H68 -> 13561.905 | H68: 16 | I68: ='Reserves Data (Reference)'!$D$36 -> 34 | J68: =14/((535-191)/60) * 60 -> 146.51163 | K68: 0.43 | L68: =timeToEmpty_shotgun(H68,I68,J68,K68) -> 27.385238 | M68: =254/1.05*2 -> 483.80952 | N68: =445/1.05*2 -> 847.61905 | O68: Assumes precision hits
B69: The Fourth Horseman | C69: =(G69)/((H69-1) * 1/J69 * 60/1) -> 5263.2 | D69: =(G69)/((H69-1) * 1/J69 * 60/1 + 0.68+K69*(H69-1)) -> 1228.7626 | F69: =G69*floor(I69/H69,1) -> 15789.6 | G69: =M69 + M69*1.18 + M69*1.39 + M69*1.59 -> 3157.92 | H69: 4 | I69: ='Reserves Data (Reference)'!$D$37 -> 20 | J69: 300 | K69: 0.43 | L69: =timeToEmpty_shotgun(H69,I69,J69,K69) -> 12.17 | M69: =51*12 -> 612 | N69: 676
A70: cata | B70: The Fourth Horseman | C70: =(G70)/((H70-1) * 1/J70 * 60/1) -> 5332.05 | D70: =(G70)/((H70-1) * 1/J70 * 60/1 + 0.68+K70*(H70-1)) -> 1333.0125 | F70: =G70*floor(I70/H70,1) -> 17062.56 | G70: =M70 + M70*1.18 + M70*1.39 + M70*1.59 + M70*1.81 -> 4265.64 | H70: 5 | I70: =I69 -> 20 | J70: =J69 -> 300 | K70: 0.43 | L70: =timeToEmpty_shotgun(H70,I70,J70,K70) -> 12.12 | M70: =M69 -> 612 | N70: =N69 -> 676
B71: Conditional Finality | C71: =(G71)/(H71 * 1/55 * 60/1) -> 1208.625 | D71: =(G71)/((H71-1) * 1/55 * 60/1 + K71) -> 1225.9932 | F71: =G71*floor(I71/H71,1) + mod(I71, 2) * (M71 + 'Elemental Effects'!E9) -> 24778 | G71: =M71+ 'Weapon Specifics'!D13+'Elemental Effects'!E9+'Weapon Specifics'!D12 -> 2637 | H71: 2 | I71: ='Reserves Data (Reference)'!D38 -> 19 | J71: 165 | K71: 1.06 | L71: =timeToEmpty(H71,I71,55,K71) -> 19.358182 | M71: =57*12 -> 684 | N71: 889 | O71: Frozen targets do not benefit from precision damage
B72: The Chaperone | C72: =(G72)/(H72 * 1/J72 * 60/1) -> 789.83333 | D72: =(G72)/((H72-1) * 1/J72 * 60/1 + 0.68+K72*(H72-1)) -> 570.84923 | F72: =I72*N72 -> 12186 | G72: =N72 * H72 -> 4062 | H72: 6 | I72: ='Reserves Data (Reference)'!D39 -> 18 | J72: 70 | K72: 0.43 | L72: =timeToEmpty_shotgun(H72,I72,J72,K72) -> 20.667143 | M72: 386 | N72: 677
A73: Roadborn | B73: The Chaperone | C73: =(G73)/(H73 * 1/J73 * 60/1) -> 1651.88 | D73: =(G73)/((H73-1) * 1/J73 * 60/1 + 0.68+K73*(H73-1)) -> 1034.0407 | F73: =(I73 - 2)*N73 + N72 -> 13892.04 | G73: =N73 * H73 -> 4955.64 | H73: 6 | I73: =I72 -> 18 | J73: 120 | K73: =0.43*0.75 -> 0.3225 | L73: =timeToEmpty_shotgun(H73,I73,J73,K73) -> 13.6975 | M73: =M72 -> 386 | N73: =N72*1.22 -> 825.94 | O73: Assumes 100% Roadborn uptime, reload to full
A74: Roadborn | B74: The Chaperone | C74: =D74 -> 1214.6176 | D74: =N74/0.68 -> 1214.6176 | F74: =F73 -> 13892.04 | G74: =G73 -> 4955.64 | H74: =H73 -> 6 | I74: =I73 -> 18 | J74: =J73 -> 120 | K74: =K73 -> 0.3225 | L74: =0.68*(I74-1) -> 11.56 | M74: =M73 -> 386 | N74: =N73 -> 825.94 | O74: Assumes 100% Roadborn uptime, reload cancel, firing final round
A75: ADS | B75: Lord of Wolves | C75: =(G75)/(H75 * 1/J75 * 60/1) -> 1045.3333 | D75: =(G75)/((H75-1) * 1/J75 * 60/1 + K75) -> 807.96977 | F75: =I75*M75 -> 18522 | G75: =M75 * H75 -> 2940 | H75: 30 | I75: ='Reserves Data (Reference)'!$D$40 -> 189 | J75: 640 | K75: 0.92 | L75: =(I75-Floor(I75/H75,1)-1)*1/J75*60/1 + (Floor(I75/H75,1)) * K75 -> 22.5825 | M75: 98 | N75: 176 | O75: Assumes all body hits
A76: ADS | B76: Lord of Wolves | C76: =(G76)/(H76 * 1/J76 * 60/1) -> 1877.3333 | D76: =(G76)/((H76-1) * 1/J76 * 60/1 + K76) -> 1451.0477 | F76: =I76*N76 -> 33264 | G76: =N76 * H76 -> 5280 | H76: =$H$75 -> 30 | I76: ='Reserves Data (Reference)'!$D$40 -> 189 | J76: =J75 -> 640 | K76: =$K$75 -> 0.92 | L76: =(I76-Floor(I76/H76,1)-1)*1/J76*60/1 + (Floor(I76/H76,1)) * K76 -> 22.5825 | M76: =M75 -> 98 | N76: =N75 -> 176 | O76: Assumes all precision hits
A77: Hip-Fire | B77: Lord of Wolves | C77: =(G77)/(H77 * 1/J77 * 60/1) -> 1527.1667 | D77: =(G77)/((H77-1) * 1/J77 * 60/1 + K77) -> 1096.7698 | F77: =I77*M77 -> 20790 | G77: =M77 * H77 -> 3300 | H77: =$H$75 -> 30 | I77: ='Reserves Data (Reference)'!$D$40 -> 189 | J77: 833 | K77: =$K$75 -> 0.92 | L77: =timeToEmpty(H77,I77,J77,K77) -> 18.629244 | M77: 110 | N77: 171 | O77: Assumes all body hits
A78: Hip-Fire | B78: Lord of Wolves | C78: =(G78)/(H78 * 1/J78 * 60/1) -> 2374.05 | D78: =(G78)/((H78-1) * 1/J78 * 60/1 + K78) -> 1704.9785 | F78: =I78*N78 -> 32319 | G78: =N78 * H78 -> 5130 | H78: =$H$75 -> 30 | I78: ='Reserves Data (Reference)'!$D$40 -> 189 | J78: =J77 -> 833 | K78: =$K$75 -> 0.92 | L78: =timeToEmpty(H78,I78,J78,K78) -> 18.629244 | M78: =M77 -> 110 | N78: =N77 -> 171 | O78: Assumes all precision hits
A79: cata, Hip-Fire | B79: Lord of Wolves | C79: =(G79)/(H79 * 1/J79 * 60/1) + 'Elemental Effects'!$E$13 + ('Elemental Effects'!$E$4)/(75 * 1/J79 * 60/1) -> 1687.0257 | D79: =(G79)/((H79-1) * 1/J79 * 60/1 + K79) + 'Elemental Effects'!$E$13 + ('Elemental Effects'!$E$4)/(75 * 1/J79 * 60 + FLOOR(75/H79,1)*K79) -> 1221.6849 | F79: =I79*N79 -> 32319 | G79: =M79 * H79 -> 3300 | H79: =$H$75 -> 30 | I79: ='Reserves Data (Reference)'!$D$40 -> 189 | J79: =$J$77 -> 833 | K79: =$K$75 -> 0.92 | L79: =timeToEmpty(H79,I79,J79,K79) -> 18.629244 | M79: =$M$77 -> 110 | N79: =$N$77 -> 171 | O79: Assumes all body hits, with ignitions and scorch
A80: cata, Hip-Fire | B80: Lord of Wolves | C80: =(G80)/(H80 * 1/J80 * 60/1) + 'Elemental Effects'!$E$13 + ('Elemental Effects'!$E$4)/(75 * 1/J80 * 60/1) -> 2533.909 | D80: =(G80)/((H80-1) * 1/J80 * 60/1 + K80) + 'Elemental Effects'!$E$13 + ('Elemental Effects'!$E$4)/(75 * 1/J80 * 60 + FLOOR(75/H80,1)*K80) -> 1829.8937 | F80: =I80*N80 -> 32319 | G80: =N80 * H80 -> 5130 | H80: =$H$75 -> 30 | I80: ='Reserves Data (Reference)'!$D$40 -> 189 | J80: =$J$77 -> 833 | K80: =$K$75 -> 0.92 | L80: =timeToEmpty(H80,I80,J80,K80) -> 18.629244 | M80: =$M$77 -> 110 | N80: =$N$77 -> 171 | O80: Assumes all precision hits, with ignitions and scorch
A81: cata, Hip-Fire, Ashes | B81: Lord of Wolves | C81: =(G81)/(H81 * 1/J81 * 60/1) + 'Elemental Effects'!$E$13 + ('Elemental Effects'!$E$4)/(45 * 1/J81 * 60/1) -> 1778.7174 | D81: =(G81)/((H81-1) * 1/J81 * 60/1 + K81) + 'Elemental Effects'!$E$13 + ('Elemental Effects'!$E$4)/(45 * 1/J81 * 60 + FLOOR(45/H81,1)*K81) -> 1297.6414 | F81: =I81*N81 -> 32319 | G81: =M81 * H81 -> 3300 | H81: =$H$75 -> 30 | I81: ='Reserves Data (Reference)'!$D$40 -> 189 | J81: =$J$77 -> 833 | K81: =$K$75 -> 0.92 | L81: =timeToEmpty(H81,I81,J81,K81) -> 18.629244 | M81: =$M$77 -> 110 | N81: =$N$77 -> 171 | O81: Assumes all body hits, with ignitions and scorch, Ember of Ashes
A82: cata, Hip-Fire, Ashes | B82: Lord of Wolves | C82: =(G82)/(H82 * 1/J82 * 60/1) + 'Elemental Effects'!$E$13 + ('Elemental Effects'!$E$4)/(45 * 1/J82 * 60/1) -> 2625.6007 | D82: =(G82)/((H82-1) * 1/J82 * 60/1 + K82) + 'Elemental Effects'!$E$13 + ('Elemental Effects'!$E$4)/(45 * 1/J82 * 60 + FLOOR(45/H82,1)*K82) -> 1905.8501 | F82: =I82*N82 -> 32319 | G82: =N82 * H82 -> 5130 | H82: =$H$75 -> 30 | I82: ='Reserves Data (Reference)'!$D$40 -> 189 | J82: =$J$77 -> 833 | K82: =$K$75 -> 0.92 | L82: =timeToEmpty(H82,I82,J82,K82) -> 18.629244 | M82: =$M$77 -> 110 | N82: =$N$77 -> 171 | O82: Assumes all precision hits, with ignitions and scorch, Ember of Ashes
A83: cata, pellet | B83: Duality | C83: =(G83)/(H83 * 1/J83 * 60/1) -> 754 | D83: =(G83)/((H83-1) * 1/J83 * 60/1 + IF(K83 > 1/J83*60, K83, 1/J83*60)) -> 754 | F83: =I83*N83 -> 12971 | G83: =M83 * H83 -> 5568 | H83: 8 | I83: ='Reserves Data (Reference)'!D41 -> 17 | J83: 65 | K83: =51/60 * 0.8 -> 0.68 | L83: =timeToEmpty(H83,I83,J83,K83) -> 14.283077 | M83: =58*12 -> 696 | N83: 763
A84: cata, slug | B84: Duality | C84: =(G84)/(H84 * 1/J84 * 60/1) -> 1135.3333 | D84: =(G84)/((H84-1) * 1/J84 * 60/1 + IF(K84 > 1/J84*60, K84, 1/J84*60)) -> 1135.3333 | F84: =I84*N84 -> 17816 | G84: =N84 * H84 -> 8384 | H84: =H83 -> 8 | I84: =I83 -> 17 | J84: =J83 -> 65 | K84: =K83 -> 0.68 | L84: =timeToEmpty(H84,I84,J84,K84) -> 14.283077 | M84: 597 | N84: 1048 | O84: Assumes all precision hits
A85: cata, On Black Wings x3 | B85: Duality | C85: =(G85)/(H85 * 1/J85 * 60/1) -> 1759.7667 | D85: =(G85)/((H85-1) * 1/J85 * 60/1 + IF(K85 > 1/J85*60, K85, 1/J85*60)) -> 1759.7667 | F85: =(I85-3)*N85 + 3*M83 -> 24829.6 | G85: =N85 * H85 -> 12995.2 | H85: =H84 -> 8 | I85: =I84 -> 17 | J85: =J84 -> 65 | K85: =K84 -> 0.68 | L85: =timeToEmpty(H85,I85,J85,K85) -> 14.283077 | M85: =M84 -> 597 | N85: =N84*1.55 -> 1624.4 | O85: Assumes 100% uptime with On Black Wings and only firing slugs, all precision hits
B86: Slayer's Fang | C86: =(G86)/(H86 * 1/J86 * 60/1) -> 1280.1515 | D86: =(G86)/((H86-1) * 1/J86 * 60/1 + K86) -> 1184.6399 | F86: =I86*N86 -> 18653.636 | G86: =N86 * H86 -> 8778.1818 | H86: 8 | I86: ='Reserves Data (Reference)'!D42 -> 17 | J86: 70 | K86: 1.41 | L86: =timeToEmpty(H86,I86,J86,K86) -> 14.82 | M86: =(425+(66*7)) -> 887 | N86: =(745+(66*7)) *1/1.1 -> 1097.2727 | O86: Splits into 7 subprojectiles on hit, assumes all precision hits
A87: Breech Grenade Launchers | B87: Double Fire | C87: N/A | D87: =M87/K87 -> 475.30864 | F87: =I87*M87 -> 15400 | G87: =M87 * H87 -> 770 | H87: 1 | I87: ='Reserves Data (Reference)'!D43 -> 20 | J87: 100 | K87: 1.62 | L87: =I87*K87 -> 32.4 | M87: =(186+199)*2 -> 770 | N87: N/A
B88: Lightweight | C88: =(G88)/(H88 * 1/J88 * 60/1) -> 900 | D88: =M88/K88 -> 370.37037 | F88: =I88*M88 -> 12000 | G88: =M88 * H88 -> 600 | H88: 1 | I88: ='Reserves Data (Reference)'!D44 -> 20 | J88: 90 | K88: 1.62 | L88: =I88*K88 -> 32.4 | M88: =176+424 -> 600 | N88: N/A
A89: Slideshot/Slideways spam | B89: Lightweight | C89: =(G89)/(H89 * 1/J89 * 60/1) -> 750 | D89: =M89*J89*1/60 -> 750 | F89: =I89*M89 -> 12000 | G89: =M89 * H89 -> 600 | H89: 1 | I89: =I88 -> 20 | J89: =1/(0.8*1/60) -> 75 | K89: 0.33 | L89: =I89*1/J89*60 -> 16 | M89: =M88 -> 600 | N89: N/A
B90: Wave | C90: =(G90)/(H90 * 1/J90 * 60/1) -> 658.5 | D90: =M90/K90 -> 270.98765 | F90: =I90*M90 -> 8780 | G90: =M90 * H90 -> 439 | H90: 1 | I90: ='Reserves Data (Reference)'!D45 -> 20 | J90: 90 | K90: 1.62 | L90: =I90*K90 -> 32.4 | M90: 439 | N90: N/A
B91: Micro-Missile | C91: =(G91)/(H91 * 1/J91 * 60/1) -> 1168.5 | D91: =M91/K91 -> 480.8642 | F91: =I91*M91 -> 15580 | G91: =M91 * H91 -> 779 | H91: 1 | I91: ='Reserves Data (Reference)'!D46 -> 20 | J91: 90 | K91: 1.62 | L91: =I91*K91 -> 32.4 | M91: =254+525 -> 779 | N91: N/A
B92: Area Denial | C92: =(M92 + 'Weapon Specifics'!$D$9*22)/(0.4 + 0.27*22) -> 158.99054 | D92: =C92 -> 158.99054 | F92: =G92*I92 -> 20160 | G92: =M92 + 22*'Weapon Specifics'!$D$9 -> 1008 | H92: 1 | I92: ='Reserves Data (Reference)'!D46 -> 20 | J92: 72 | K92: 1.62 | L92: =I92*(0.4 + 0.27*22) -> 126.8 | M92: 18 | N92: N/A | O92: Fire only 1 projectile per magazine; wait out AoE expiration
B93: Area Denial | C93: =(G93)/(0.13*(5-1) + 0.27*22) -> 174.14861 | D93: =C93 -> 174.14861 | F93: =G93*I93 -> 22500 | G93: =5*M93 + floor(0.13*(5-1) / 0.27,1)*'Weapon Specifics'!$D$9 + 22*'Weapon Specifics'!$D$9 -> 1125 | H93: 1 | I93: ='Reserves Data (Reference)'!D47 -> 20 | J93: 72 | K93: 1.62 | L93: =I93*(0.13*5 + 0.27*22) -> 131.8 | M93: =$M$92 -> 18 | N93: N/A | O93: Fire all five projectiles per magazine; wait out AoE expiration
B94: Area Denial | C94: N/A | D94: =G94/(0.13*(5-1) + K94) -> 189.25234 | F94: =G94*I94 + 22*'Weapon Specifics'!$D$9 -> 9090 | G94: =5*M94 + floor((0.13*(5-1) + K94) / 0.27,1)*'Weapon Specifics'!$D$9 -> 405 | H94: 1 | I94: ='Reserves Data (Reference)'!D47 -> 20 | J94: 72 | K94: 1.62 | L94: =I94*(0.13*(5-1) + K94) -> 42.8 | M94: =$M$92 -> 18 | N94: N/A | O94: Fire all five projectiles per magazine, spamming
A95: No Enrage | B95: Ex Diris | C95: =M95*J95*1/60 + ('Weapon Specifics'!$D$22)/((CEILING(3*J95/60,1)+2)*1/J95*60) -> 711.6 | D95: =C95 -> 711.6 | F95: =I95*M95 -> 21595 | G95: =M95 * H95 -> 617 | H95: 1 | I95: ='Reserves Data (Reference)'!D48 -> 35 | J95: 60 | K95: N/A | L95: =I95*1/J95*60 -> 35 | M95: =282+335 -> 617 | N95: N/A
A96: Max Enrage | B96: Ex Diris | C96: =M96*J96*1/60 + ('Weapon Specifics'!$D$22)/((CEILING(3*J96/60,1)+2)*1/J96*60) -> 1079.1008 | D96: =C96 -> 1079.1008 | F96: =I96*M96 -> 21595 | G96: =M96 * H96 -> 617 | H96: 1 | I96: =I95 -> 35 | J96: =5/((375-185)*1/59.9)*60 -> 94.578947 | K96: N/A | L96: =I96*1/J96*60 -> 22.203673 | M96: =M95 -> 617 | N96: N/A
A97: passive | B97: Witherhoard | C97: =('Weapon Specifics'!$D$97 + 17*'Weapon Specifics'!$D$99)/(9.5) -> 216.73684 | D97: =C97 -> 216.73684 | F97: =(M97 + 'Weapon Specifics'!$D$85*17) * I97 -> 10440 | G97: ='Weapon Specifics'!$D$83 + 17*'Weapon Specifics'!$D$85 -> 522 | H97: 1 | I97: ='Reserves Data (Reference)'!D49 -> 20 | J97: 90 | K97: 1.62 | L97: =I97*4.5 -> 90 | M97: ='Weapon Specifics'!$D$83 -> 29 | N97: N/A | O97: This assumes you reapply the frame after the DOT expires; reload during wait
A98: passive | B98: Witherhoard | C98: =('Weapon Specifics'!$D$98+'Weapon Specifics'!$D$98 + 17*'Weapon Specifics'!$D$99)/(9.5) -> 325.36842 | D98: =C98 -> 325.36842 | F98: =('Weapon Specifics'!$D$85*17)*I98 + (M98 + 'Weapon Specifics'!D84) * (I98-1) -> 11095 | G98: ='Weapon Specifics'!$D$84 + 17*'Weapon Specifics'!$D$85 -> 529 | H98: 1 | I98: =I97 -> 20 | J98: 90 | K98: 1.62 | L98: =I98*4.5 -> 90 | M98: ='Weapon Specifics'!$D$83 -> 29 | N98: N/A | O98: This assumes you reapply the frame before the DOT expires; reload during wait
A99: passive, ground | B99: Witherhoard | C99: =('Weapon Specifics'!$D$100)/(3.7) + 'Weapon Specifics'!$D$101/0.27 -> 254.38438 | D99: =C99 -> 254.38438 | F99: =('Weapon Specifics'!$D$86 + 14*'Weapon Specifics'!$D$87)*I99 -> 14480 | G99: ='Weapon Specifics'!$D$86 + 14*'Weapon Specifics'!$D$87 -> 724 | H99: 1 | I99: =I98 -> 20 | J99: 90 | K99: 1.62 | L99: =I99*3.7 -> 74 | M99: ='Weapon Specifics'!$D$83 -> 29 | N99: N/A | O99: Blighting the ground only, shoot the ground just before blight expiration (every ~3.7 seconds)
A100: cata, single blight, boss | B100: Witherhoard | C100: =('Weapon Specifics'!$D$98+'Weapon Specifics'!$D$98)/(2.5) + ('Weapon Specifics'!$D$99)/0.56 -> 639.7 | D100: =C100 -> 639.7 | F100: =('Weapon Specifics'!$D$85*17)*I100 + ('Weapon Specifics'!$D$84) * (I100-1) -> 10544 | G100: =$G$98 -> 529 | H100: 1 | I100: =I97 -> 20 | J100: 90 | K100: 1.62 | L100: =I100*2.5 -> 50 | M100: ='Weapon Specifics'!$D$83 -> 29 | N100: N/A | O100: This assumes you auto-reload > boss before DOT expires
...

Sheet Heavies
A1: Note: all weapons assume Backup Mag whenever applicable, rocket launchers assume Impact Casing wherever applicable; All weapon damage (except exotics) is normalized. Want to contribute? Have questions, comments, or concerns? See Home page for contact information.
B2: Frame/Weapon | C2: 1-Mag Burst or "True" DPS | D2: Sustained DPS | F2: Theoretical Total Damage | G2: 1-Mag Damage | H2: Magazine Capacity | I2: Reserves + Magazine | J2: Fire rate (rpm) | K2: Reload Speed (s) | L2: Time to Empty (s) | M2: Body Damage | N2: Precision Damage
A3: Machine Guns | B3: Rapid-Fire | C3: =(G3)/(H3 * 1/J3 * 60/1) -> 825 | D3: =(G3)/((H3-1) * 1/J3 * 60/1 + K3) -> 604.91584 | F3: =I3*N3 -> 31625 | G3: =N3 * H3 -> 6325 | H3: 115 | I3: ='Reserves Data (Reference)'!D67 -> 575 | J3: 900 | K3: =3.57*0.8 -> 2.856 | L3: =timeToEmpty(H3,I3,J3,K3) -> 49.424 | M3: 42 | N3: 55
A4: Triple Tap | B4: Rapid-Fire | C4: =(G4)/(H4 * 1/J4 * 60/1) -> 825 | D4: =(G4)/((H4-1) * 1/J4 * 60/1 + K4) -> 663.58025 | F4: =I4*N4 -> 47300 | G4: =N4 * H4 -> 9460 | H4: =tripleTap(H3) -> 172 | I4: =floor(I3/H3,1)*H4+tripleTap(mod(I3, H3)) -> 860 | J4: =J3 -> 900 | K4: =3.57*0.8 -> 2.856 | L4: =timeToEmpty(H4,I4,J4,K4) -> 68.424 | M4: =M3 -> 42 | N4: =N3 -> 55
A5: Fourth Time's the Charm | B5: Rapid-Fire | C5: =(G5)/(H5 * 1/J5 * 60/1) -> 825 | D5: =(G5)/((H5-1) * 1/J5 * 60/1 + K5) -> 696.60393 | F5: =I5*N5 -> 62425 | G5: =N5 * H5 -> 12485 | H5: =fourthTimesTheCharm(H3) -> 227 | I5: =floor(I3/H3,1)*H5+fourthTimesTheCharm(mod(I3, H3)) -> 1135 | J5: =J3 -> 900 | K5: =3.57*0.8 -> 2.856 | L5: =timeToEmpty(H5,I5,J5,K5) -> 86.757333 | M5: =M3 -> 42 | N5: =N3 -> 55
B6: Aggressive | C6: =(G6)/(H6 * 1/J6 * 60/1) -> 770 | D6: =(G6)/((H6-1) * 1/J6 * 60/1 + K6) -> 557.43835 | F6: =I6*N6 -> 35035 | G6: =N6 * H6 -> 7007 | H6: 91 | I6: ='Reserves Data (Reference)'!D68 -> 455 | J6: 600 | K6: 3.57 | L6: =timeToEmpty(H6,I6,J6,K6) -> 59.28 | M6: 60 | N6: 77
B7: Adaptive | C7: =(G7)/(H7 * 1/J7 * 60/1) -> 720 | D7: =(G7)/((H7-1) * 1/J7 * 60/1 + K7) -> 535.84718 | F7: =I7*N7 -> 36000 | G7: =N7 * H7 -> 7200 | H7: 75 | I7: ='Reserves Data (Reference)'!D69 -> 375 | J7: 450 | K7: 3.57 | L7: =timeToEmpty(H7,I7,J7,K7) -> 63.613333 | M7: 68 | N7: 96
B8: High-Impact | C8: =(G8)/(H8 * 1/J8 * 60/1) -> 678 | D8: =(G8)/((H8-1) * 1/J8 * 60/1 + K8) -> 532.90715 | F8: =I8*N8 -> 42149 | G8: =N8 * H8 -> 8475 | H8: 75 | I8: ='Reserves Data (Reference)'!D70 -> 373 | J8: 360 | K8: 3.57 | L8: =timeToEmpty(H8,I8,J8,K8) -> 75.613333 | M8: 78 | N8: 113
B9: Heir Apparent | C9: =(G9)/(H9 * 1/J9 * 60/1) -> 810 | D9: =(G9)/((H9-1) * 1/J9 * 60/1 + K9) -> 641.45714 | F9: =I9*N9 -> 23760 | G9: =N9 * H9 -> 10800 | H9: 200 | I9: ='Reserves Data (Reference)'!D71 -> 440 | J9: 900 | K9: 3.57 | L9: =timeToEmpty(H9,I9,J9,K9) -> 36.273333 | M9: 45 | N9: 54
B10: Thunderlord | C10: =(N10*720*1/60) + 'Weapon Specifics'!$D$88/(10*1/720 * 60) -> 1189.62 | D10: =(G10)/((H10-1) * 1/J10 * 60/1 + K10) -> 645.91691 | F10: =G10*floor(I10/H10,1) + mod(I10, H10) * N10 + floor(mod(I10, H10)/10,1) * 'Weapon Specifics'!$D$88 -> 37512.6 | G10: =H10*N10 + floor(H10/10,1) * 'Weapon Specifics'!$D$88 -> 6140.1 | H10: 62 | I10: ='Reserves Data (Reference)'!D72 -> 379 | J10: =H10/(13*1/450 + 13*1/600 + (H10-13*2)*1/720) -> 616.57459 | K10: 3.57 | L10: =timeToEmpty(H10,I10,J10,K10) -> 57.62 | M10: 68 | N10: 96
A11: cata | B11: Thunderlord | C11: =(N11*720*1/60) + 'Weapon Specifics'!$D$88/(10*1/720 * 60) -> 1189.62 | D11: =C11 -> 1189.62 | F11: =I11*N11 + FLOOR(I11/10,1)*'Weapon Specifics'!$D$88 -> 37543.95 | G11: inf | H11: inf | I11: =I10 -> 379 | J11: =J10 -> 616.57459 | K11: 3.57 | L11: =13*1/450*60 + 13*1/600*60 + (I11-13*2)*1/720*60 -> 32.45 | M11: =M10 -> 68 | N11: =N10 -> 96
A12: w/o weaken | B12: Deterministic Chaos | C12: =(G12)/(H12 * 1/J12 * 60/1) -> 1566.1141 | D12: =(G12)/((H12-1) * 1/J12 * 60/1 + K12) -> 1098.7062 | F12: =I12*N12 -> 42488 | G12: =N12 * H12 + floor(H12/16,1) * (2681*1/1.15 + 37) -> 12528.913 | H12: 48 | I12: ='Reserves Data (Reference)'!D73 -> 376 | J12: 360 | K12: 3.57 | L12: =timeToEmpty(H12,I12,J12,K12) -> 86.323333 | M12: =M8 -> 78 | N12: =N8 -> 113 | O12: This assumes 0% weaken uptime
A13: w/ weaken | B13: Deterministic Chaos | C13: =(G13)/(H13 * 1/J13 * 60/1) -> 1798.95 | D13: =(G13)/((H13-1) * 1/J13 * 60/1 + K13) -> 1262.052 | F13: =I13*N13 -> 48861.2 | G13: =N13 * H13 + floor(H13/16,1) * (2681 + 37) -> 14391.6 | H13: 48 | I13: =I12 -> 376 | J13: 360 | K13: 3.57 | L13: =timeToEmpty(H13,I13,J13,K13) -> 86.323333 | M13: =M12*1.15 -> 89.7 | N13: =N12*1.15 -> 129.95 | O13: This assumes 100% weaken uptime
B14: Xenophage | C14: =(G14)/(H14 * 1/J14 * 60/1) -> 1362 | D14: =(G14)/((H14-1) * 1/J14 * 60/1 + K14) -> 925.07837 | F14: =I14*M14 -> 19749 | G14: =M14 * H14 -> 8853 | H14: 13 | I14: ='Reserves Data (Reference)'!D74 -> 29 | J14: 120 | K14: 3.57 | L14: =timeToEmpty(H14,I14,J14,K14) -> 20.14 | M14: =138+543 -> 681 | N14: N/A | O14: Does not deal precision damage
A15: w/o rockets | B15: Grand Overture | C15: =(G15)/(H15 * 1/J15 * 60/1) -> 898.33333 | D15: =(G15)/(0.8 + (H15-1) * 1/J15 * 60/1 + K15) -> 683.57641 | F15: =I15*M15 -> 31262 | G15: =M15 * H15 -> 10780 | H15: 20 | I15: ='Reserves Data (Reference)'!D75 -> 58 | J15: 100 | K15: 3.57 | L15: =timeToEmpty(H15,I15,J15,K15) -> 40.14 | M15: 539 | N15: N/A | O15: Does not deal precision damage
A16: w/ rockets | B16: Grand Overture | C16: =(('Weapon Specifics'!$D$89)*20)/(1.4) -> 855 | D16: =(G16)/(0.8 + (H15-1) * 1/J16 * 60/1 + 0.8 + 1.4 + K16) -> 666.49972 | F16: =I15*M16 + I15*('Weapon Specifics'!$D$89) -> 34733.3 | G16: =M16 * H15 + H15 * ('Weapon Specifics'!$D$89) -> 11977 | H16: =H15 -> 20 | I16: =I15 -> 58 | J16: =J15 -> 100 | K16: =K15 -> 3.57 | L16: =timeToEmpty(H15,I15,J16,K16) + ceiling(I15/20,1)*0.8 + ceiling(I15/20,1)*0.8 + I15*(1.4/20) -> 49 | M16: =M15 -> 539 | N16: N/A | O16: Does not deal precision damage; shoot 20 rounds > swap mode > shoot 20 rockets > reload
A17: Grenade Launchers | B17: Rapid-Fire | C17: =(G17)/(H17 * 1/J17 * 60/1) -> 1535 | D17: =(G17)/((H17-1) * 1/J17 * 60/1 + K17) -> 1040.678 | F17: =I17*M17 -> 18420 | G17: =M17 * H17 -> 4912 | H17: 8 | I17: ='Reserves Data (Reference)'!D76 -> 30 | J17: 150 | K17: 1.92 | L17: =timeToEmpty(H17,I17,J17,K17) -> 16.16 | M17: =450+164 -> 614 | N17: N/A
A18: Cascade Point | B18: Rapid-Fire | C18: =(G18)/(H18 * 1/J18 * 60/1) -> 2558.3333 | D18: =(G18)/((H18-1) * 1/J18 * 60/1 + K18) -> 1364.4444 | F18: =I18*M18 -> 18420 | G18: =M18 * H18 -> 4912 | H18: 8 | I18: =I17 -> 30 | J18: =J17/0.6 -> 250 | K18: 1.92 | L18: =timeToEmpty(H18,I18,J18,K18) -> 12 | M18: =M17 -> 614 | N18: N/A
B19: Adaptive | C19: =(G19)/(H19 * 1/J19 * 60/1) -> 1444 | D19: =(G19)/((H19-1) * 1/J19 * 60/1 + K19) -> 1035.1254 | F19: =I19*M19 -> 18772 | G19: =M19 * H19 -> 5776 | H19: 8 | I19: ='Reserves Data (Reference)'!D77 -> 26 | J19: 120 | K19: 2.08 | L19: =timeToEmpty(H19,I19,J19,K19) -> 17.24 | M19: =535+187 -> 722 | N19: N/A
A20: Cascade Point | B20: Adaptive | C20: =(G20)/(H20 * 1/J20 * 60/1) -> 2406.6667 | D20: =(G20)/((H20-1) * 1/J20 * 60/1 + K20) -> 1381.8182 | F20: =I20*M20 -> 18772 | G20: =M20 * H20 -> 5776 | H20: 8 | I20: =I19 -> 26 | J20: =J19/0.6 -> 200 | K20: 2.08 | L20: =timeToEmpty(H20,I20,J20,K20) -> 12.84 | M20: =M19 -> 722 | N20: N/A
B21: Compressed Wave | C21: =(G21)/(H21 * 1/J21 * 60/1) -> 1460 | D21: =(G21)/(H21 * 1/J21 * 60/1 + K21) -> 902.82686 | F21: =I21*M21 -> 18980 | G21: =M21 * H21 -> 5110 | H21: 7 | I21: ='Reserves Data (Reference)'!D78 -> 26 | J21: 120 | K21: 2.16 | L21: =I21*1/J21*60/1 + Floor(I21/H21,1) * K21 -> 19.48 | M21: 730 | N21: N/A
A22: Cascade Point | B22: Compressed Wave | C22: =(G22)/(H22 * 1/J22 * 60/1) -> 2433.3333 | D22: =(G22)/(H22 * 1/J22 * 60/1 + K22) -> 1199.5305 | F22: =I22*M22 -> 18980 | G22: =M22 * H22 -> 5110 | H22: =H21 -> 7 | I22: =I21 -> 26 | J22: =J21/0.6 -> 200 | K22: =K21 -> 2.16 | L22: =I22*1/J22*60/1 + Floor(I22/H22,1) * K22 -> 14.28 | M22: =M21 -> 730 | N22: N/A
A23: cata | B23: The Prospector | C23: =(G23)/(H23 * 1/J23 * 60/1) -> 1694 | D23: =(G23)/((H23-1) * 1/J23 * 60/1 + K23) -> 948.13433 | F23: =I23*M23 -> 18480 | G23: =M23*H23 -> 3696 | H23: =H24 -> 6 | I23: =I24 -> 30 | J23: =J24 -> 165 | K23: =K24 -> 2.08 | L23: =L24 -> 17.410909 | M23: =187+429 -> 616 | N23: N/A | O23: Assumes no bomblets contact the boss (DPS minimum)
A24: cata | B24: The Prospector | C24: =(G24)/(H24 * 1/J24 * 60/1) -> 2915 | D24: =(G24)/((H24-1) * 1/J24 * 60/1 + K24) -> 1631.5299 | F24: =I24*(M24+'Weapon Specifics'!$D$4*3) -> 31800 | G24: =(M24+'Weapon Specifics'!$D$4*3)*H24 -> 6360 | H24: 6 | I24: ='Reserves Data (Reference)'!D79 -> 30 | J24: 165 | K24: 2.08 | L24: =timeToEmpty(H24,I24,J24,K24) -> 17.410909 | M24: =M23 + 'Weapon Specifics'!D4*3 -> 838 | N24: N/A | O24: Assumes all bomblets contact the boss (DPS maximum)
A25: single-stick | B25: Anarchy | C25: =(M26+'Weapon Specifics'!D5*10/0.5)/10 -> 145.9 | D25: =C25 -> 145.9 | F25: =I25*M25 + I25 * 10/0.5 * 'Weapon Specifics'!D5 -> 42311 | G25: =M25 * H25 + H25 * 10/0.5 * 'Weapon Specifics'!D5 -> 8754 | H25: 6 | I25: ='Reserves Data (Reference)'!D80 -> 29 | J25: 150 | K25: 2.08 | L25: =I25*10 -> 290 | M25: 19 | N25: N/A | O25: Assumes a single grenade > wait out damage, reloading while waiting
A26: double-stick | B26: Anarchy | C26: =(M26+'Weapon Specifics'!D6*10/0.5)/10 -> 963.9 | D26: =C26 -> 963.9 | F26: =I26*M26 + floor(I26/2,1) * 10/0.5 * 'Weapon Specifics'!D6 + mod(I26, 2) * 10/0.5 * 'Weapon Specifics'!D5 -> 136671 | G26: =M26 * H26 + H26/2 * 10/0.5 * 'Weapon Specifics'!D6 -> 28974 | H26: 6 | I26: =I25 -> 29 | J26: 150 | K26: 2.08 | L26: =FLOOR(I26/2,1) * 10 + mod(I26, 2) * 10 -> 150 | M26: 19 | N26: N/A | O26: Assumes two grenades > wait out damage, reloading while waiting
A27: cata | B27: The Colony | C27: =(G27)/(H27 * 1/J27 * 60/1) -> 1766.3333 | D27: =(G27)/((H27-1) * 1/J27 * 60/1 + K27) -> 1192.126 | F27: =I27*M27 -> 18925 | G27: =M27 * H27 -> 6056 | H27: 8 | I27: ='Reserves Data (Reference)'!D81 -> 25 | J27: 140 | K27: 2.08 | L27: =timeToEmpty(H27,I27,J27,K27) -> 15.24 | M27: =715+42 -> 757 | N27: N/A
B28: Parasite | C28: =(G28)/(H28 * 1/J28 * 60/1) -> 4064 | D28: =(G28)/(K28) -> 976.92308 | F28: =I28*M28 -> 36576 | G28: =M28 * H28 -> 2032 | H28: 1 | I28: ='Reserves Data (Reference)'!D82 -> 18 | J28: 120 | K28: 2.08 | L28: =timeToEmpty(H28,I28,J28,K28) -> 35.36 | M28: =543+1489 -> 2032 | N28: N/A
A29: x20 WH on first, avg | B29: Parasite | C29: =C28 -> 4064 | D29: =(M29*(I29-1) + G29)/(K29 * (I29-1)) -> 1149.3213 | F29: =(I29-1)*M29 + G29 -> 40640 | G29: =M29*(1+0.1*20) -> 6096 | H29: 1 | I29: =I28 -> 18 | J29: 120 | K29: 2.08 | L29: =timeToEmpty(H29,I29,J29,K29) -> 35.36 | M29: =M28 -> 2032 | N29: N/A | O29: Assumes first shot is x20 Worm's Hunger, rest are 0x Worm's Hunger; Average DPS
A30: no charge, spamming | B30: Salvation's Grip | C30: =(G30)/(H30 * 1/J30 * 60/1) -> 1522 | D30: =(G30)/((H30-1) * 1/J30 * 60/1 + K30) -> 1068.0702 | F30: =I30*M30 -> 19025 | G30: =M30 * H30 -> 6088 | H30: 8 | I30: ='Reserves Data (Reference)'!D83 -> 25 | J30: 120 | K30: 2.2 | L30: =timeToEmpty(H30,I30,J30,K30) -> 17.1 | M30: =581+180 -> 761 | N30: N/A
A31: full charge, spamming | B31: Salvation's Grip | C31: =('Weapon Specifics'!$D$8*5 + 'Weapon Specifics'!$D$8*5 + 'Weapon Specifics'!$D$7)/(2 + 2 * 1/$J$30 * 60/1) -> 672 | D31: =C31 -> 672 | F31: =('Weapon Specifics'!D8*5 + 'Weapon Specifics'!D8*5 + 'Weapon Specifics'!D7) * (floor(I31/2,1)) + ('Elemental Effects'!$E$9 + 'Weapon Specifics'!D8*5 + 'Weapon Specifics'!D7) * mod(I31, 2) -> 25609 | G31: N/A | H31: 8 | I31: =I30 -> 25 | J31: =1/(1000/1000*1/60) -> 60 | K31: 2.2 | L31: =timeToEmpty(H31,I31,J31,K31) -> 27.6 | M31: ='Elemental Effects'!$E$7 -> 158 | N31: N/A | O31: Assumes boss naturally shatters on its own (no additional damage done from any other source)
A32: full charge, spamming | B32: Salvation's Grip | C32: =('Weapon Specifics'!$D$9*5+'Elemental Effects'!$E$9)/(1+1/$J$30*60) -> 390.66667 | D32: =C32 -> 390.66667 | F32: =('Weapon Specifics'!$D$9*5+'Elemental Effects'!$E$9)*I32 -> 14650 | G32: N/A | H32: 8 | I32: =I31 -> 25 | J32: =1/(1000/1000*1/60) -> 60 | K32: 2.2 | L32: =timeToEmpty(H32,I32,J32,K32) -> 27.6 | M32: ='Elemental Effects'!$E$7 -> 158 | N32: N/A | O32: Assumes boss is big enough that all crystals shatter as they spawn
A33: mix | B33: Salvation's Grip | C33: =(M33 + 'Elemental Effects'!$E$9 + 'Weapon Specifics'!$D$8*5) / (1 + 0.5 + 1/J30*60) -> 1156 | D33: =C33 -> 1156 | F33: =('Weapon Specifics'!D8*5 + 'Elemental Effects'!$E$9 + M33) * Floor(I33/2,1) + ('Weapon Specifics'!D8*5 + 'Elemental Effects'!$E$9) * mod(I33, 2) -> 29065 | G33: N/A | H33: 8 | I33: =I30 -> 25 | J33: =J31 -> 60 | K33: =K31 -> 2.2 | L33: =I33/2 * 2/(1 + 1*1/J30*60) -> 16.666667 | M33: =247+744 -> 991 | N33: N/A | O33: Full charge > normal shot > repeat
A34: full charge, spamming, WoF | B34: Salvation's Grip | C34: =('Elemental Effects'!$E$9 + ('Weapon Specifics'!$D$8+'Elemental Effects'!$E$8)*5+('Weapon Specifics'!$D$8+'Elemental Effects'!$E$8)*5 + 'Weapon Specifics'!$D$7)/(2 + 1/J34 * 60/1) -> 869 | D34: =C34 -> 869 | F34: =('Elemental Effects'!$E$9 + ('Weapon Specifics'!D8+'Elemental Effects'!$E$8)*5 + ('Weapon Specifics'!D8+'Elemental Effects'!$E$8)*5 + 'Weapon Specifics'!D7) * (floor(I34/2,1)) + ('Elemental Effects'!$E$9+('Weapon Specifics'!D8+'Elemental Effects'!$E$8)*5 + 'Weapon Specifics'!D7) * mod(I34, 2) -> 32816 | G34: N/A | H34: 8 | I34: =I33 -> 25 | J34: =1/(1000/1000*1/60) -> 60 | K34: 2.2 | L34: =timeToEmpty(H34,I34,J34,K34) -> 27.6 | M34: =M31 -> 158 | N34: N/A | O34: Whisper of Fissures; Assumes boss naturally shatters on its own
A35: full charge, spamming, WoF | B35: Salvation's Grip | C35: =(('Weapon Specifics'!$D$9 + 'Elemental Effects'!$E$8)*5+'Elemental Effects'!$E$9)/(1+1/$J$30*60) -> 467.33333 | D35: =C35 -> 467.33333 | F35: =(('Weapon Specifics'!$D$9 + 'Elemental Effects'!$E$8)*5+'Elemental Effects'!$E$9)*I35 -> 17525 | G35: N/A | H35: 8 | I35: =I34 -> 25 | J35: =1/(1000/1000*1/60) -> 60 | K35: 2.2 | L35: =timeToEmpty(H35,I35,J35,K35) -> 27.6 | M35: =M32 -> 158 | N35: N/A | O35: Whisper of Fissures; Assumes boss is bit enough that all crystals shatter as they spawn
A36: mix, WoF | B36: Salvation's Grip | C36: =(M36 + 'Elemental Effects'!$E$9 + ('Weapon Specifics'!D8+'Elemental Effects'!$E$8)*5) / (1 + 1/J33*60 + 0.5) -> 970.8 | D36: =C36 -> 970.8 | F36: =(M36 + ('Weapon Specifics'!D8+'Elemental Effects'!$E$8)*5+'Elemental Effects'!$E$9) * Floor(I36/2,1) + mod(I36, 2) * (('Weapon Specifics'!D8+'Elemental Effects'!$E$8)*5+'Elemental Effects'!$E$9) -> 30560 | G36: N/A | H36: 8 | I36: =I33 -> 25 | J36: =J34 -> 60 | K36: =K34 -> 2.2 | L36: =I36/2 * 2/(1 + 1*1/J33*60) -> 12.5 | M36: =M33 -> 991 | N36: N/A | O36: Whisper of Fissures; Full charge > normal shot > repeat
A37: Rocket Launchers | B37: Aggressive | C37: =(G37)/(H37 * 1/J37 * 60/1) -> 2294.875 | D37: =(M37)/(K37) -> 781.23404 | F37: =I37*M37 -> 16523.1 | G37: =M37 * H37 -> 1835.9 | H37: 1 | I37: ='Reserves Data (Reference)'!D84 -> 9 | J37: =1/0.8*60 -> 75 | K37: 2.35 | L37: =timeToEmpty(H37,I37,J37,K37) -> 18.8 | M37: =(1397+399*1.1) -> 1835.9 | N37: N/A | O37: Adaptive and Aggressive rocket launchers share the same damage
A38: Wolfpack Rounds | B38: Aggressive | C38: =(G38)/(H38 * 1/J38 * 60/1) -> 2894.875 | D38: =(M38)/(K38) -> 985.48936 | F38: =I38*M38 -> 20843.1 | G38: =M38 * H38 -> 2315.9 | H38: 1 | I38: =I37 -> 9 | J38: =J37 -> 75 | K38: 2.35 | L38: =L37 -> 18.8 | M38: =M37 + ('Weapon Specifics'!$D$92)*8 -> 2315.9 | N38: N/A
A39: Bipod | B39: Aggressive | C39: =(G39)/(H39 * 1/J39 * 60/1) -> 1721.1562 | D39: =(G39)/((H39-1) * 1/J39 * 60/1 + K39) -> 874.2381 | F39: =I39*M39 -> 19276.95 | G39: =M39 * H39 -> 2753.85 | H39: 2 | I39: ='Reserves Data (Reference)'!D85 -> 14 | J39: =J37 -> 75 | K39: 2.35 | L39: =timeToEmpty(H39,I39,J39,K39) -> 19.7 | M39: =M37*(1-0.25) -> 1376.925 | N39: N/A
A40: Bipod + Wolfpack Rounds | B40: Aggressive | C40: =(G40)/(H40 * 1/J40 * 60/1) -> 2321.1562 | D40: =(G40)/((H40-1) * 1/J40 * 60/1 + K40) -> 1179 | F40: =I40*M40 -> 25996.95 | G40: =M40 * H40 -> 3713.85 | H40: 2 | I40: =I39 -> 14 | J40: =J37 -> 75 | K40: 2.35 | L40: =L39 -> 19.7 | M40: =M39 + ('Weapon Specifics'!$D$92)*8 -> 1856.925 | N40: N/A
B41: Adaptive | C41: =(G41)/(H41 * 1/J41 * 60/1) -> 2086.25 | D41: =(M41)/(K41) -> 781.23404 | F41: =I41*M41 -> 16523.1 | G41: =M41 * H41 -> 1835.9 | H41: 1 | I41: ='Reserves Data (Reference)'!D86 -> 9 | J41: =1/0.88*60 -> 68.181818 | K41: 2.35 | L41: =timeToEmpty(H41,I41,J41,K41) -> 18.8 | M41: =M37 -> 1835.9 | N41: N/A | O41: Adaptive and Aggressive rocket launchers share the same damage
B42: High-Impact | C42: =(G42)/(H42 * 1/J42 * 60/1) -> 1720.7216 | D42: =(M42)/(K42) -> 710.25532 | F42: =I42*M42 -> 18360.1 | G42: =M42 * H42 -> 1669.1 | H42: 1 | I42: ='Reserves Data (Reference)'!D88 -> 11 | J42: =1/0.97*60 -> 61.85567 | K42: 2.35 | L42: =timeToEmpty(H42,I42,J42,K42) -> 23.5 | M42: =1481+171*1.1 -> 1669.1 | N42: N/A
A43: Wolfpack Rounds | B43: High-Impact | C43: =(G43)/(H43 * 1/J43 * 60/1) -> 2215.567 | D43: =(M43)/(K43) -> 914.51064 | F43: =I43*M43 -> 23640.1 | G43: =M43 * H43 -> 2149.1 | H43: =H42 -> 1 | I43: =I42 -> 11 | J43: =$J$42 -> 61.85567 | K43: =$K$42 -> 2.35 | L43: =L42 -> 23.5 | M43: =M42 + ('Weapon Specifics'!$D$92)*8 -> 2149.1 | N43: N/A
A44: Bipod | B44: High-Impact | C44: =(G44)/(H44 * 1/J44 * 60/1) -> 1290.5412 | D44: =(G44)/((H44-1) * 1/J44 * 60/1 + K44) -> 754.11145 | F44: =I44*M44 -> 20029.2 | G44: =M44 * H44 -> 2503.65 | H44: 2 | I44: ='Reserves Data (Reference)'!D89 -> 16 | J44: =$J$42 -> 61.85567 | K44: =$K$42 -> 2.35 | L44: =timeToEmpty(H44,I44,J44,K44) -> 24.21 | M44: =M42*(1-0.25) -> 1251.825 | N44: N/A
A45: Bipod + Wolfpack Rounds | B45: High-Impact | C45: =(G45)/(H45 * 1/J45 * 60/1) -> 1785.3866 | D45: =(G45)/((H45-1) * 1/J45 * 60/1 + K45) -> 1043.2681 | F45: =I45*M45 -> 27709.2 | G45: =M45 * H45 -> 3463.65 | H45: =H44 -> 2 | I45: =I44 -> 16 | J45: =$J$42 -> 61.85567 | K45: =$K$42 -> 2.35 | L45: =L44 -> 24.21 | M45: =M44 + ('Weapon Specifics'!$D$92)*8 -> 1731.825 | N45: N/A
B46: Precision | C46: =(G46)/(H46 * 1/J46 * 60/1) -> 1634.0206 | D46: =(M46)/(K46) -> 698.23789 | F46: =I46*M46 -> 17435 | G46: =M46 * H46 -> 1585 | H46: 1 | I46: ='Reserves Data (Reference)'!D90 -> 11 | J46: =J42 -> 61.85567 | K46: 2.27 | L46: =timeToEmpty(H46,I46,J46,K46) -> 22.7 | M46: =1206+379 -> 1585 | N46: N/A
A47: Wolfpack Rounds | B47: Precision | C47: =(G47)/(H47 * 1/J47 * 60/1) -> 2128.866 | D47: =(M47)/(K47) -> 909.69163 | F47: =I47*M47 -> 22715 | G47: =M47 * H47 -> 2065 | H47: =H46 -> 1 | I47: =I46 -> 11 | J47: =$J$46 -> 61.85567 | K47: =$K$46 -> 2.27 | L47: =L46 -> 22.7 | M47: =M46 + ('Weapon Specifics'!$D$92)*8 -> 2065 | N47: N/A
A48: Bipod | B48: Precision | C48: =(G48)/(H48 * 1/J48 * 60/1) -> 1225.5155 | D48: =(G48)/((H48-1) * 1/J48 * 60/1 + K48) -> 733.7963 | F48: =I48*M48 -> 19020 | G48: =M48 * H48 -> 2377.5 | H48: 2 | I48: ='Reserves Data (Reference)'!D91 -> 16 | J48: =$J$46 -> 61.85567 | K48: =$K$46 -> 2.27 | L48: =timeToEmpty(H48,I48,J48,K48) -> 23.65 | M48: =M46*(1-0.25) -> 1188.75 | N48: N/A
A49: Bipod + Wolfpack Rounds | B49: Precision | C49: =(G49)/(H49 * 1/J49 * 60/1) -> 1720.3608 | D49: =(G49)/((H49-1) * 1/J49 * 60/1 + K49) -> 1030.0926 | F49: =I49*M49 -> 26700 | G49: =M49 * H49 -> 3337.5 | H49: =H48 -> 2 | I49: =I48 -> 16 | J49: =$J$46 -> 61.85567 | K49: =$K$46 -> 2.27 | L49: =L48 -> 23.65 | M49: =M48 + ('Weapon Specifics'!$D$92)*8 -> 1668.75 | N49: N/A
B50: The Wardcliff Coil | C50: =(G50)/(H50 * 1/J50 * 60/1) -> 3120 | D50: =(M50)/(K50 + 0.7) -> 716.06557 | F50: =I50*M50 -> 17472 | G50: =M50 * H50 -> 2184 | H50: 1 | I50: ='Reserves Data (Reference)'!D92 -> 8 | J50: =1/0.7*60 -> 85.714286 | K50: 2.35 | L50: =timeToEmpty(H50,I50,J50,K50+0.7) -> 21.35 | M50: =(254+19)*8 -> 2184 | N50: N/A
B51: Two-Tailed Fox | C51: N/A | D51: =(M51)/(K51 + 0.22) -> 826.45914 | F51: =I51*M51 -> 21240 | G51: =M51 * H51 -> 2124 | H51: 1 | I51: ='Reserves Data (Reference)'!D93 -> 10 | J51: 40 | K51: 2.35 | L51: =timeToEmpty(H51,I51,J51,K51+0.33) -> 24.12 | M51: =2*(236+826) -> 2124 | N51: N/A | O51: Does not consider scorch; does not consider ignitions
A52: cata | B52: Two-Tailed Fox | C52: N/A | D52: =(M52 + 'Elemental Effects'!$E$5)/(K52 + 0.44) -> 865.15233 | F52: =I52*M52 -> 23137.75 | G52: =M52 * H52 -> 2313.775 | H52: 1 | I52: =I51 -> 10 | J52: =J51 -> 40 | K52: 2.35 | L52: =timeToEmpty(H52,I52,J52,K52+0.33) -> 24.12 | M52: =M51+'Weapon Specifics'!$D$91 + 'Elemental Effects'!$E$5 -> 2313.775 | N52: N/A | O52: Does not consider scorch; does not consider igntitions; considers jolt damage on every hit
B53: Two-Tailed Fox | C53: N/A | D53: =(M53)/(K53 + 0.22) + ('Elemental Effects'!$E$4)/((K53 + 0.22)*2) + 'Elemental Effects'!$E$13 -> 993.3331 | F53: =I53*M53+floor(I53/2,1)*'Elemental Effects'!$E$4 -> 24955 | G53: =M53 * H53 -> 2124 | H53: 1 | I53: =I51 -> 10 | J53: =J51 -> 40 | K53: 2.35 | L53: =timeToEmpty(H53,I53,J53,K53+0.33) -> 24.12 | M53: =M51 -> 2124 | N53: N/A | O53: Approximates scorch; considers ignitions
A54: cata | B54: Two-Tailed Fox | C54: N/A | D54: =(M54 + 'Elemental Effects'!$E$5)/(K54 + 0.44) + ('Elemental Effects'!$E$4)/((K54 + 0.44)*2) + 'Elemental Effects'!$E$13 -> 1020.6279 | F54: =I54*M54+floor(I54/2,1)*'Elemental Effects'!$E$4 -> 26852.75 | G54: =M54 * H54 -> 2313.775 | H54: 1 | I54: =I51 -> 10 | J54: =J51 -> 40 | K54: 2.35 | L54: =timeToEmpty(H54,I54,J54,K54+0.33) -> 24.12 | M54: =M52 -> 2313.775 | N54: N/A | O54: Approximates scorch; considers igntitions; considers jolt damage on every hit
B55: Eyes of Tomorrow | C55: =(G55)/(H55 * 1/J55 * 60/1) -> 2956.6265 | D55: =(M55)/(K55 + 0.83) -> 771.69811 | F55: =I55*M55 -> 24540 | G55: =M55 * H55 -> 2454 | H55: 1 | I55: ='Reserves Data (Reference)'!D94 -> 10 | J55: =1/0.83*60 -> 72.289157 | K55: 2.35 | L55: =timeToEmpty(H55,I55,J55,K55+0.9) -> 29.25 | M55: =(409)*6 -> 2454 | N55: N/A
A56: Adaptive Ordnance cancel | B56: Eyes of Tomorrow | C56: =(G56)/(H56 * 1/J56 * 60/1) -> 3695.7831 | D56: =(M56)/(K56 + 0.7) -> 1005.7377 | F56: =I56*M56 -> 30675 | G56: =M56 * H56 -> 3067.5 | H56: 1 | I56: =I55 -> 10 | J56: =J55 -> 72.289157 | K56: =K55 -> 2.35 | L56: =timeToEmpty(H56,I56,J56,K56+0.7) -> 27.45 | M56: =(M55*5/6)*1.5 -> 3067.5 | N56: N/A | O56: Assumes you fire only 5/6 of the volley to keep Adaptive Ordnance
B57: Truth | C57: =(G57)/(H57 * 1/48 * 60/1) -> 1303.2 | D57: =(G57)/((H57-1) * 1/J57 * 60/1 + K57) -> 995.31568 | F57: =I57*M57 -> 22806 | G57: =M57 * H57 -> 4887 | H57: 3 | I57: ='Reserves Data (Reference)'!D95 -> 14 | J57: =1/1.28*60 -> 46.875 | K57: 2.35 | L57: =timeToEmpty(H57,I57,48,K57) -> 20.65 | M57: 1629 | N57: N/A
B58: Gjallarhorn | C58: =(G58)/(H58 * 1/48 * 60/1) -> 1375.2 | D58: =(G58)/((H58-1) * 1/J58 * 60/1 + K58) -> 947.10744 | F58: =I58*M58 -> 18909 | G58: =M58 * H58 -> 3438 | H58: 2 | I58: ='Reserves Data (Reference)'!D96 -> 11 | J58: =1/1.28*60 -> 46.875 | K58: 2.35 | L58: =timeToEmpty(H58,I58,48,K58) -> 18 | M58: =128+1111 + ('Weapon Specifics'!$D$92)*8 -> 1719 | N58: N/A
A59: direct impact | B59: Deathbringer | C59: =(G59)/(H59 * 1/J59 * 60/1) -> 2100 | D59: =(M59)/(K59) -> 866.80851 | F59: =I59*M59 -> 22407 | G59: =M59 * H59 -> 2037 | H59: 1 | I59: ='Reserves Data (Reference)'!D97 -> 11 | J59: =J42 -> 61.85567 | K59: 2.35 | L59: =timeToEmpty(H59,I59,J59,K59) -> 23.5 | M59: =7*291 -> 2037 | N59: N/A | O59: Assumes all orbs have no travel time to build up damage
A60: max distance damage | B60: Deathbringer | C60: =(G60)/(H60 * 1/J60 * 60/1) -> 3644.3299 | D60: =(M60)/(K60) -> 1504.2553 | F60: =I60*M60 -> 38885 | G60: =M60 * H60 -> 3535 | H60: 1 | I60: =I59 -> 11 | J60: =J59 -> 61.85567 | K60: 2.35 | L60: =timeToEmpty(H60,I60,J60,K60) -> 23.5 | M60: =7*505 -> 3535 | N60: N/A | O60: Note that multiple people firing Deathbringer may cause projectiles to despawn
B61: Dragon's Breath | C61: =(G61)*J61*1/60 + 'Elemental Effects'!$E$4/3 + 'Elemental Effects'!$E$13 -> 1917.3077 | D61: =G61/(K61) + 'Elemental Effects'!$E$4/3 + (235+558)/2/0.56 -> 1635.6598 | F61: =G61*I61 -> 17576.9 | G61: =M61+'Weapon Specifics'!$D$93+'Weapon Specifics'!$D$95 -> 1597.9 | H61: 1 | I61: ='Reserves Data (Reference)'!D98 -> 11 | J61: =J42 -> 61.85567 | K61: 2.35 | L61: =timeToEmpty(H61,I61,J61,K61) -> 23.5 | M61: 171 | N61: N/A | O61: 1x fuel
B62: Dragon's Breath | C62: =(M61+'Weapon Specifics'!$D$93*3+'Weapon Specifics'!$D$95)/(3 + 0.75) + 'Elemental Effects'!$E$4/3 + 'Elemental Effects'!$E$13 + 'Weapon Specifics'!$D$94/0.5 -> 4166.9748 | D62: =C62 -> 4166.9748 | F62: =G62*I62 -> 55084.7 | G62: =M61+'Weapon Specifics'!$D$93*3+'Weapon Specifics'!$D$96+'Elemental Effects'!$E$4 -> 5007.7 | H62: 1 | I62: =I61 -> 11 | J62: =J42 -> 61.85567 | K62: 2.35 | L62: =1.5 + (I62-1)*(3 + 0.75) -> 39 | M62: =M61 -> 171 | N62: N/A | O62: 3x fuel, refueled by ignitions
B63: Dragon's Breath | C63: =(M61+'Weapon Specifics'!$D$93*5+'Weapon Specifics'!$D$97)/(3*2 + 0.75) + 'Elemental Effects'!$E$4/3 + 'Elemental Effects'!$E$13 + 'Weapon Specifics'!$D$94/0.5 -> 4034.9214 | D63: =C63 -> 4034.9214 | F63: =G63*I63 -> 88467.5 | G63: =M61+'Weapon Specifics'!$D$93*5+'Weapon Specifics'!$D$97+'Elemental Effects'!$E$4*2 -> 8042.5 | H63: 1 | I63: =I61 -> 11 | J63: =J42 -> 61.85567 | K63: 2.35 | L63: =1.5+3+(I63-1)*(3*2 + 0.75) -> 72 | M63: =M61 -> 171 | N63: N/A | O63: 5x fuel, refueled by ignitions
A64: Linear Fusion Rifles | B64: Precision | C64: =(G64)/(H64 * 1/J64 * 60/1) -> 938.8523 | D64: =(G64)/(H64 * 1/J64 * 60/1 + K64 - 0.53) -> 848.74256 | F64: =I64*N64 -> 20958 | G64: =N64 * H64 -> 6986 | H64: 7 | I64: ='Reserves Data (Reference)'!D99 -> 21 | J64: =1/((533*1/1000)*1/60 + 0.53*1/60) -> 56.444026 | K64: 1.32 | L64: =timeToEmpty_fusions(H64, I64, 0, 1, 0.533, 0.53, K64) -> 31.604 | M64: 290 | N64: 998
A65: Triple Tap | B65: Precision | C65: =(G65)/(H65 * 1/J65 * 60/1) -> 938.8523 | D65: =(G65)/(H65 * 1/J65 * 60/1 + K65 - 0.53) -> 873.90543 | F65: =I65*N65 -> 29940 | G65: =N65 * H65 -> 9980 | H65: =tripleTap(H64) -> 10 | I65: =H65*floor(I64/H64,1) + tripleTap(mod(I64,H64)) -> 30 | J65: =1/((533*1/1000)*1/60 + 0.53*1/60) -> 56.444026 | K65: 1.32 | L65: =timeToEmpty_fusions(H65, I65, 0, 1, 0.533, 0.53, K65) -> 44.36 | M65: =M64 -> 290 | N65: =N64 -> 998
A66: Fourth Time's The Charm | B66: Precision | C66: =(G66)/(H66 * 1/J66 * 60/1) -> 938.8523 | D66: =(G66)/(H66 * 1/J66 * 60/1 + K66 - 0.53) -> 879.43603 | F66: =I66*N66 -> 32934 | G66: =N66 * H66 -> 10978 | H66: =fourthTimesTheCharm(H64) -> 11 | I66: =H66*floor(I64/H64,1) + fourthTimesTheCharm(mod(I64,H64)) -> 33 | J66: =1/((533*1/1000)*1/60 + 0.53*1/60) -> 56.444026 | K66: 1.32 | L66: =timeToEmpty_fusions(H66, I66, 0, 1, 0.533, 0.53, K66) -> 48.612 | M66: =M64 -> 290 | N66: =N64 -> 998
B67: Adaptive Burst | C67: =(G67)/(H67 * 1/J67 * 60/1) -> 985.44699 | D67: =(G67)/(H67 * 1/J67 * 60/1 + K67 - (0.91 - 0.2*(3-1))) -> 912.29035 | F67: =I67*N67 -> 29862 | G67: =N67 * H67 -> 9954 | H67: 7 | I67: ='Reserves Data (Reference)'!D100 -> 21 | J67: =1/(533*1/1000*1/60 + 0.91*1/60) -> 41.580042 | K67: 1.32 | L67: =timeToEmpty_fusions(H67, I67, 0.2, 3, 0.533, 0.91, K67) -> 42.324 | M67: =138*3 -> 414 | N67: =474*3 -> 1422
A68: Marksman Sights | B68: The Queenbreaker | C68: =(G68)/(H68 * 1/J68 * 60/1) -> 1265.6664 | D68: =(G68)/(H68 * 1/J68 * 60/1 + K68 - 0.5) -> 1105.6284 | F68: =I68*N68 -> 30114 | G68: =N68 * H68 -> 7170 | H68: 5 | I68: ='Reserves Data (Reference)'!D101 -> 21 | J68: =1/((633*1/1000*1/60) + 0.5*1/60) -> 52.956752 | K68: 1.32 | L68: =timeToEmpty_fusions(H68, I68, 0, 1, 0.633, 0.5, K68) -> 26.573 | M68: 417 | N68: 1434 | O68: Fires a single bolt
A69: Combat Sights | B69: The Queenbreaker | C69: =(G69)/(H69 * 1/J69 * 60/1) -> 1297.2973 | D69: =(G69)/(H69 * 1/J69 * 60/1 + K69 - 0.5) -> 1164.9035 | F69: =I69*N69 -> 39312 | G69: =N69 * H69 -> 9360 | H69: 5 | I69: =I68 -> 21 | J69: =1/(533*1/1000 + 0.91)*60 -> 41.580042 | K69: 1.32 | L69: =timeToEmpty_fusions(H69, I69, 0.2, 3, 0.533, 0.91, K69) -> 33.033 | M69: =182*3 -> 546 | N69: =624*3 -> 1872 | O69: Fires in a burst
A70: cata | B70: Sleeper Simulant | C70: =(G70)/(H70 * 1/J70 * 60/1) -> 1583.2025 | D70: =(G70)/(H70 * 1/J70 * 60/1 + K70 - 0.5) -> 1363.7593 | F70: =I70*N70 -> 32272 | G70: =N70 * H70 -> 8068 | H70: 4 | I70: ='Reserves Data (Reference)'!D102 -> 16 | J70: =1/((774*1/1000*1/60) + 0.5*1/60) -> 47.095761 | K70: 1.32 | L70: =timeToEmpty_fusions(H70, I70, 0, 1, 0.774, 0.5, K70) -> 28.26 | M70: 1459 | N70: 2017
B71: Finality's Auger | C71: =(G71)/(H71 * 1/J71 * 60/1) -> 966.1181 | D71: =(G71)/(H71 * 1/J71 * 60/1 + K71 - 0.5) -> 853.23454 | F71: =I71*N71 -> #VALUE! | G71: =N71 * H71 -> 5988 | H71: 6 | I71: ='Reserves Data (Reference)'!D103 -> ??? | J71: =1/((533*1/1000*1/60) + 0.5*1/60) -> 58.083253 | K71: 1.32 | L71: =timeToEmpty_fusions(H71, I71, 0, 1, 0.774, 0.5, K71) -> #NUM! | M71: =M64 -> 290 | N71: =N64 -> 998 | O71: Base
A72: Swords | B72: SEE SWORDS PAGE | F72: SEE SWORDS PAGE
A73: Glaives | B73: Winterbite | C73: =('Weapon Specifics'!$D$98+'Weapon Specifics'!$D$100+'Elemental Effects'!$E$9 +'Weapon Specifics'!$D$99)/((2) * 1/J73 * 60/1) -> 424.875 | D73: =('Weapon Specifics'!$D$98+'Weapon Specifics'!$D$100+'Elemental Effects'!$E$9 +'Weapon Specifics'!$D$99 + 'Weapon Specifics'!$D$98+'Weapon Specifics'!$D$100 +'Elemental Effects'!$E$9)/((H73-1) * 1/J73 * 60/1 + K73) -> 506.76633 | F73: =I73*M73 -> 18252 | G73: =M73 * H73 -> 3042 | H73: 3 | I73: ='Reserves Data (Reference)'!D104 -> 18 | J73: 45 | K73: 1.57 | L73: =timeToEmpty(H73,I73,J73,K73) -> 23.85 | M73: ='Weapon Specifics'!$D$98+'Weapon Specifics'!$D$100+'Elemental Effects'!E9 -> 1014 | N73: N/A | O73: This assumes there is a freeze between every shot
A74: melee, w/ ammo | B74: Winterbite | C74: =(M74)*J74*1/60 + 'Elemental Effects'!E9/(8*1/J74*60) -> 404.27778 | D74: =C74 -> 404.27778 | F74: inf | G74: N/A | H74: N/A | I74: N/A | J74: =Specials!J109 -> 133.33333 | K74: N/A | L74: N/A | M74: =$M$76*1.2 -> 136.8 | N74: N/A | O74: Melee while blocking/ADS
A75: melee, w/ ammo | B75: Winterbite | C75: =(M75+M75+'Weapon Specifics'!D3*1.2)/(0.44+0.48+0.63) + 'Elemental Effects'!E9/(8*1/J75*60) -> 306.43548 | D75: =C75 -> 306.43548 | F75: inf | G75: N/A | H75: N/A | I75: N/A | J75: =Specials!J110 -> 116.12903 | K75: N/A | L75: N/A | M75: =$M$76*1.2 -> 136.8 | N75: N/A | O75: Melee without blocking/ADS
A76: melee, w/o ammo | B76: Winterbite | C76: =M76*J76*1/60 -> 253.33333 | D76: =C76 -> 253.33333 | F76: inf | G76: N/A | H76: N/A | I76: N/A | J76: =Specials!J109 -> 133.33333 | K76: N/A | L76: N/A | M76: =Specials!M107 -> 114 | N76: N/A | O76: Melee while blocking/ADS
A77: Sniper Rifles | B77: D.A.R.C.I. | C77: =(3*N77 + 'Elemental Effects'!E5)/(3 * 1/J77 * 60/1) -> 1788.1111 | D77: =(G77)/((H77-1) * 1/J77 * 60/1 + K77) -> 1248.0602 | F77: =I77*N77 + floor(I77/3,1)*'Elemental Effects'!E5 -> 23723 | G77: =N77 * H77 + floor(H77/3,1) * 'Elemental Effects'!$E$5 -> 5331 | H77: 7 | I77: ='Reserves Data (Reference)'!D105 -> 31 | J77: 140 | K77: 1.7 | L77: =timeToEmpty(H77,I77,J77,K77) -> 17.942857 | M77: 162 | N77: 733 | O77: Considers 100% uptime on Target Acquired; considers jolt
A78: cata | B78: D.A.R.C.I. | C78: =(3*N78 + 'Elemental Effects'!E5)/(3 * 1/J78 * 60/1) -> 1951.4444 | D78: =(N78*H78 + ROUNDDOWN(H78/3,0)*'Elemental Effects'!E5)/((H78-1) * 1/J78 * 60/1 + K78) -> 1362.7759 | F78: =G78 + (I78-H78)*N78 + floor((I78-H78)/3,1)*'Elemental Effects'!E5 -> 26616.845 | G78: =N77 * (1 + 1.028 + 1.062 + 1.091 + 1.125 + 1.159) + N78*(H78-5) + floor(H78/3,1) * 'Elemental Effects'!$E$5 -> 6544.845 | H78: =H77 -> 7 | I78: =I77 -> 31 | J78: =J77 -> 140 | K78: =K77 -> 1.7 | L78: =L77 -> 17.942857 | M78: =M77 -> 162 | N78: 803 | O78: Considers 100% uptime on Target Acquired; considers jolt, assumes usage without allies nearby
A79: cata | B79: D.A.R.C.I. | C79: =(3*N79 + 'Elemental Effects'!E5)/(3 * 1/J79 * 60/1) -> 2232.4944 | D79: =(N79*H79 + ROUNDDOWN(H79/3,0)*'Elemental Effects'!E5)/((H79-1) * 1/J79 * 60/1 + K79) -> 1560.1689 | F79: =G79 + (I79-H79)*N79 + floor((I79-H79)/3,1)*1.15*'Elemental Effects'!E5 -> 29868.545 | G79: =N77 * (1 + 1.028 + 1.062 + 1.091 + 1.125 + 1.159) + N79*(H79-5) + floor((H79)/3,1) * 'Elemental Effects'!$E$5 -> 6785.745 | H79: =H78 -> 7 | I79: =I78 -> 31 | J79: =J78 -> 140 | K79: =K78 -> 1.7 | L79: =L78 -> 17.942857 | M79: =M77*1.15 -> 186.3 | N79: =N78*1.15 -> 923.45 | O79: Considers 100% uptime on Target Acquired; considers jolt, assumes usage with allies nearby
B80: Whisper of the Worm | C80: =(G80)/(H80 * 1/J80 * 60/1) -> 969.81818 | D80: =C80 -> 969.81818 | F80: =I80*N80 -> 30710.909 | G80: =N80 * H80 -> 2424.5455 | H80: 3 | I80: =tripleTap('Reserves Data (Reference)'!$D$106) -> 38 | J80: 72 | K80: 1.98 | L80: =I80*1/J80*60 -> 31.666667 | M80: =255*1/1.1 -> 231.81818 | N80: =889*1/1.1 -> 808.18182
A81: cata | B81: Whisper of the Worm | C81: =(G81)/(H81 * 1/J81 * 60/1) -> 1428 | D81: =C81 -> 1428 | F81: =I81*N81 -> 45220 | G81: =N81 * H81 -> 3570 | H81: 3 | I81: =tripleTap('Reserves Data (Reference)'!D106) -> 38 | J81: 72 | K81: 1.98 | L81: =I81*1/J81*60 -> 31.666667 | M81: =278*1/1.1 -> 252.72727 | N81: =1309*1/1.1 -> 1190 | O81: Assumes 100% uptime on Whispered Breathing
A82: Shotguns | B82: Tractor Cannon | C82: =(G82)/(H82 * 1/J82 * 60/1) -> 664 | D82: =(G82)/((H82-1) * 1/J82 * 60/1 + K82) -> 583.9196 | F82: =I82*M82 -> 8964 | G82: =M82 * H82 -> 3486 | H82: 7 | I82: ='Reserves Data (Reference)'!D107 -> 18 | J82: 80 | K82: 1.47 | L82: =timeToEmpty(H82,I82,J82,K82) -> 14.19 | M82: =249*2 -> 498 | N82: N/A | O82: Assumes catalyst, base damage
A83: cata | B83: Legend of Acrius | C83: =(G83)/(H83 * 1/J83 * 60/1) -> 1175 | D83: =(G83)/((H83-1) * 1/J83 * 60/1 + K84*(H84-1) + 0.68) -> 928.34412 | F83: =I83*M83 -> 20509.091 | G83: =M83 * H83 -> 7690.9091 | H83: 6 | I83: ='Reserves Data (Reference)'!D108 -> 16 | J83: 55 | K83: 0.43 | L83: =timeToEmpty_shotgun(H83,I83,J83,K83) -> 21.131818 | M83: =(94*15*1/1.1) -> 1281.8182 | N83: =1555*1/1.1 -> 1413.6364 | O83: Considers reloading entire magazine
A84: cata w/ Trench Barrel | B84: Legend of Acrius | C84: =(G84 + 2*'Elemental Effects'!$E$3)/(floor(H84/3,1) * 1 + H84 * 1/J84 * 60/1) -> 1443.1489 | D84: =(G84 + 2*'Elemental Effects'!$E$3)/(floor(H84/3,1) * 1 + (H84-1) * 1/J84 * 60/1 + K84*(H84-1) + 0.68) -> 1199.1161 | F84: =I84*M84 -> 30763.636 | G84: =M84 * H84 + 2 * 'Elemental Effects'!$E$3 -> 11934.364 | H84: =H83 -> 6 | I84: =I83 -> 16 | J84: =J83 -> 55 | K84: =K83 -> 0.43 | L84: =timeToEmpty_shotgun(H84,I84,J84,K84) + floor(I84/3,1)*1 -> 26.131818 | M84: =M83*1.5 -> 1922.7273 | N84: =N83*1.5 -> 2120.4545 | O84: Melee > shoot > shoot > shoot; considers reloading entire magazine
A85: cata w/ Trench Barrel | B85: Legend of Acrius | C85: =(M85*3 + 2*'Elemental Effects'!$E$3)/(3*1/J85*60 + 1) -> 1443.1489 | D85: =C85 -> 1443.1489 | F85: =I85*M85 -> 30763.636 | G85: N/A | H85: 1 | I85: =I83 -> 16 | J85: =J83 -> 55 | K85: 0.68 | L85: =I85*1/J85*60/1 + floor(I85/3,1)*1 -> 22.454545 | M85: =M83*1.5 -> 1922.7273 | N85: =N83*1.5 -> 2120.4545 | O85: Melee > shoot > shoot > shoot; considers reload cancel the entire time
A86: Fusion Rifles | B86: One Thousand Voices | C86: =(G86)/(H86 * 1/J86 * 60/1) -> 1153.0055 | D86: =(G86)/(H86 * 1/J86 * 60/1 + K86 - (0.83-0.5)) -> 1024.2718 | F86: =I86*M86 + floor(I86/2,1)*'Weapon Specifics'!$D$101 -> 23180 | G86: =M86 * H86 + floor(H86/2,1) * 'Weapon Specifics'!$D$101 -> 8440 | H86: 4 | I86: ='Reserves Data (Reference)'!D109 -> 11 | J86: =1/((1000/1000 + 0.83) * 1/60) -> 32.786885 | K86: 1.25 | L86: =timeToEmpty_fusions(H86, I86, 0.02, 10, 1, 0.83, K86) -> 20.68 | M86: =10*(15+193) -> 2080 | N86: N/A | O86: Does not consider Scorch; with ignition
A87: Ember of Ashes | B87: One Thousand Voices | C87: =(G87)/(H87 * 1/J87 * 60/1) -> 1169.3989 | D87: =(G87)/(H87 * 1/J87 * 60/1 + K87 - (0.83-0.5)) -> 1038.835 | F87: =I87*(M87+'Weapon Specifics'!$D$101) -> 23540 | G87: =(M87 + 'Weapon Specifics'!$D$101) * H87 -> 8560 | H87: 4 | I87: =$I$86 -> 11 | J87: =1/((1000/1000 + 0.83) * 1/60) -> 32.786885 | K87: 1.25 | L87: =timeToEmpty_fusions(H87, I87, 0.02, 10, 1, 0.83, K87) -> 20.68 | M87: =10*(15+193) -> 2080 | N87: N/A | O87: Does not consider Scorch; with ignition; Ember of Ashes
B88: One Thousand Voices | C88: =(G88)/(H88 * 1/J88 * 60/1) -> 1136.612 | D88: =(G88)/(H88 * 1/J88 * 60/1 + K88 - (0.83-0.5)) -> 1009.7087 | F88: =I88*M88 -> 22880 | G88: =M88 * H88 -> 8320 | H88: 4 | I88: =$I$86 -> 11 | J88: =1/((1000/1000 + 0.83) * 1/60) -> 32.786885 | K88: 1.25 | L88: =L86 -> 20.68 | M88: =M86 -> 2080 | N88: N/A | O88: Does not consider Scorch; without ignition
A89: Bows | B89: Leviathan's Breath | C89: =D89 -> 1087.6556 | D89: =(G89)/(H89 * 1/J89 * 60/1) -> 1087.6556 | F89: =I89*N89 -> 18873 | G89: =N89 * H89 -> 2097 | H89: 1 | I89: ='Reserves Data (Reference)'!D110 -> 9 | J89: =1/(1328*1/1000*1/60 + K89*1/60) -> 31.120332 | K89: 0.6 | L89: =I89*1/J89*60/1 -> 17.352 | M89: =532+1152+'Elemental Effects'!E6 -> 1779 | N89: =850+1152+'Elemental Effects'!E6 -> 2097 | O89: Without catalyst
A90: cata | B90: Leviathan's Breath | C90: =D90 -> 1556.7929 | D90: =(G90)/(H90 * 1/J90 * 60/1) -> 1556.7929 | F90: =I90*N90 -> 29358 | G90: =N90 * H90 -> 2097 | H90: 1 | I90: ='Reserves Data (Reference)'!D111 -> 14 | J90: =1/(1328*(1-0.4375)*1/1000*1/60 + K90*1/60) -> 44.54343 | K90: 0.6 | L90: =I90*1/J90*60/1 -> 18.858 | M90: =M89 -> 1779 | N90: =N89 -> 2097 | O90: Assumes 100% uptime on Archer's Tempo
A91: Trace Rifles | B91: Microcosm | C91: =(G91)/(H91 * 1/J91 * 60/1) -> 1172.7273 | D91: =(G91)/((H91-1) * 1/J91 * 60/1 + K91) -> 1000.9052 | F91: =I91*N91 -> 30100 | G91: =N91 * H91 -> 9381.8182 | H91: 120 | I91: ='Reserves Data (Reference)'!$D$112 -> 385 | J91: 900 | K91: 1.44 | L91: =timeToEmpty(H91,I91,J91,K91) -> 29.72 | M91: =65*1/1.1 -> 59.090909 | N91: =86*1/1.1 -> 78.181818
A92: Paracausal Imbuement | B92: Microcosm | C92: =(G92)/(H92 * 1/J92 * 60/1) -> 1407.2727 | D92: =(G92)/((H92-1) * 1/J92 * 60/1 + K92) -> 1201.0863 | F92: =2*H92*N92 + N92 * (floor((20-(2*H92*1/J92*60+2*K92))*J92*1/60,1)) + N91 * (I92-(2*H92 + (floor((20-(2*H92*1/J92*60+2*K92))*J92*1/60,1)))) -> 34102.909 | G92: =N92 * H92 -> 11258.182 | H92: 120 | I92: ='Reserves Data (Reference)'!$D$112 -> 385 | J92: 900 | K92: 1.44 | L92: =timeToEmpty(H92,I92,J92,K92) -> 29.72 | M92: =M91*1.2 -> 70.909091 | N92: =N91*1.2 -> 93.818182 | O92: Grants +20% damage on end of super for 20 seconds

Sheet Swords
A1: !!! IMPORTANT: ALL SWORDS ASSUME SWORDMASTER'S GUARD + JAGGED EDGE + MASTERWORK + BACKUP MAG UNLESS OTHERWISE STATED !!! All weapon damage (except exotic) is normalized. Want to contribute? Have questions, comments, or concerns? See Home page for contact information.
A2: Sword | B2: Lucent Blades Count | C2: DPS: Waiting for Heavy to Recharge | D2: DPS: Not Waiting for Heavy to Recharge | F2: Theoretical Total Damage if Waiting for Heavy | G2: Theoretical Total Damage if Not Waiting for Heavy | H2: Reserves | I2: Average Swing Speed (spm) | J2: Heavy Swing Time (s) | K2: Recharge Delay (s) | L2: Time to Empty if Waiting for Heavy (s) | M2: Time to Empty if Not Waiting for Heavy (s) | N2: Time if Waiting for Heavy (s) | O2: Light Count until Waiting for Heavy | P2: Light Count until Heavy is Ready | Q2: Heavy Ammo Cost | R2: Light Attack Damage | S2: Heavy Attack Damage
A3: Adaptive | B3: 0 | C3: =(O3*R3 + S3) / (K3 + J3) -> 962.28571 | D3: =(P3*R3 + S3) / (P3*1/I3*60 + J3) -> 966.15385 | F3: =floor(H3/(O3+Q3),1)*(O3*R3+S3) + if(mod(H3, O3+Q3) > O3, (O3*R3+S3), mod(H3, O3+Q3)*R3) -> 26944 | G3: =floor(H3/(P3+Q3),1)*(P3*R3+S3) + if(mod(H3, P3+Q3) > P3, (P3*R3+S3), mod(H3, P3+Q3)*R3) -> 26376 | H3: ='Reserves Data (Reference)'!$D$113 -> 70 | I3: =(3)/((0.46+0.46+0.49)*1/60) -> 127.65957 | J3: 1.08 | K3: 2.42 | L3: =floor(H3/(O3+Q3),1)*(O3*1/I3*60+J3) + if(mod(H3, O3+Q3) > O3, (O3*1/I3*60+J3), mod(H3, O3+Q3)*1/I3*60) -> 27.44 | M3: =floor(H3/(P3+Q3),1)*(P3*1/I3*60+J3) + if(mod(H3, P3+Q3) > P3, (P3*1/I3*60+J3), mod(H3, P3+Q3)*1/I3*60) -> 27.3 | N3: =K3-(O3*1/I3*60) -> 0.07 | O3: =CEILING(K3*I3*1/60,1)-1 -> 5 | P3: =O3+1 -> 6 | Q3: 4 | R3: 400 | S3: =R3+242*4 -> 1368
B4: 1 | C4: =(O4*R4 + S4) / (K4 + J4) -> 982.78146 | D4: =(P4*R4 + S4) / (P4*1/I4*60 + J4) -> 981.9242 | F4: =floor(H4/(O4+Q4),1)*(O4*R4+S4) + if(mod(H4, O4+Q4) > O4, (O4*R4+S4), mod(H4, O4+Q4)*R4) -> 26712 | G4: =floor(H4/(P4+Q4),1)*(P4*R4+S4) + if(mod(H4, P4+Q4) > P4, (P4*R4+S4), mod(H4, P4+Q4)*R4) -> 26944 | H4: =$H$3 -> 70 | I4: =$I$3 -> 127.65957 | J4: =$J$3 -> 1.08 | K4: 1.94 | L4: =floor(H4/(O4+Q4),1)*(O4*1/I4*60+J4) + if(mod(H4, O4+Q4) > O4, (O4*1/I4*60+J4), mod(H4, O4+Q4)*1/I4*60) -> 26.64 | M4: =floor(H4/(P4+Q4),1)*(P4*1/I4*60+J4) + if(mod(H4, P4+Q4) > P4, (P4*1/I4*60+J4), mod(H4, P4+Q4)*1/I4*60) -> 27.44 | N4: =K4-(O4*1/I4*60) -> 0.06 | O4: =CEILING(K4*I4*1/60,1)-1 -> 4 | P4: =O4+1 -> 5 | Q4: =$Q$3 -> 4 | R4: =$R$3 -> 400 | S4: =S3 -> 1368
B5: 2 | C5: =(O5*R5 + S5) / (K5 + J5) -> 987.69231 | D5: =(P5*R5 + S5) / (P5*1/I5*60 + J5) -> 1002.7027 | F5: =floor(H5/(O5+Q5),1)*(O5*R5+S5) + if(mod(H5, O5+Q5) > O5, (O5*R5+S5), mod(H5, O5+Q5)*R5) -> 25680 | G5: =floor(H5/(P5+Q5),1)*(P5*R5+S5) + if(mod(H5, P5+Q5) > P5, (P5*R5+S5), mod(H5, P5+Q5)*R5) -> 26712 | H5: =$H$3 -> 70 | I5: =$I$3 -> 127.65957 | J5: =$J$3 -> 1.08 | K5: 1.52 | L5: =floor(H5/(O5+Q5),1)*(O5*1/I5*60+J5) + if(mod(H5, O5+Q5) > O5, (O5*1/I5*60+J5), mod(H5, O5+Q5)*1/I5*60) -> 24.9 | M5: =floor(H5/(P5+Q5),1)*(P5*1/I5*60+J5) + if(mod(H5, P5+Q5) > P5, (P5*1/I5*60+J5), mod(H5, P5+Q5)*1/I5*60) -> 26.64 | N5: =K5-(O5*1/I5*60) -> 0.11 | O5: =CEILING(K5*I5*1/60,1)-1 -> 3 | P5: =O5+1 -> 4 | Q5: =$Q$3 -> 4 | R5: =$R$3 -> 400 | S5: =S3 -> 1368
B6: 3 | C6: =(O6*R6 + S6) / (K6 + J6) -> 934.48276 | D6: =(P6*R6 + S6) / (P6*1/I6*60 + J6) -> 1031.3253 | F6: =floor(H6/(O6+Q6),1)*(O6*R6+S6) + if(mod(H6, O6+Q6) > O6, (O6*R6+S6), mod(H6, O6+Q6)*R6) -> 26016 | G6: =floor(H6/(P6+Q6),1)*(P6*R6+S6) + if(mod(H6, P6+Q6) > P6, (P6*R6+S6), mod(H6, P6+Q6)*R6) -> 25680 | H6: =$H$3 -> 70 | I6: =$I$3 -> 127.65957 | J6: =$J$3 -> 1.08 | K6: 1.24 | L6: =floor(H6/(O6+Q6),1)*(O6*1/I6*60+J6) + if(mod(H6, O6+Q6) > O6, (O6*1/I6*60+J6), mod(H6, O6+Q6)*1/I6*60) -> 24.24 | M6: =floor(H6/(P6+Q6),1)*(P6*1/I6*60+J6) + if(mod(H6, P6+Q6) > P6, (P6*1/I6*60+J6), mod(H6, P6+Q6)*1/I6*60) -> 24.9 | N6: =K6-(O6*1/I6*60) -> 0.3 | O6: =CEILING(K6*I6*1/60,1)-1 -> 2 | P6: =O6+1 -> 3 | Q6: =$Q$3 -> 4 | R6: =$R$3 -> 400 | S6: =S3 -> 1368
A7: Jump-Heavy | B7: 0 | C7: =(R7+S7)/(0.5+0.33+0.48) -> 540.45802 | D7: =(R7+S7)/(0.5+0.33+0.48) -> 540.45802 | F7: =floor(H7/(1+Q7),1)*(R7+S7)+mod(H7, (1+Q7))*R7 -> 24780 | G7: =floor(H7/(1+Q7),1)*(R7+S7)+mod(H7, (1+Q7))*R7 -> 24780 | H7: =$H$3 -> 70 | I7: =(2/(0.05+0.33+0.48))*60 -> 139.53488 | J7: 0.48 | K7: N/A | L7: =H7*1/I7*60 -> 30.1 | M7: =H7*1/I7*60 -> 30.1 | N7: N/A | O7: N/A | P7: N/A | Q7: 1 | R7: 333 | S7: 375
A8: Light Spam | B8: N/A | C8: =R8*I8*1/60 -> 851.06383 | D8: =R8*I8*1/60 -> 851.06383 | F8: =H8*R8 -> 28000 | G8: =H8*R8 -> 28000 | H8: =$H$3 -> 70 | I8: =$I$3 -> 127.65957 | J8: N/A | K8: N/A | L8: N/A | M8: N/A | N8: N/A | O8: N/A | P8: N/A | Q8: N/A | R8: =$R$3 -> 400 | S8: N/A
A9: Adaptive (Bequest) | B9: 0 | C9: =(O9*R9 + S9) / (K9 + J9) -> 1056.6038 | D9: =(P9*R9 + S9) / (P9*1/I9*60 + J9) -> 1093.2432 | F9: =floor(H9/(O9+Q9),1)*(O9*R9+S9) + if(mod(H9, O9+Q9) > O9, (O9*R9+S9), mod(H9, O9+Q9)*R9) -> 28000 | G9: =floor(H9/(P9+Q9),1)*(P9*R9+S9) + if(mod(H9, P9+Q9) > P9, (P9*R9+S9), mod(H9, P9+Q9)*R9) -> 29124 | H9: ='Reserves Data (Reference)'!$D$114 -> 69 | I9: =(3)/((0.46+0.46+0.49)*1/60) -> 127.65957 | J9: 1.08 | K9: 1.57 | L9: =floor(H9/(O9+Q9),1)*(O9*1/I9*60+J9) + if(mod(H9, O9+Q9) > O9, (O9*1/I9*60+J9), mod(H9, O9+Q9)*1/I9*60) -> 24.9 | M9: =floor(H9/(P9+Q9),1)*(P9*1/I9*60+J9) + if(mod(H9, P9+Q9) > P9, (P9*1/I9*60+J9), mod(H9, P9+Q9)*1/I9*60) -> 26.64 | N9: =K9-(O9*1/I9*60) -> 0.16 | O9: =CEILING(K9*I9*1/60,1)-1 -> 3 | P9: =O9+1 -> 4 | Q9: 4 | R9: 436 | S9: =R9 + 264*4 -> 1492
B10: 1 | C10: =(O10*R10 + S10) / (K10 + J10) -> 1060.0897 | D10: =(P10*R10 + S10) / (P10*1/I10*60 + J10) -> 1124.498 | F10: =floor(H10/(O10+Q10),1)*(O10*R10+S10) + if(mod(H10, O10+Q10) > O10, (O10*R10+S10), mod(H10, O10+Q10)*R10) -> 28368 | G10: =floor(H10/(P10+Q10),1)*(P10*R10+S10) + if(mod(H10, P10+Q10) > P10, (P10*R10+S10), mod(H10, P10+Q10)*R10) -> 28000 | H10: =$H$9 -> 69 | I10: =$I$9 -> 127.65957 | J10: =$J$9 -> 1.08 | K10: 1.15 | L10: =floor(H10/(O10+Q10),1)*(O10*1/I10*60+J10) + if(mod(H10, O10+Q10) > O10, (O10*1/I10*60+J10), mod(H10, O10+Q10)*1/I10*60) -> 24.24 | M10: =floor(H10/(P10+Q10),1)*(P10*1/I10*60+J10) + if(mod(H10, P10+Q10) > P10, (P10*1/I10*60+J10), mod(H10, P10+Q10)*1/I10*60) -> 24.9 | N10: =K10-(O10*1/I10*60) -> 0.21 | O10: =CEILING(K10*I10*1/60,1)-1 -> 2 | P10: =O10+1 -> 3 | Q10: =$Q$9 -> 4 | R10: =$R$9 -> 436 | S10: =S9 -> 1492
B11: 2 | C11: =(O11*R11 + S11) / (K11 + J11) -> 1064.8649 | D11: =(P11*R11 + S11) / (P11*1/I11*60 + J11) -> 1124.498 | F11: =floor(H11/(O11+Q11),1)*(O11*R11+S11) + if(mod(H11, O11+Q11) > O11, (O11*R11+S11), mod(H11, O11+Q11)*R11) -> 28368 | G11: =floor(H11/(P11+Q11),1)*(P11*R11+S11) + if(mod(H11, P11+Q11) > P11, (P11*R11+S11), mod(H11, P11+Q11)*R11) -> 28000 | H11: =$H$9 -> 69 | I11: =$I$9 -> 127.65957 | J11: =$J$9 -> 1.08 | K11: 1.14 | L11: =floor(H11/(O11+Q11),1)*(O11*1/I11*60+J11) + if(mod(H11, O11+Q11) > O11, (O11*1/I11*60+J11), mod(H11, O11+Q11)*1/I11*60) -> 24.24 | M11: =floor(H11/(P11+Q11),1)*(P11*1/I11*60+J11) + if(mod(H11, P11+Q11) > P11, (P11*1/I11*60+J11), mod(H11, P11+Q11)*1/I11*60) -> 24.9 | N11: =K11-(O11*1/I11*60) -> 0.2 | O11: =CEILING(K11*I11*1/60,1)-1 -> 2 | P11: =O11+1 -> 3 | Q11: =$Q$9 -> 4 | R11: =$R$9 -> 436 | S11: =S9 -> 1492
B12: 3 | C12: =(O12*R12 + S12) / (K12 + J12) -> 1064.8649 | D12: =(P12*R12 + S12) / (P12*1/I12*60 + J12) -> 1124.498 | F12: =floor(H12/(O12+Q12),1)*(O12*R12+S12) + if(mod(H12, O12+Q12) > O12, (O12*R12+S12), mod(H12, O12+Q12)*R12) -> 28368 | G12: =floor(H12/(P12+Q12),1)*(P12*R12+S12) + if(mod(H12, P12+Q12) > P12, (P12*R12+S12), mod(H12, P12+Q12)*R12) -> 28000 | H12: =$H$9 -> 69 | I12: =$I$9 -> 127.65957 | J12: =$J$9 -> 1.08 | K12: 1.14 | L12: =floor(H12/(O12+Q12),1)*(O12*1/I12*60+J12) + if(mod(H12, O12+Q12) > O12, (O12*1/I12*60+J12), mod(H12, O12+Q12)*1/I12*60) -> 24.24 | M12: =floor(H12/(P12+Q12),1)*(P12*1/I12*60+J12) + if(mod(H12, P12+Q12) > P12, (P12*1/I12*60+J12), mod(H12, P12+Q12)*1/I12*60) -> 24.9 | N12: =K12-(O12*1/I12*60) -> 0.2 | O12: =CEILING(K12*I12*1/60,1)-1 -> 2 | P12: =O12+1 -> 3 | Q12: =$Q$9 -> 4 | R12: =$R$9 -> 436 | S12: =S9 -> 1492
A13: Jump-Heavy | B13: 0 | C13: =(R13+S13)/(0.5+0.33+0.48) -> 590.07634 | D13: =(R13+S13)/(0.5+0.33+0.48) -> 590.07634 | F13: =floor(H13/(1+Q13),1)*(R13+S13)+mod(H13, (1+Q13))*R13 -> 26646 | G13: =floor(H13/(1+Q13),1)*(R13+S13)+mod(H13, (1+Q13))*R13 -> 26646 | H13: =$H$9 -> 69 | I13: =(2/(0.05+0.33+0.48))*60 -> 139.53488 | J13: 0.48 | K13: N/A | L13: =H13*1/I13*60 -> 29.67 | M13: =H13*1/I13*60 -> 29.67 | N13: N/A | O13: N/A | P13: N/A | Q13: 1 | R13: 364 | S13: 409
A14: Light Spam | B14: N/A | C14: =R14*I14*1/60 -> 927.65957 | D14: =R14*I14*1/60 -> 927.65957 | F14: =H14*R14 -> 30084 | G14: =H14*R14 -> 30084 | H14: =$H$9 -> 69 | I14: =$I$9 -> 127.65957 | J14: N/A | K14: N/A | L14: N/A | M14: N/A | N14: N/A | O14: N/A | P14: N/A | Q14: N/A | R14: =$R$9 -> 436 | S14: N/A
A15: Vortex | B15: 0 | C15: =(O15*R15 + S15) / (K15 + J15) -> 906.04027 | D15: =(P15*R15 + S15) / (P15*1/I15*60 + J15) -> 968.75 | F15: =floor(H15/(O15+Q15),1)*(O15*R15+S15) + if(mod(H15, O15+Q15) > O15, (O15*R15+S15), mod(H15, O15+Q15)*R15) -> 21600 | G15: =floor(H15/(P15+Q15),1)*(P15*R15+S15) + if(mod(H15, P15+Q15) > P15, (P15*R15+S15), mod(H15, P15+Q15)*R15) -> 21700 | H15: ='Reserves Data (Reference)'!$D$115 -> 68 | I15: =(3)/((0.46+0.46+0.49)*1/60) -> 127.65957 | J15: 1.32 | K15: 1.66 | L15: =floor(H15/(O15+Q15),1)*(O15*1/I15*60+J15) + if(mod(H15, O15+Q15) > O15, (O15*1/I15*60+J15), mod(H15, O15+Q15)*1/I15*60) -> 21.84 | M15: =floor(H15/(P15+Q15),1)*(P15*1/I15*60+J15) + if(mod(H15, P15+Q15) > P15, (P15*1/I15*60+J15), mod(H15, P15+Q15)*1/I15*60) -> 22.4 | N15: =K15-(O15*1/I15*60) -> 0.25 | O15: =CEILING(K15*I15*1/60,1)-1 -> 3 | P15: =O15+1 -> 4 | Q15: 6 | R15: =$R$3 -> 400 | S15: =250*6 -> 1500
B16: 1 | C16: =(O16*R16 + S16) / (K16 + J16) -> 934.95935 | D16: =(P16*R16 + S16) / (P16*1/I16*60 + J16) -> 989.01099 | F16: =floor(H16/(O16+Q16),1)*(O16*R16+S16) + if(mod(H16, O16+Q16) > O16, (O16*R16+S16), mod(H16, O16+Q16)*R16) -> 20700 | G16: =floor(H16/(P16+Q16),1)*(P16*R16+S16) + if(mod(H16, P16+Q16) > P16, (P16*R16+S16), mod(H16, P16+Q16)*R16) -> 21600 | H16: =$H$15 -> 68 | I16: =$I$15 -> 127.65957 | J16: =$J$15 -> 1.32 | K16: 1.14 | L16: =floor(H16/(O16+Q16),1)*(O16*1/I16*60+J16) + if(mod(H16, O16+Q16) > O16, (O16*1/I16*60+J16), mod(H16, O16+Q16)*1/I16*60) -> 20.34 | M16: =floor(H16/(P16+Q16),1)*(P16*1/I16*60+J16) + if(mod(H16, P16+Q16) > P16, (P16*1/I16*60+J16), mod(H16, P16+Q16)*1/I16*60) -> 21.84 | N16: =K16-(O16*1/I16*60) -> 0.2 | O16: =CEILING(K16*I16*1/60,1)-1 -> 2 | P16: =O16+1 -> 3 | Q16: =$Q$15 -> 6 | R16: =$R$15 -> 400 | S16: =S15 -> 1500
B17: 2 | C17: =(O17*R17 + S17) / (K17 + J17) -> 931.37255 | D17: =(P17*R17 + S17) / (P17*1/I17*60 + J17) -> 1017.6991 | F17: =floor(H17/(O17+Q17),1)*(O17*R17+S17) + if(mod(H17, O17+Q17) > O17, (O17*R17+S17), mod(H17, O17+Q17)*R17) -> 19000 | G17: =floor(H17/(P17+Q17),1)*(P17*R17+S17) + if(mod(H17, P17+Q17) > P17, (P17*R17+S17), mod(H17, P17+Q17)*R17) -> 20700 | H17: =$H$15 -> 68 | I17: =$I$15 -> 127.65957 | J17: =$J$15 -> 1.32 | K17: 0.72 | L17: =floor(H17/(O17+Q17),1)*(O17*1/I17*60+J17) + if(mod(H17, O17+Q17) > O17, (O17*1/I17*60+J17), mod(H17, O17+Q17)*1/I17*60) -> 17.9 | M17: =floor(H17/(P17+Q17),1)*(P17*1/I17*60+J17) + if(mod(H17, P17+Q17) > P17, (P17*1/I17*60+J17), mod(H17, P17+Q17)*1/I17*60) -> 20.34 | N17: =K17-(O17*1/I17*60) -> 0.25 | O17: =CEILING(K17*I17*1/60,1)-1 -> 1 | P17: =O17+1 -> 2 | Q17: =$Q$15 -> 6 | R17: =$R$15 -> 400 | S17: =S15 -> 1500
B18: 3 | C18: =(O18*R18 + S18) / (K18 + J18) -> 1010.6383 | D18: =(P18*R18 + S18) / (P18*1/I18*60 + J18) -> 1017.6991 | F18: =floor(H18/(O18+Q18),1)*(O18*R18+S18) + if(mod(H18, O18+Q18) > O18, (O18*R18+S18), mod(H18, O18+Q18)*R18) -> 19000 | G18: =floor(H18/(P18+Q18),1)*(P18*R18+S18) + if(mod(H18, P18+Q18) > P18, (P18*R18+S18), mod(H18, P18+Q18)*R18) -> 20700 | H18: =$H$15 -> 68 | I18: =$I$15 -> 127.65957 | J18: =$J$15 -> 1.32 | K18: 0.56 | L18: =floor(H18/(O18+Q18),1)*(O18*1/I18*60+J18) + if(mod(H18, O18+Q18) > O18, (O18*1/I18*60+J18), mod(H18, O18+Q18)*1/I18*60) -> 17.9 | M18: =floor(H18/(P18+Q18),1)*(P18*1/I18*60+J18) + if(mod(H18, P18+Q18) > P18, (P18*1/I18*60+J18), mod(H18, P18+Q18)*1/I18*60) -> 20.34 | N18: =K18-(O18*1/I18*60) -> 0.09 | O18: =CEILING(K18*I18*1/60,1)-1 -> 1 | P18: =O18+1 -> 2 | Q18: =$Q$15 -> 6 | R18: =$R$15 -> 400 | S18: =S15 -> 1500
A19: Jump-Heavy | B19: 0 | C19: =(R19+S19)/(0.5+0.33+0.48) -> 548.85496 | D19: =(R19+S19)/(0.5+0.33+0.48) -> 548.85496 | F19: =floor(H19/(1+Q19),1)*(R19+S19)+mod(H19, (1+Q19))*R19 -> 24446 | G19: =floor(H19/(1+Q19),1)*(R19+S19)+mod(H19, (1+Q19))*R19 -> 24446 | H19: =$H$15 -> 68 | I19: =(2/(0.05+0.33+0.48))*60 -> 139.53488 | J19: 0.48 | K19: N/A | L19: =H19*1/I19*60 -> 29.24 | M19: =H19*1/I19*60 -> 29.24 | N19: N/A | O19: N/A | P19: N/A | Q19: 1 | R19: =R7 -> 333 | S19: 386
A20: Light Spam | B20: N/A | C20: =R20*I20*1/60 -> 851.06383 | D20: =R20*I20*1/60 -> 851.06383 | F20: =H20*R20 -> 27200 | G20: =H20*R20 -> 27200 | H20: =$H$15 -> 68 | I20: =$I$15 -> 127.65957 | J20: N/A | K20: N/A | L20: N/A | M20: N/A | N20: N/A | O20: N/A | P20: N/A | Q20: N/A | R20: =$R$15 -> 400 | S20: N/A
A21: Caster | B21: 0 | C21: =(O21*R21 + S21) / (K21 + J21) -> 938.62816 | D21: =(P21*R21 + S21) / (P21*1/I21*60 + J21) -> 990.09901 | F21: =floor(H21/(O21+Q21),1)*(O21*R21+S21) + if(mod(H21, O21+Q21) > O21, (O21*R21+S21), mod(H21, O21+Q21)*R21) -> 23400 | G21: =floor(H21/(P21+Q21),1)*(P21*R21+S21) + if(mod(H21, P21+Q21) > P21, (P21*R21+S21), mod(H21, P21+Q21)*R21) -> 24000 | H21: ='Reserves Data (Reference)'!$D$116 -> 63 | I21: =(3)/((0.46+0.46+0.49)*1/60) -> 127.65957 | J21: 1.15 | K21: 1.62 | L21: =floor(H21/(O21+Q21),1)*(O21*1/I21*60+J21) + if(mod(H21, O21+Q21) > O21, (O21*1/I21*60+J21), mod(H21, O21+Q21)*1/I21*60) -> 23.04 | M21: =floor(H21/(P21+Q21),1)*(P21*1/I21*60+J21) + if(mod(H21, P21+Q21) > P21, (P21*1/I21*60+J21), mod(H21, P21+Q21)*1/I21*60) -> 24.24 | N21: =K21-(O21*1/I21*60) -> 0.21 | O21: =CEILING(K21*I21*1/60,1)-1 -> 3 | P21: =O21+1 -> 4 | Q21: 4 | R21: =$R$3 -> 400 | S21: =140*10 -> 1400
B22: 1 | C22: =(O22*R22 + S22) / (K22 + J22) -> 1000 | D22: =(P22*R22 + S22) / (P22*1/I22*60 + J22) -> 1015.625 | F22: =floor(H22/(O22+Q22),1)*(O22*R22+S22) + if(mod(H22, O22+Q22) > O22, (O22*R22+S22), mod(H22, O22+Q22)*R22) -> 24200 | G22: =floor(H22/(P22+Q22),1)*(P22*R22+S22) + if(mod(H22, P22+Q22) > P22, (P22*R22+S22), mod(H22, P22+Q22)*R22) -> 23400 | H22: =$H$21 -> 63 | I22: =$I$21 -> 127.65957 | J22: =$J$21 -> 1.15 | K22: 1.05 | L22: =floor(H22/(O22+Q22),1)*(O22*1/I22*60+J22) + if(mod(H22, O22+Q22) > O22, (O22*1/I22*60+J22), mod(H22, O22+Q22)*1/I22*60) -> 22.99 | M22: =floor(H22/(P22+Q22),1)*(P22*1/I22*60+J22) + if(mod(H22, P22+Q22) > P22, (P22*1/I22*60+J22), mod(H22, P22+Q22)*1/I22*60) -> 23.04 | N22: =K22-(O22*1/I22*60) -> 0.11 | O22: =CEILING(K22*I22*1/60,1)-1 -> 2 | P22: =O22+1 -> 3 | Q22: =$Q$21 -> 4 | R22: =$R$21 -> 400 | S22: =S21 -> 1400
B23: 2 | C23: =(O23*R23 + S23) / (K23 + J23) -> 913.70558 | D23: =(P23*R23 + S23) / (P23*1/I23*60 + J23) -> 1052.6316 | F23: =floor(H23/(O23+Q23),1)*(O23*R23+S23) + if(mod(H23, O23+Q23) > O23, (O23*R23+S23), mod(H23, O23+Q23)*R23) -> 23400 | G23: =floor(H23/(P23+Q23),1)*(P23*R23+S23) + if(mod(H23, P23+Q23) > P23, (P23*R23+S23), mod(H23, P23+Q23)*R23) -> 24200 | H23: =$H$21 -> 63 | I23: =$I$21 -> 127.65957 | J23: =$J$21 -> 1.15 | K23: 0.82 | L23: =floor(H23/(O23+Q23),1)*(O23*1/I23*60+J23) + if(mod(H23, O23+Q23) > O23, (O23*1/I23*60+J23), mod(H23, O23+Q23)*1/I23*60) -> 21.06 | M23: =floor(H23/(P23+Q23),1)*(P23*1/I23*60+J23) + if(mod(H23, P23+Q23) > P23, (P23*1/I23*60+J23), mod(H23, P23+Q23)*1/I23*60) -> 22.99 | N23: =K23-(O23*1/I23*60) -> 0.35 | O23: =CEILING(K23*I23*1/60,1)-1 -> 1 | P23: =O23+1 -> 2 | Q23: =$Q$21 -> 4 | R23: =$R$21 -> 400 | S23: =S21 -> 1400
B24: 3 | C24: =(O24*R24 + S24) / (K24 + J24) -> 913.70558 | D24: =(P24*R24 + S24) / (P24*1/I24*60 + J24) -> 1052.6316 | F24: =floor(H24/(O24+Q24),1)*(O24*R24+S24) + if(mod(H24, O24+Q24) > O24, (O24*R24+S24), mod(H24, O24+Q24)*R24) -> 23400 | G24: =floor(H24/(P24+Q24),1)*(P24*R24+S24) + if(mod(H24, P24+Q24) > P24, (P24*R24+S24), mod(H24, P24+Q24)*R24) -> 24200 | H24: =$H$21 -> 63 | I24: =$I$21 -> 127.65957 | J24: =$J$21 -> 1.15 | K24: 0.82 | L24: =floor(H24/(O24+Q24),1)*(O24*1/I24*60+J24) + if(mod(H24, O24+Q24) > O24, (O24*1/I24*60+J24), mod(H24, O24+Q24)*1/I24*60) -> 21.06 | M24: =floor(H24/(P24+Q24),1)*(P24*1/I24*60+J24) + if(mod(H24, P24+Q24) > P24, (P24*1/I24*60+J24), mod(H24, P24+Q24)*1/I24*60) -> 22.99 | N24: =K24-(O24*1/I24*60) -> 0.35 | O24: =CEILING(K24*I24*1/60,1)-1 -> 1 | P24: =O24+1 -> 2 | Q24: =$Q$21 -> 4 | R24: =$R$21 -> 400 | S24: =S21 -> 1400
A25: Jump-Heavy | B25: 0 | C25: =(R25+S25)/(0.5+0.33+0.48) -> 540.45802 | D25: =(R25+S25)/(0.5+0.33+0.48) -> 540.45802 | F25: =floor(H25/(1+Q25),1)*(R25+S25)+mod(H25, (1+Q25))*R25 -> 22281 | G25: =floor(H25/(1+Q25),1)*(R25+S25)+mod(H25, (1+Q25))*R25 -> 22281 | H25: =$H$21 -> 63 | I25: =(2/(0.05+0.33+0.48))*60 -> 139.53488 | J25: 0.48 | K25: N/A | L25: =H25*1/I25*60 -> 27.09 | M25: =H25*1/I25*60 -> 27.09 | N25: N/A | O25: N/A | P25: N/A | Q25: 1 | R25: =$R$7 -> 333 | S25: =$S$7 -> 375
A26: Light Spam | B26: N/A | C26: =R26*I26*1/60 -> 851.06383 | D26: =R26*I26*1/60 -> 851.06383 | F26: =H26*R26 -> 25200 | G26: =H26*R26 -> 25200 | H26: =$H$21 -> 63 | I26: =$I$21 -> 127.65957 | J26: N/A | K26: N/A | L26: N/A | M26: N/A | N26: N/A | O26: N/A | P26: N/A | Q26: N/A | R26: =$R$21 -> 400 | S26: N/A
A27: Wave Sword (30 Charge Rate) | B27: 0 | C27: =(O27*R27 + S27) / (K27 + J27) -> #VALUE! | D27: =(P27*R27 + S27) / (P27*1/I27*60 + J27) -> #VALUE! | F27: =floor(H27/(O27+Q27),1)*(O27*R27+S27) + if(mod(H27, O27+Q27) > O27, (O27*R27+S27), mod(H27, O27+Q27)*R27) -> #VALUE! | G27: =floor(H27/(P27+Q27),1)*(P27*R27+S27) + if(mod(H27, P27+Q27) > P27, (P27*R27+S27), mod(H27, P27+Q27)*R27) -> #VALUE! | H27: ='Reserves Data (Reference)'!$D$118 -> 69 | I27: =(3)/((0.46+0.46+0.49)*1/60) -> 127.65957 | J27: =0.73+0.92 -> 1.65 | K27: ??? | L27: =floor(H27/(O27+Q27),1)*(O27*1/I27*60+J27) + if(mod(H27, O27+Q27) > O27, (O27*1/I27*60+J27), mod(H27, O27+Q27)*1/I27*60) -> #VALUE! | M27: =floor(H27/(P27+Q27),1)*(P27*1/I27*60+J27) + if(mod(H27, P27+Q27) > P27, (P27*1/I27*60+J27), mod(H27, P27+Q27)*1/I27*60) -> #VALUE! | N27: =K27-(O27*1/I27*60) -> #VALUE! | O27: =CEILING(K27*I27*1/60,1)-1 -> #VALUE! | P27: =O27+1 -> #VALUE! | Q27: 4 | R27: ??? | S27: ???
B28: 1 | C28: =(O28*R28 + S28) / (K28 + J28) -> #VALUE! | D28: =(P28*R28 + S28) / (P28*1/I28*60 + J28) -> #VALUE! | F28: =floor(H28/(O28+Q28),1)*(O28*R28+S28) + if(mod(H28, O28+Q28) > O28, (O28*R28+S28), mod(H28, O28+Q28)*R28) -> #VALUE! | G28: =floor(H28/(P28+Q28),1)*(P28*R28+S28) + if(mod(H28, P28+Q28) > P28, (P28*R28+S28), mod(H28, P28+Q28)*R28) -> #VALUE! | H28: =H27 -> 69 | I28: =$I$27 -> 127.65957 | J28: =J27 -> 1.65 | K28: =K27 -> ??? | L28: =floor(H28/(O28+Q28),1)*(O28*1/I28*60+J28) + if(mod(H28, O28+Q28) > O28, (O28*1/I28*60+J28), mod(H28, O28+Q28)*1/I28*60) -> #VALUE! | M28: =floor(H28/(P28+Q28),1)*(P28*1/I28*60+J28) + if(mod(H28, P28+Q28) > P28, (P28*1/I28*60+J28), mod(H28, P28+Q28)*1/I28*60) -> #VALUE! | N28: =K28-(O28*1/I28*60) -> #VALUE! | O28: =CEILING(K28*I28*1/60,1)-1 -> #VALUE! | P28: =O28+1 -> #VALUE! | Q28: =Q27 -> 4 | R28: =R27 -> ??? | S28: =S27 -> ???
B29: 2 | C29: =(O29*R29 + S29) / (K29 + J29) -> #VALUE! | D29: =(P29*R29 + S29) / (P29*1/I29*60 + J29) -> #VALUE! | F29: =floor(H29/(O29+Q29),1)*(O29*R29+S29) + if(mod(H29, O29+Q29) > O29, (O29*R29+S29), mod(H29, O29+Q29)*R29) -> #VALUE! | G29: =floor(H29/(P29+Q29),1)*(P29*R29+S29) + if(mod(H29, P29+Q29) > P29, (P29*R29+S29), mod(H29, P29+Q29)*R29) -> #VALUE! | H29: =H27 -> 69 | I29: =$I$27 -> 127.65957 | J29: =J27 -> 1.65 | K29: =K27 -> ??? | L29: =floor(H29/(O29+Q29),1)*(O29*1/I29*60+J29) + if(mod(H29, O29+Q29) > O29, (O29*1/I29*60+J29), mod(H29, O29+Q29)*1/I29*60) -> #VALUE! | M29: =floor(H29/(P29+Q29),1)*(P29*1/I29*60+J29) + if(mod(H29, P29+Q29) > P29, (P29*1/I29*60+J29), mod(H29, P29+Q29)*1/I29*60) -> #VALUE! | N29: =K29-(O29*1/I29*60) -> #VALUE! | O29: =CEILING(K29*I29*1/60,1)-1 -> #VALUE! | P29: =O29+1 -> #VALUE! | Q29: =Q27 -> 4 | R29: =R27 -> ??? | S29: =S27 -> ???
B30: 3 | C30: =(O30*R30 + S30) / (K30 + J30) -> #VALUE! | D30: =(P30*R30 + S30) / (P30*1/I30*60 + J30) -> #VALUE! | F30: =floor(H30/(O30+Q30),1)*(O30*R30+S30) + if(mod(H30, O30+Q30) > O30, (O30*R30+S30), mod(H30, O30+Q30)*R30) -> #VALUE! | G30: =floor(H30/(P30+Q30),1)*(P30*R30+S30) + if(mod(H30, P30+Q30) > P30, (P30*R30+S30), mod(H30, P30+Q30)*R30) -> #VALUE! | H30: =H27 -> 69 | I30: =$I$27 -> 127.65957 | J30: =J27 -> 1.65 | K30: =K27 -> ??? | L30: =floor(H30/(O30+Q30),1)*(O30*1/I30*60+J30) + if(mod(H30, O30+Q30) > O30, (O30*1/I30*60+J30), mod(H30, O30+Q30)*1/I30*60) -> #VALUE! | M30: =floor(H30/(P30+Q30),1)*(P30*1/I30*60+J30) + if(mod(H30, P30+Q30) > P30, (P30*1/I30*60+J30), mod(H30, P30+Q30)*1/I30*60) -> #VALUE! | N30: =K30-(O30*1/I30*60) -> #VALUE! | O30: =CEILING(K30*I30*1/60,1)-1 -> #VALUE! | P30: =O30+1 -> #VALUE! | Q30: =Q27 -> 4 | R30: =R27 -> ??? | S30: =S27 -> ???
A31: Jump-Heavy | B31: 0 | C31: =(R31+S31)/(0.5+0.33+0.48) -> #VALUE! | D31: =(R31+S31)/(0.5+0.33+0.48) -> #VALUE! | F31: =floor(H31/(1+Q31),1)*(R31+S31)+mod(H31, (1+Q31))*R31 -> #VALUE! | G31: =floor(H31/(1+Q31),1)*(R31+S31)+mod(H31, (1+Q31))*R31 -> #VALUE! | H31: =H27 -> 69 | I31: =(2/(0.05+0.33+0.48))*60 -> 139.53488 | J31: 0.48 | K31: N/A | L31: =H31*1/I31*60 -> 29.67 | M31: =H31*1/I31*60 -> 29.67 | N31: N/A | O31: N/A | P31: N/A | Q31: 1 | R31: ??? | S31: ???
A32: Light Spam | B32: N/A | C32: =R32*I32*1/60 -> #VALUE! | D32: =R32*I32*1/60 -> #VALUE! | F32: =H32*R32 -> #VALUE! | G32: =H32*R32 -> #VALUE! | H32: =H27 -> 69 | I32: =$I$27 -> 127.65957 | J32: N/A | K32: N/A | L32: N/A | M32: N/A | N32: N/A | O32: N/A | P32: N/A | Q32: N/A | R32: =R27 -> ??? | S32: N/A
A33: Wave Sword (60 Charge Rate) | B33: 0 | C33: =(O33*R33 + S33) / (K33 + J33) -> 700.71685 | D33: =(P33*R33 + S33) / (P33*1/I33*60 + J33) -> 778.43137 | F33: =floor(H33/(O33+Q33),1)*(O33*R33+S33) + if(mod(H33, O33+Q33) > O33, (O33*R33+S33), mod(H33, O33+Q33)*R33) -> 23460 | G33: =floor(H33/(P33+Q33),1)*(P33*R33+S33) + if(mod(H33, P33+Q33) > P33, (P33*R33+S33), mod(H33, P33+Q33)*R33) -> 23820 | H33: ='Reserves Data (Reference)'!$D$118 -> 69 | I33: =(3)/((0.46+0.46+0.49)*1/60) -> 127.65957 | J33: =0.73+0.92 -> 1.65 | K33: 1.14 | L33: =floor(H33/(O33+Q33),1)*(O33*1/I33*60+J33) + if(mod(H33, O33+Q33) > O33, (O33*1/I33*60+J33), mod(H33, O33+Q33)*1/I33*60) -> 31.08 | M33: =floor(H33/(P33+Q33),1)*(P33*1/I33*60+J33) + if(mod(H33, P33+Q33) > P33, (P33*1/I33*60+J33), mod(H33, P33+Q33)*1/I33*60) -> 30.6 | N33: =K33-(O33*1/I33*60) -> 0.2 | O33: =CEILING(K33*I33*1/60,1)-1 -> 2 | P33: =O33+1 -> 3 | Q33: 4 | R33: 427 | S33: =603+498 -> 1101
B34: 1 | C34: =(O34*R34 + S34) / (K34 + J34) -> 661.47186 | D34: =(P34*R34 + S34) / (P34*1/I34*60 + J34) -> 754.82625 | F34: =floor(H34/(O34+Q34),1)*(O34*R34+S34) + if(mod(H34, O34+Q34) > O34, (O34*R34+S34), mod(H34, O34+Q34)*R34) -> 21392 | G34: =floor(H34/(P34+Q34),1)*(P34*R34+S34) + if(mod(H34, P34+Q34) > P34, (P34*R34+S34), mod(H34, P34+Q34)*R34) -> 23460 | H34: =H33 -> 69 | I34: =$I$27 -> 127.65957 | J34: =J33 -> 1.65 | K34: 0.66 | L34: =floor(H34/(O34+Q34),1)*(O34*1/I34*60+J34) + if(mod(H34, O34+Q34) > O34, (O34*1/I34*60+J34), mod(H34, O34+Q34)*1/I34*60) -> 29.68 | M34: =floor(H34/(P34+Q34),1)*(P34*1/I34*60+J34) + if(mod(H34, P34+Q34) > P34, (P34*1/I34*60+J34), mod(H34, P34+Q34)*1/I34*60) -> 31.08 | N34: =K34-(O34*1/I34*60) -> 0.19 | O34: =CEILING(K34*I34*1/60,1)-1 -> 1 | P34: =O34+1 -> 2 | Q34: =Q33 -> 4 | R34: =R33 -> 427 | S34: =S33 -> 1101
B35: 2 | C35: =(O35*R35 + S35) / (K35 + J35) -> 582.53968 | D35: =(P35*R35 + S35) / (P35*1/I35*60 + J35) -> 720.75472 | F35: =floor(H35/(O35+Q35),1)*(O35*R35+S35) + if(mod(H35, O35+Q35) > O35, (O35*R35+S35), mod(H35, O35+Q35)*R35) -> 19818 | G35: =floor(H35/(P35+Q35),1)*(P35*R35+S35) + if(mod(H35, P35+Q35) > P35, (P35*R35+S35), mod(H35, P35+Q35)*R35) -> 21392 | H35: =H33 -> 69 | I35: =$I$27 -> 127.65957 | J35: =J33 -> 1.65 | K35: 0.24 | L35: =floor(H35/(O35+Q35),1)*(O35*1/I35*60+J35) + if(mod(H35, O35+Q35) > O35, (O35*1/I35*60+J35), mod(H35, O35+Q35)*1/I35*60) -> 29.7 | M35: =floor(H35/(P35+Q35),1)*(P35*1/I35*60+J35) + if(mod(H35, P35+Q35) > P35, (P35*1/I35*60+J35), mod(H35, P35+Q35)*1/I35*60) -> 29.68 | N35: =K35-(O35*1/I35*60) -> 0.24 | O35: =CEILING(K35*I35*1/60,1)-1 -> 0 | P35: =O35+1 -> 1 | Q35: =Q33 -> 4 | R35: =R33 -> 427 | S35: =S33 -> 1101
B36: 3 | C36: =(O36*R36 + S36) / (K36 + J36) -> 625.56818 | D36: =(P36*R36 + S36) / (P36*1/I36*60 + J36) -> 720.75472 | F36: =floor(H36/(O36+Q36),1)*(O36*R36+S36) + if(mod(H36, O36+Q36) > O36, (O36*R36+S36), mod(H36, O36+Q36)*R36) -> 19818 | G36: =floor(H36/(P36+Q36),1)*(P36*R36+S36) + if(mod(H36, P36+Q36) > P36, (P36*R36+S36), mod(H36, P36+Q36)*R36) -> 21392 | H36: =H33 -> 69 | I36: =$I$27 -> 127.65957 | J36: =J33 -> 1.65 | K36: 0.11 | L36: =floor(H36/(O36+Q36),1)*(O36*1/I36*60+J36) + if(mod(H36, O36+Q36) > O36, (O36*1/I36*60+J36), mod(H36, O36+Q36)*1/I36*60) -> 29.7 | M36: =floor(H36/(P36+Q36),1)*(P36*1/I36*60+J36) + if(mod(H36, P36+Q36) > P36, (P36*1/I36*60+J36), mod(H36, P36+Q36)*1/I36*60) -> 29.68 | N36: =K36-(O36*1/I36*60) -> 0.11 | O36: =CEILING(K36*I36*1/60,1)-1 -> 0 | P36: =O36+1 -> 1 | Q36: =Q33 -> 4 | R36: =R33 -> 427 | S36: =S33 -> 1101
A37: Jump-Heavy | B37: 0 | C37: =(R37+S37)/(0.5+0.33+0.48) -> 577.8626 | D37: =(R37+S37)/(0.5+0.33+0.48) -> 577.8626 | F37: =floor(H37/(1+Q37),1)*(R37+S37)+mod(H37, (1+Q37))*R37 -> 26094 | G37: =floor(H37/(1+Q37),1)*(R37+S37)+mod(H37, (1+Q37))*R37 -> 26094 | H37: =H33 -> 69 | I37: =(2/(0.05+0.33+0.48))*60 -> 139.53488 | J37: 0.48 | K37: N/A | L37: =H37*1/I37*60 -> 29.67 | M37: =H37*1/I37*60 -> 29.67 | N37: N/A | O37: N/A | P37: N/A | Q37: 1 | R37: 356 | S37: 401
A38: Light Spam | B38: N/A | C38: =R38*I38*1/60 -> 908.51064 | D38: =R38*I38*1/60 -> 908.51064 | F38: =H38*R38 -> 29463 | G38: =H38*R38 -> 29463 | H38: =H33 -> 69 | I38: =$I$27 -> 127.65957 | J38: N/A | K38: N/A | L38: N/A | M38: N/A | N38: N/A | O38: N/A | P38: N/A | Q38: N/A | R38: =R33 -> 427 | S38: N/A
A39: Lightweight | B39: 0 | C39: =(O39*R39 + S39) / (K39 + J39) -> 993.47826 | D39: =(P39*R39 + S39) / (P39*1/I39*60 + J39) -> 998.33564 | F39: =floor(H39/(O39+Q39),1)*(O39*R39+S39) + if(mod(H39, O39+Q39) > O39, (O39*R39+S39), mod(H39, O39+Q39)*R39) -> 35189 | G39: =floor(H39/(P39+Q39),1)*(P39*R39+S39) + if(mod(H39, P39+Q39) > P39, (P39*R39+S39), mod(H39, P39+Q39)*R39) -> 34391 | H39: ='Reserves Data (Reference)'!$D$119 -> 86 | I39: =(4)/((0.43+0.49+0.43+0.42)*1/60) -> 135.59322 | J39: 0.95 | K39: 2.27 | L39: =floor(H39/(O39+Q39),1)*(O39*1/I39*60+J39) + if(mod(H39, O39+Q39) > O39, (O39*1/I39*60+J39), mod(H39, O39+Q39)*1/I39*60) -> 34.7875 | M39: =floor(H39/(P39+Q39),1)*(P39*1/I39*60+J39) + if(mod(H39, P39+Q39) > P39, (P39*1/I39*60+J39), mod(H39, P39+Q39)*1/I39*60) -> 34.6575 | N39: =K39-(O39*1/I39*60) -> 0.0575 | O39: =CEILING(K39*I39*1/60,1)-1 -> 5 | P39: =O39+1 -> 6 | Q39: 3 | R39: =$R$3 -> 400 | S39: 1199
B40: 1 | C40: =(O40*R40 + S40) / (K40 + J40) -> 1021.5328 | D40: =(P40*R40 + S40) / (P40*1/I40*60 + J40) -> 1011.5415 | F40: =floor(H40/(O40+Q40),1)*(O40*R40+S40) + if(mod(H40, O40+Q40) > O40, (O40*R40+S40), mod(H40, O40+Q40)*R40) -> 34388 | G40: =floor(H40/(P40+Q40),1)*(P40*R40+S40) + if(mod(H40, P40+Q40) > P40, (P40*R40+S40), mod(H40, P40+Q40)*R40) -> 35189 | H40: =$H$39 -> 86 | I40: =$I$39 -> 135.59322 | J40: =$J$39 -> 0.95 | K40: 1.79 | L40: =floor(H40/(O40+Q40),1)*(O40*1/I40*60+J40) + if(mod(H40, O40+Q40) > O40, (O40*1/I40*60+J40), mod(H40, O40+Q40)*1/I40*60) -> 33.525 | M40: =floor(H40/(P40+Q40),1)*(P40*1/I40*60+J40) + if(mod(H40, P40+Q40) > P40, (P40*1/I40*60+J40), mod(H40, P40+Q40)*1/I40*60) -> 34.7875 | N40: =K40-(O40*1/I40*60) -> 0.02 | O40: =CEILING(K40*I40*1/60,1)-1 -> 4 | P40: =O40+1 -> 5 | Q40: =$Q$39 -> 3 | R40: =$R$39 -> 400 | S40: =S39 -> 1199
B41: 2 | C41: =(O41*R41 + S41) / (K41 + J41) -> 1038.5281 | D41: =(P41*R41 + S41) / (P41*1/I41*60 + J41) -> 1029.0441 | F41: =floor(H41/(O41+Q41),1)*(O41*R41+S41) + if(mod(H41, O41+Q41) > O41, (O41*R41+S41), mod(H41, O41+Q41)*R41) -> 34386 | G41: =floor(H41/(P41+Q41),1)*(P41*R41+S41) + if(mod(H41, P41+Q41) > P41, (P41*R41+S41), mod(H41, P41+Q41)*R41) -> 34388 | H41: =$H$39 -> 86 | I41: =$I$39 -> 135.59322 | J41: =$J$39 -> 0.95 | K41: 1.36 | L41: =floor(H41/(O41+Q41),1)*(O41*1/I41*60+J41) + if(mod(H41, O41+Q41) > O41, (O41*1/I41*60+J41), mod(H41, O41+Q41)*1/I41*60) -> 32.77 | M41: =floor(H41/(P41+Q41),1)*(P41*1/I41*60+J41) + if(mod(H41, P41+Q41) > P41, (P41*1/I41*60+J41), mod(H41, P41+Q41)*1/I41*60) -> 33.525 | N41: =K41-(O41*1/I41*60) -> 0.0325 | O41: =CEILING(K41*I41*1/60,1)-1 -> 3 | P41: =O41+1 -> 4 | Q41: =$Q$39 -> 3 | R41: =$R$39 -> 400 | S41: =S39 -> 1199
B42: 3 | C42: =(O42*R42 + S42) / (K42 + J42) -> 925.46296 | D42: =(P42*R42 + S42) / (P42*1/I42*60 + J42) -> 1053.348 | F42: =floor(H42/(O42+Q42),1)*(O42*R42+S42) + if(mod(H42, O42+Q42) > O42, (O42*R42+S42), mod(H42, O42+Q42)*R42) -> 34383 | G42: =floor(H42/(P42+Q42),1)*(P42*R42+S42) + if(mod(H42, P42+Q42) > P42, (P42*R42+S42), mod(H42, P42+Q42)*R42) -> 34386 | H42: =$H$39 -> 86 | I42: =$I$39 -> 135.59322 | J42: =$J$39 -> 0.95 | K42: 1.21 | L42: =floor(H42/(O42+Q42),1)*(O42*1/I42*60+J42) + if(mod(H42, O42+Q42) > O42, (O42*1/I42*60+J42), mod(H42, O42+Q42)*1/I42*60) -> 31.6375 | M42: =floor(H42/(P42+Q42),1)*(P42*1/I42*60+J42) + if(mod(H42, P42+Q42) > P42, (P42*1/I42*60+J42), mod(H42, P42+Q42)*1/I42*60) -> 32.77 | N42: =K42-(O42*1/I42*60) -> 0.325 | O42: =CEILING(K42*I42*1/60,1)-1 -> 2 | P42: =O42+1 -> 3 | Q42: =$Q$39 -> 3 | R42: =$R$39 -> 400 | S42: =S39 -> 1199
A43: Jump-Heavy | B43: 0 | C43: =(R43+S43)/(0.5+0.46+0.49) -> 715.17241 | D43: =(R43+S43)/(0.5+0.46+0.49) -> 715.17241 | F43: =floor(H43/(1+Q43),1)*(R43+S43) +if(mod(H43, 1+Q43) > 1+Q43, (R43+S43), R43) -> 29324 | G43: =floor(H43/(1+Q43),1)*(R43+S43) +if(mod(H43, 1+Q43) > 1+Q43, (R43+S43), R43) -> 29324 | H43: =$H$39 -> 86 | I43: =(2/(0.05+0.46+0.49))*60 -> 120 | J43: 0.48 | K43: N/A | L43: =H43*1/I43*60 -> 43 | M43: =H43*1/I43*60 -> 43 | N43: N/A | O43: N/A | P43: N/A | Q43: 2 | R43: 288 | S43: 749
A44: Light Spam | B44: N/A | C44: =R44*I44*1/60 -> 903.9548 | D44: =R44*I44*1/60 -> 903.9548 | F44: =H44*R44 -> 34400 | G44: =H44*R44 -> 34400 | H44: =$H$39 -> 86 | I44: =$I$39 -> 135.59322 | J44: N/A | K44: N/A | L44: N/A | M44: N/A | N44: N/A | O44: N/A | P44: N/A | Q44: N/A | R44: =$R$39 -> 400 | S44: N/A
A45: Aggressive | B45: 0 | C45: =(O45*R45 + S45) / (K45 + J45) -> 939.26702 | D45: =(P45*R45 + S45) / (P45*1/I45*60 + J45) -> 1011.1111 | F45: =floor(H45/(O45+Q45),1)*(O45*R45+S45) + if(mod(H45, O45+Q45) > O45, (O45*R45+S45), mod(H45, O45+Q45)*R45) -> 33488 | G45: =floor(H45/(P45+Q45),1)*(P45*R45+S45) + if(mod(H45, P45+Q45) > P45, (P45*R45+S45), mod(H45, P45+Q45)*R45) -> 33488 | H45: ='Reserves Data (Reference)'!$D$120 -> 56 | I45: =(2)/((0.66+0.66)*1/60) -> 90.909091 | J45: 1.5 | K45: 2.32 | L45: =floor(H45/(O45+Q45),1)*(O45*1/I45*60+J45) + if(mod(H45, O45+Q45) > O45, (O45*1/I45*60+J45), mod(H45, O45+Q45)*1/I45*60) -> 32.64 | M45: =floor(H45/(P45+Q45),1)*(P45*1/I45*60+J45) + if(mod(H45, P45+Q45) > P45, (P45*1/I45*60+J45), mod(H45, P45+Q45)*1/I45*60) -> 33.12 | N45: =K45-(O45*1/I45*60) -> 0.34 | O45: =CEILING(K45*I45*1/60,1)-1 -> 3 | P45: =O45+1 -> 4 | Q45: 3 | R45: 598 | S45: 1794
B46: 1 | C46: =(O46*R46 + S46) / (K46 + J46) -> 866.66667 | D46: =(P46*R46 + S46) / (P46*1/I46*60 + J46) -> 1031.0345 | F46: =floor(H46/(O46+Q46),1)*(O46*R46+S46) + if(mod(H46, O46+Q46) > O46, (O46*R46+S46), mod(H46, O46+Q46)*R46) -> 33488 | G46: =floor(H46/(P46+Q46),1)*(P46*R46+S46) + if(mod(H46, P46+Q46) > P46, (P46*R46+S46), mod(H46, P46+Q46)*R46) -> 33488 | H46: =$H$45 -> 56 | I46: =$I$45 -> 90.909091 | J46: =$J$45 -> 1.5 | K46: 1.95 | L46: =floor(H46/(O46+Q46),1)*(O46*1/I46*60+J46) + if(mod(H46, O46+Q46) > O46, (O46*1/I46*60+J46), mod(H46, O46+Q46)*1/I46*60) -> 31.68 | M46: =floor(H46/(P46+Q46),1)*(P46*1/I46*60+J46) + if(mod(H46, P46+Q46) > P46, (P46*1/I46*60+J46), mod(H46, P46+Q46)*1/I46*60) -> 32.64 | N46: =K46-(O46*1/I46*60) -> 0.63 | O46: =CEILING(K46*I46*1/60,1)-1 -> 2 | P46: =O46+1 -> 3 | Q46: =$Q$45 -> 3 | R46: =R45 -> 598 | S46: =S45 -> 1794
B47: 2 | C47: =(O47*R47 + S47) / (K47 + J47) -> 973.94137 | D47: =(P47*R47 + S47) / (P47*1/I47*60 + J47) -> 1031.0345 | F47: =floor(H47/(O47+Q47),1)*(O47*R47+S47) + if(mod(H47, O47+Q47) > O47, (O47*R47+S47), mod(H47, O47+Q47)*R47) -> 33488 | G47: =floor(H47/(P47+Q47),1)*(P47*R47+S47) + if(mod(H47, P47+Q47) > P47, (P47*R47+S47), mod(H47, P47+Q47)*R47) -> 33488 | H47: =$H$45 -> 56 | I47: =$I$45 -> 90.909091 | J47: =$J$45 -> 1.5 | K47: 1.57 | L47: =floor(H47/(O47+Q47),1)*(O47*1/I47*60+J47) + if(mod(H47, O47+Q47) > O47, (O47*1/I47*60+J47), mod(H47, O47+Q47)*1/I47*60) -> 31.68 | M47: =floor(H47/(P47+Q47),1)*(P47*1/I47*60+J47) + if(mod(H47, P47+Q47) > P47, (P47*1/I47*60+J47), mod(H47, P47+Q47)*1/I47*60) -> 32.64 | N47: =K47-(O47*1/I47*60) -> 0.25 | O47: =CEILING(K47*I47*1/60,1)-1 -> 2 | P47: =O47+1 -> 3 | Q47: =$Q$45 -> 3 | R47: =R45 -> 598 | S47: =S45 -> 1794
B48: 3 | C48: =(O48*R48 + S48) / (K48 + J48) -> 1017.0068 | D48: =(P48*R48 + S48) / (P48*1/I48*60 + J48) -> 1031.0345 | F48: =floor(H48/(O48+Q48),1)*(O48*R48+S48) + if(mod(H48, O48+Q48) > O48, (O48*R48+S48), mod(H48, O48+Q48)*R48) -> 33488 | G48: =floor(H48/(P48+Q48),1)*(P48*R48+S48) + if(mod(H48, P48+Q48) > P48, (P48*R48+S48), mod(H48, P48+Q48)*R48) -> 33488 | H48: =$H$45 -> 56 | I48: =$I$45 -> 90.909091 | J48: =$J$45 -> 1.5 | K48: 1.44 | L48: =floor(H48/(O48+Q48),1)*(O48*1/I48*60+J48) + if(mod(H48, O48+Q48) > O48, (O48*1/I48*60+J48), mod(H48, O48+Q48)*1/I48*60) -> 31.68 | M48: =floor(H48/(P48+Q48),1)*(P48*1/I48*60+J48) + if(mod(H48, P48+Q48) > P48, (P48*1/I48*60+J48), mod(H48, P48+Q48)*1/I48*60) -> 32.64 | N48: =K48-(O48*1/I48*60) -> 0.12 | O48: =CEILING(K48*I48*1/60,1)-1 -> 2 | P48: =O48+1 -> 3 | Q48: =$Q$45 -> 3 | R48: =R45 -> 598 | S48: =S45 -> 1794
A49: Light Spam | B49: N/A | C49: =R49*I49*1/60 -> 906.06061 | D49: =R49*I49*1/60 -> 906.06061 | F49: =H49*R49 -> 33488 | G49: =H49*R49 -> 33488 | H49: =$H$45 -> 56 | I49: =$I$45 -> 90.909091 | J49: N/A | K49: N/A | L49: N/A | M49: N/A | N49: N/A | O49: N/A | P49: N/A | Q49: N/A | R49: =R45 -> 598 | S49: N/A
A50: Black Talon (x1 Heavy) | B50: 0 | C50: =(O50*R50 + S50) / (K50 + J50) -> 938.91213 | D50: =(P50*R50 + S50) / (P50*1/I50*60 + J50) -> 925.08834 | F50: =floor(H50/(O50+Q50),1)*(O50*R50+S50) + if(mod(H50, O50+Q50) > O50, (O50*R50+S50), mod(H50, O50+Q50)*R50) -> 22440 | G50: =floor(H50/(P50+Q50),1)*(P50*R50+S50) + if(mod(H50, P50+Q50) > P50, (P50*R50+S50), mod(H50, P50+Q50)*R50) -> 23562 | H50: ='Reserves Data (Reference)'!$D$121 -> 69 | I50: =(3)/((0.46+0.46+0.49)*1/60) -> 127.65957 | J50: 0.95 | K50: 1.44 | L50: =floor(H50/(O50+Q50),1)*(O50*1/I50*60+J50) + if(mod(H50, O50+Q50) > O50, (O50*1/I50*60+J50), mod(H50, O50+Q50)*1/I50*60) -> 23.6 | M50: =floor(H50/(P50+Q50),1)*(P50*1/I50*60+J50) + if(mod(H50, P50+Q50) > P50, (P50*1/I50*60+J50), mod(H50, P50+Q50)*1/I50*60) -> 25.47 | N50: =K50-(O50*1/I50*60) -> 0.03 | O50: =CEILING(K50*I50*1/60,1)-1 -> 3 | P50: =O50+1 -> 4 | Q50: 4 | R50: 374 | S50: =561*2 -> 1122
B51: 1 | C51: =(O51*R51 + S51) / (K51 + J51) -> 835.75419 | D51: =(P51*R51 + S51) / (P51*1/I51*60 + J51) -> 989.41799 | F51: =floor(H51/(O51+Q51),1)*(O51*R51+S51) + if(mod(H51, O51+Q51) > O51, (O51*R51+S51), mod(H51, O51+Q51)*R51) -> 20944 | G51: =floor(H51/(P51+Q51),1)*(P51*R51+S51) + if(mod(H51, P51+Q51) > P51, (P51*R51+S51), mod(H51, P51+Q51)*R51) -> 22440 | H51: =$H$50 -> 69 | I51: =$I$50 -> 127.65957 | J51: =$J$50 -> 0.95 | K51: 0.84 | L51: =floor(H51/(O51+Q51),1)*(O51*1/I51*60+J51) + if(mod(H51, O51+Q51) > O51, (O51*1/I51*60+J51), mod(H51, O51+Q51)*1/I51*60) -> 19.88 | M51: =floor(H51/(P51+Q51),1)*(P51*1/I51*60+J51) + if(mod(H51, P51+Q51) > P51, (P51*1/I51*60+J51), mod(H51, P51+Q51)*1/I51*60) -> 22.68 | N51: =K51-(O51*1/I51*60) -> 0.37 | O51: =CEILING(K51*I51*1/60,1)-1 -> 1 | P51: =O51+1 -> 2 | Q51: =$Q$50 -> 4 | R51: =$R$50 -> 374 | S51: =S50 -> 1122
B52: 2 | C52: =(O52*R52 + S52) / (K52 + J52) -> 890.47619 | D52: =(P52*R52 + S52) / (P52*1/I52*60 + J52) -> 989.41799 | F52: =floor(H52/(O52+Q52),1)*(O52*R52+S52) + if(mod(H52, O52+Q52) > O52, (O52*R52+S52), mod(H52, O52+Q52)*R52) -> 20944 | G52: =floor(H52/(P52+Q52),1)*(P52*R52+S52) + if(mod(H52, P52+Q52) > P52, (P52*R52+S52), mod(H52, P52+Q52)*R52) -> 22440 | H52: =$H$50 -> 69 | I52: =$I$50 -> 127.65957 | J52: =$J$50 -> 0.95 | K52: 0.73 | L52: =floor(H52/(O52+Q52),1)*(O52*1/I52*60+J52) + if(mod(H52, O52+Q52) > O52, (O52*1/I52*60+J52), mod(H52, O52+Q52)*1/I52*60) -> 19.88 | M52: =floor(H52/(P52+Q52),1)*(P52*1/I52*60+J52) + if(mod(H52, P52+Q52) > P52, (P52*1/I52*60+J52), mod(H52, P52+Q52)*1/I52*60) -> 22.68 | N52: =K52-(O52*1/I52*60) -> 0.26 | O52: =CEILING(K52*I52*1/60,1)-1 -> 1 | P52: =O52+1 -> 2 | Q52: =$Q$50 -> 4 | R52: =$R$50 -> 374 | S52: =S50 -> 1122
B53: 3 | C53: =(O53*R53 + S53) / (K53 + J53) -> 890.47619 | D53: =(P53*R53 + S53) / (P53*1/I53*60 + J53) -> 989.41799 | F53: =floor(H53/(O53+Q53),1)*(O53*R53+S53) + if(mod(H53, O53+Q53) > O53, (O53*R53+S53), mod(H53, O53+Q53)*R53) -> 20944 | G53: =floor(H53/(P53+Q53),1)*(P53*R53+S53) + if(mod(H53, P53+Q53) > P53, (P53*R53+S53), mod(H53, P53+Q53)*R53) -> 22440 | H53: =$H$50 -> 69 | I53: =$I$50 -> 127.65957 | J53: =$J$50 -> 0.95 | K53: 0.73 | L53: =floor(H53/(O53+Q53),1)*(O53*1/I53*60+J53) + if(mod(H53, O53+Q53) > O53, (O53*1/I53*60+J53), mod(H53, O53+Q53)*1/I53*60) -> 19.88 | M53: =floor(H53/(P53+Q53),1)*(P53*1/I53*60+J53) + if(mod(H53, P53+Q53) > P53, (P53*1/I53*60+J53), mod(H53, P53+Q53)*1/I53*60) -> 22.68 | N53: =K53-(O53*1/I53*60) -> 0.26 | O53: =CEILING(K53*I53*1/60,1)-1 -> 1 | P53: =O53+1 -> 2 | Q53: =$Q$50 -> 4 | R53: =$R$50 -> 374 | S53: =S50 -> 1122
A54: Light Spam | B54: N/A | C54: =R54*I54*1/60 -> 795.74468 | D54: =R54*I54*1/60 -> 795.74468 | F54: =H54*R54 -> 25806 | G54: =H54*R54 -> 25806 | H54: =$H$50 -> 69 | I54: =$I$50 -> 127.65957 | J54: N/A | K54: N/A | L54: N/A | M54: N/A | N54: N/A | O54: N/A | P54: N/A | Q54: N/A | R54: =$R$50 -> 374 | S54: N/A
A55: Black Talon (x2 Heavy) | B55: 0 | C55: =(O55*R55 + S55) / (K55 + J55) -> 1193.617 | D55: =(P55*R55 + S55) / (P55*1/I55*60 + J55) -> 1285.2234 | F55: =floor(H55/(O55+Q55),1)*(O55*R55+S55) + if(mod(H55, O55+Q55) > O55, (O55*R55+S55), mod(H55, O55+Q55)*R55) -> 21318 | G55: =floor(H55/(P55+Q55),1)*(P55*R55+S55) + if(mod(H55, P55+Q55) > P55, (P55*R55+S55), mod(H55, P55+Q55)*R55) -> 22440 | H55: =$H$50 -> 69 | I55: =$I$50 -> 127.65957 | J55: 1.03 | K55: 1.79 | L55: =floor(H55/(O55+Q55),1)*(O55*1/I55*60+J55) + if(mod(H55, O55+Q55) > O55, (O55*1/I55*60+J55), mod(H55, O55+Q55)*1/I55*60) -> 16.05 | M55: =floor(H55/(P55+Q55),1)*(P55*1/I55*60+J55) + if(mod(H55, P55+Q55) > P55, (P55*1/I55*60+J55), mod(H55, P55+Q55)*1/I55*60) -> 17.46 | N55: =K55-(O55*1/I55*60) -> 0.38 | O55: =CEILING(K55*I55*1/60,1)-1 -> 3 | P55: =O55+1 -> 4 | Q55: 8 | R55: =$R$50 -> 374 | S55: =$S$50*2 -> 2244
B56: 1 | C56: =(O56*R56 + S56) / (K56 + J56) -> 1341.704 | D56: =(P56*R56 + S56) / (P56*1/I56*60 + J56) -> 1379.5082 | F56: =floor(H56/(O56+Q56),1)*(O56*R56+S56) + if(mod(H56, O56+Q56) > O56, (O56*R56+S56), mod(H56, O56+Q56)*R56) -> 20944 | G56: =floor(H56/(P56+Q56),1)*(P56*R56+S56) + if(mod(H56, P56+Q56) > P56, (P56*R56+S56), mod(H56, P56+Q56)*R56) -> 21318 | H56: =$H$50 -> 69 | I56: =$I$50 -> 127.65957 | J56: =$J$55 -> 1.03 | K56: 1.2 | L56: =floor(H56/(O56+Q56),1)*(O56*1/I56*60+J56) + if(mod(H56, O56+Q56) > O56, (O56*1/I56*60+J56), mod(H56, O56+Q56)*1/I56*60) -> 13.79 | M56: =floor(H56/(P56+Q56),1)*(P56*1/I56*60+J56) + if(mod(H56, P56+Q56) > P56, (P56*1/I56*60+J56), mod(H56, P56+Q56)*1/I56*60) -> 16.05 | N56: =K56-(O56*1/I56*60) -> 0.26 | O56: =CEILING(K56*I56*1/60,1)-1 -> 2 | P56: =O56+1 -> 3 | Q56: =$Q$55 -> 8 | R56: =$R$50 -> 374 | S56: =$S$50*2 -> 2244
B57: 2 | C57: =(O57*R57 + S57) / (K57 + J57) -> 1411.3208 | D57: =(P57*R57 + S57) / (P57*1/I57*60 + J57) -> 1379.5082 | F57: =floor(H57/(O57+Q57),1)*(O57*R57+S57) + if(mod(H57, O57+Q57) > O57, (O57*R57+S57), mod(H57, O57+Q57)*R57) -> 20944 | G57: =floor(H57/(P57+Q57),1)*(P57*R57+S57) + if(mod(H57, P57+Q57) > P57, (P57*R57+S57), mod(H57, P57+Q57)*R57) -> 21318 | H57: =$H$50 -> 69 | I57: =$I$50 -> 127.65957 | J57: =$J$55 -> 1.03 | K57: 1.09 | L57: =floor(H57/(O57+Q57),1)*(O57*1/I57*60+J57) + if(mod(H57, O57+Q57) > O57, (O57*1/I57*60+J57), mod(H57, O57+Q57)*1/I57*60) -> 13.79 | M57: =floor(H57/(P57+Q57),1)*(P57*1/I57*60+J57) + if(mod(H57, P57+Q57) > P57, (P57*1/I57*60+J57), mod(H57, P57+Q57)*1/I57*60) -> 16.05 | N57: =K57-(O57*1/I57*60) -> 0.15 | O57: =CEILING(K57*I57*1/60,1)-1 -> 2 | P57: =O57+1 -> 3 | Q57: =$Q$55 -> 8 | R57: =$R$50 -> 374 | S57: =$S$50*2 -> 2244
B58: 3 | C58: =(O58*R58 + S58) / (K58 + J58) -> 1411.3208 | D58: =(P58*R58 + S58) / (P58*1/I58*60 + J58) -> 1379.5082 | F58: =floor(H58/(O58+Q58),1)*(O58*R58+S58) + if(mod(H58, O58+Q58) > O58, (O58*R58+S58), mod(H58, O58+Q58)*R58) -> 20944 | G58: =floor(H58/(P58+Q58),1)*(P58*R58+S58) + if(mod(H58, P58+Q58) > P58, (P58*R58+S58), mod(H58, P58+Q58)*R58) -> 21318 | H58: =$H$50 -> 69 | I58: =$I$50 -> 127.65957 | J58: =$J$55 -> 1.03 | K58: 1.09 | L58: =floor(H58/(O58+Q58),1)*(O58*1/I58*60+J58) + if(mod(H58, O58+Q58) > O58, (O58*1/I58*60+J58), mod(H58, O58+Q58)*1/I58*60) -> 13.79 | M58: =floor(H58/(P58+Q58),1)*(P58*1/I58*60+J58) + if(mod(H58, P58+Q58) > P58, (P58*1/I58*60+J58), mod(H58, P58+Q58)*1/I58*60) -> 16.05 | N58: =K58-(O58*1/I58*60) -> 0.15 | O58: =CEILING(K58*I58*1/60,1)-1 -> 2 | P58: =O58+1 -> 3 | Q58: =$Q$55 -> 8 | R58: =$R$50 -> 374 | S58: =$S$50*2 -> 2244
A59: Worldline Zero (Normal) | B59: 0 | C59: =(O59*R59 + S59) / (K59 + J59) -> 862.86426 | D59: =(P59*R59 + S59) / (P59*1/I59*60 + J59) -> 903.44988 | F59: =floor(H59/(O59+Q59),1)*(O59*R59+S59) + if(mod(H59, O59+Q59) > O59, (O59*R59+S59), mod(H59, O59+Q59)*R59) -> 25195.636 | G59: =floor(H59/(P59+Q59),1)*(P59*R59+S59) + if(mod(H59, P59+Q59) > P59, (P59*R59+S59), mod(H59, P59+Q59)*R59) -> 24664.182 | H59: ='Reserves Data (Reference)'!$D$122 -> 69 | I59: =(3)/((0.46+0.46+0.49)*1/60) -> 127.65957 | J59: 1.08 | K59: 2.57 | L59: =floor(H59/(O59+Q59),1)*(O59*1/I59*60+J59) + if(mod(H59, O59+Q59) > O59, (O59*1/I59*60+J59), mod(H59, O59+Q59)*1/I59*60) -> 27.44 | M59: =floor(H59/(P59+Q59),1)*(P59*1/I59*60+J59) + if(mod(H59, P59+Q59) > P59, (P59*1/I59*60+J59), mod(H59, P59+Q59)*1/I59*60) -> 27.3 | N59: =K59-(O59*1/I59*60) -> 0.22 | O59: =CEILING(K59*I59*1/60,1)-1 -> 5 | P59: =O59+1 -> 6 | Q59: 4 | R59: =R55 -> 374 | S59: =R59+249*4/1.1 -> 1279.4545
B60: 1 | C60: =(O60*R60 + S60) / (K60 + J60) -> 867.32955 | D60: =(P60*R60 + S60) / (P60*1/I60*60 + J60) -> 918.20832 | F60: =floor(H60/(O60+Q60),1)*(O60*R60+S60) + if(mod(H60, O60+Q60) > O60, (O60*R60+S60), mod(H60, O60+Q60)*R60) -> 24979.091 | G60: =floor(H60/(P60+Q60),1)*(P60*R60+S60) + if(mod(H60, P60+Q60) > P60, (P60*R60+S60), mod(H60, P60+Q60)*R60) -> 25195.636 | H60: =$H$59 -> 69 | I60: =$I$59 -> 127.65957 | J60: =$J$59 -> 1.08 | K60: 2.12 | L60: =floor(H60/(O60+Q60),1)*(O60*1/I60*60+J60) + if(mod(H60, O60+Q60) > O60, (O60*1/I60*60+J60), mod(H60, O60+Q60)*1/I60*60) -> 26.64 | M60: =floor(H60/(P60+Q60),1)*(P60*1/I60*60+J60) + if(mod(H60, P60+Q60) > P60, (P60*1/I60*60+J60), mod(H60, P60+Q60)*1/I60*60) -> 27.44 | N60: =K60-(O60*1/I60*60) -> 0.24 | O60: =CEILING(K60*I60*1/60,1)-1 -> 4 | P60: =O60+1 -> 5 | Q60: =$Q$59 -> 4 | R60: =$R$59 -> 374 | S60: =S59 -> 1279.4545
B61: 2 | C61: =(O61*R61 + S61) / (K61 + J61) -> 906.20926 | D61: =(P61*R61 + S61) / (P61*1/I61*60 + J61) -> 937.65356 | F61: =floor(H61/(O61+Q61),1)*(O61*R61+S61) + if(mod(H61, O61+Q61) > O61, (O61*R61+S61), mod(H61, O61+Q61)*R61) -> 24014.545 | G61: =floor(H61/(P61+Q61),1)*(P61*R61+S61) + if(mod(H61, P61+Q61) > P61, (P61*R61+S61), mod(H61, P61+Q61)*R61) -> 24979.091 | H61: =$H$59 -> 69 | I61: =$I$59 -> 127.65957 | J61: =$J$59 -> 1.08 | K61: 1.57 | L61: =floor(H61/(O61+Q61),1)*(O61*1/I61*60+J61) + if(mod(H61, O61+Q61) > O61, (O61*1/I61*60+J61), mod(H61, O61+Q61)*1/I61*60) -> 24.9 | M61: =floor(H61/(P61+Q61),1)*(P61*1/I61*60+J61) + if(mod(H61, P61+Q61) > P61, (P61*1/I61*60+J61), mod(H61, P61+Q61)*1/I61*60) -> 26.64 | N61: =K61-(O61*1/I61*60) -> 0.16 | O61: =CEILING(K61*I61*1/60,1)-1 -> 3 | P61: =O61+1 -> 4 | Q61: =$Q$59 -> 4 | R61: =$R$59 -> 374 | S61: =S59 -> 1279.4545
B62: 3 | C62: =(O62*R62 + S62) / (K62 + J62) -> 921.57025 | D62: =(P62*R62 + S62) / (P62*1/I62*60 + J62) -> 964.43958 | F62: =floor(H62/(O62+Q62),1)*(O62*R62+S62) + if(mod(H62, O62+Q62) > O62, (O62*R62+S62), mod(H62, O62+Q62)*R62) -> 24329.455 | G62: =floor(H62/(P62+Q62),1)*(P62*R62+S62) + if(mod(H62, P62+Q62) > P62, (P62*R62+S62), mod(H62, P62+Q62)*R62) -> 24014.545 | H62: =$H$59 -> 69 | I62: =$I$59 -> 127.65957 | J62: =$J$59 -> 1.08 | K62: 1.12 | L62: =floor(H62/(O62+Q62),1)*(O62*1/I62*60+J62) + if(mod(H62, O62+Q62) > O62, (O62*1/I62*60+J62), mod(H62, O62+Q62)*1/I62*60) -> 24.24 | M62: =floor(H62/(P62+Q62),1)*(P62*1/I62*60+J62) + if(mod(H62, P62+Q62) > P62, (P62*1/I62*60+J62), mod(H62, P62+Q62)*1/I62*60) -> 24.9 | N62: =K62-(O62*1/I62*60) -> 0.18 | O62: =CEILING(K62*I62*1/60,1)-1 -> 2 | P62: =O62+1 -> 3 | Q62: =$Q$59 -> 4 | R62: =$R$59 -> 374 | S62: =S59 -> 1279.4545
A63: Light Spam | B63: N/A | C63: =R63*I63*1/60 -> 795.74468 | D63: =R63*I63*1/60 -> 795.74468 | F63: =H63*R63 -> 25806 | G63: =H63*R63 -> 25806 | H63: =$H$59 -> 69 | I63: =$I$59 -> 127.65957 | J63: N/A | K63: N/A | L63: N/A | M63: N/A | N63: N/A | O63: N/A | P63: N/A | Q63: N/A | R63: =$R$59 -> 374 | S63: N/A
A64: Worldline Zero (1x T, cata) | B64: 0 | C64: =(O64*R64 + S64) / (K64 + J64) -> 477.84568 | D64: =(P64*R64 + S64) / (P64*1/I64*60 + J64) -> 548.3531 | F64: =floor(H64/(O64+Q64),1)*(O64*R64+S64) + if(mod(H64, O64+Q64) > O64, (O64*R64+S64), mod(H64, O64+Q64)*R64) -> 20066.364 | G64: =floor(H64/(P64+Q64),1)*(P64*R64+S64) + if(mod(H64, P64+Q64) > P64, (P64*R64+S64), mod(H64, P64+Q64)*R64) -> 20783.818 | H64: =$H$59 -> 69 | I64: =$I$59 -> 127.65957 | J64: =0.84+1.17 -> 2.01 | K64: =2.2+0.55 -> 2.75 | L64: =floor(H64/(O64+Q64),1)*(O64*1/I64*60+J64) + if(mod(H64, O64+Q64) > O64, (O64*1/I64*60+J64), mod(H64, O64+Q64)*1/I64*60) -> 37.23 | M64: =floor(H64/(P64+Q64),1)*(P64*1/I64*60+J64) + if(mod(H64, P64+Q64) > P64, (P64*1/I64*60+J64), mod(H64, P64+Q64)*1/I64*60) -> 36.63 | N64: =K64-(O64*1/I64*60) -> 0.4 | O64: =CEILING(K64*I64*1/60,1)-1 -> 5 | P64: =O64+1 -> 6 | Q64: 3 | R64: =$R$59 -> 374 | S64: =445/1.1 -> 404.54545 | T64: Substitutes Tesseract for heavy
B65: 1 | C65: =(O65*R65 + S65) / (K65 + J65) -> 456.86189 | D65: =(P65*R65 + S65) / (P65*1/I65*60 + J65) -> 521.68474 | F65: =floor(H65/(O65+Q65),1)*(O65*R65+S65) + if(mod(H65, O65+Q65) > O65, (O65*R65+S65), mod(H65, O65+Q65)*R65) -> 19005.455 | G65: =floor(H65/(P65+Q65),1)*(P65*R65+S65) + if(mod(H65, P65+Q65) > P65, (P65*R65+S65), mod(H65, P65+Q65)*R65) -> 20066.364 | H65: =$H$59 -> 69 | I65: =$I$59 -> 127.65957 | J65: =$J$64 -> 2.01 | K65: =1.76+0.39 -> 2.15 | L65: =floor(H65/(O65+Q65),1)*(O65*1/I65*60+J65) + if(mod(H65, O65+Q65) > O65, (O65*1/I65*60+J65), mod(H65, O65+Q65)*1/I65*60) -> 38.9 | M65: =floor(H65/(P65+Q65),1)*(P65*1/I65*60+J65) + if(mod(H65, P65+Q65) > P65, (P65*1/I65*60+J65), mod(H65, P65+Q65)*1/I65*60) -> 37.23 | N65: =K65-(O65*1/I65*60) -> 0.27 | O65: =CEILING(K65*I65*1/60,1)-1 -> 4 | P65: =O65+1 -> 5 | Q65: =$Q$64 -> 3 | R65: =$R$59 -> 374 | S65: =S64 -> 404.54545 | T65: Substitutes Tesseract for heavy
B66: 2 | C66: =(O66*R66 + S66) / (K66 + J66) -> 419.38062 | D66: =(P66*R66 + S66) / (P66*1/I66*60 + J66) -> 488.5721 | F66: =floor(H66/(O66+Q66),1)*(O66*R66+S66) + if(mod(H66, O66+Q66) > O66, (O66*R66+S66), mod(H66, O66+Q66)*R66) -> 17914 | G66: =floor(H66/(P66+Q66),1)*(P66*R66+S66) + if(mod(H66, P66+Q66) > P66, (P66*R66+S66), mod(H66, P66+Q66)*R66) -> 19005.455 | H66: =$H$59 -> 69 | I66: =$I$59 -> 127.65957 | J66: =$J$64 -> 2.01 | K66: =1.34+0.29 -> 1.63 | L66: =floor(H66/(O66+Q66),1)*(O66*1/I66*60+J66) + if(mod(H66, O66+Q66) > O66, (O66*1/I66*60+J66), mod(H66, O66+Q66)*1/I66*60) -> 39.03 | M66: =floor(H66/(P66+Q66),1)*(P66*1/I66*60+J66) + if(mod(H66, P66+Q66) > P66, (P66*1/I66*60+J66), mod(H66, P66+Q66)*1/I66*60) -> 38.9 | N66: =K66-(O66*1/I66*60) -> 0.22 | O66: =CEILING(K66*I66*1/60,1)-1 -> 3 | P66: =O66+1 -> 4 | Q66: =$Q$64 -> 3 | R66: =$R$59 -> 374 | S66: =S64 -> 404.54545 | T66: Substitutes Tesseract for heavy
B67: 3 | C67: =(O67*R67 + S67) / (K67 + J67) -> 441.19811 | D67: =(P67*R67 + S67) / (P67*1/I67*60 + J67) -> 488.5721 | F67: =floor(H67/(O67+Q67),1)*(O67*R67+S67) + if(mod(H67, O67+Q67) > O67, (O67*R67+S67), mod(H67, O67+Q67)*R67) -> 17914 | G67: =floor(H67/(P67+Q67),1)*(P67*R67+S67) + if(mod(H67, P67+Q67) > P67, (P67*R67+S67), mod(H67, P67+Q67)*R67) -> 19005.455 | H67: =$H$59 -> 69 | I67: =$I$59 -> 127.65957 | J67: =$J$64 -> 2.01 | K67: =1.21+0.24 -> 1.45 | L67: =floor(H67/(O67+Q67),1)*(O67*1/I67*60+J67) + if(mod(H67, O67+Q67) > O67, (O67*1/I67*60+J67), mod(H67, O67+Q67)*1/I67*60) -> 39.03 | M67: =floor(H67/(P67+Q67),1)*(P67*1/I67*60+J67) + if(mod(H67, P67+Q67) > P67, (P67*1/I67*60+J67), mod(H67, P67+Q67)*1/I67*60) -> 38.9 | N67: =K67-(O67*1/I67*60) -> 0.04 | O67: =CEILING(K67*I67*1/60,1)-1 -> 3 | P67: =O67+1 -> 4 | Q67: =$Q$64 -> 3 | R67: =$R$59 -> 374 | S67: =S64 -> 404.54545 | T67: Substitutes Tesseract for heavy
A68: Heartshadow (cata) | B68: 0 | C68: =(O68*R68 + S68) / (K68 + J68) -> 1178.3172 | D68: =(P68*R68 + S68) / (P68*1/I68*60 + J68) -> 1150.2857 | F68: =floor(H68/(O68+Q68),1)*(O68*R68+S68) + if(mod(H68, O68+Q68) > O68, (O68*R68+S68), mod(H68, O68+Q68)*R68) -> 32769 | G68: =floor(H68/(P68+Q68),1)*(P68*R68+S68) + if(mod(H68, P68+Q68) > P68, (P68*R68+S68), mod(H68, P68+Q68)*R68) -> 32208 | H68: ='Reserves Data (Reference)'!$D$123 -> 63 | I68: =(3)/((0.46+0.46+0.49)*1/60) -> 127.65957 | J68: 1.15 | K68: 1.94 | L68: =floor(H68/(O68+Q68),1)*(O68*1/I68*60+J68) + if(mod(H68, O68+Q68) > O68, (O68*1/I68*60+J68), mod(H68, O68+Q68)*1/I68*60) -> 27.27 | M68: =floor(H68/(P68+Q68),1)*(P68*1/I68*60+J68) + if(mod(H68, P68+Q68) > P68, (P68*1/I68*60+J68), mod(H68, P68+Q68)*1/I68*60) -> 28 | N68: =K68-(O68*1/I68*60) -> 0.06 | O68: =CEILING(K68*I68*1/60,1)-1 -> 4 | P68: =O68+1 -> 5 | Q68: 3 | R68: 385 | S68: =(433+417*4) -> 2101 | T68: Base Damage, no buffs
B69: 1 | C69: =(O69*R69 + S69) / (K69 + J69) -> 1262.0155 | D69: =(P69*R69 + S69) / (P69*1/I69*60 + J69) -> 1201.6502 | F69: =floor(H69/(O69+Q69),1)*(O69*R69+S69) + if(mod(H69, O69+Q69) > O69, (O69*R69+S69), mod(H69, O69+Q69)*R69) -> 33715 | G69: =floor(H69/(P69+Q69),1)*(P69*R69+S69) + if(mod(H69, P69+Q69) > P69, (P69*R69+S69), mod(H69, P69+Q69)*R69) -> 32769 | H69: =$H$68 -> 63 | I69: =$I$68 -> 127.65957 | J69: =$J$68 -> 1.15 | K69: 1.43 | L69: =floor(H69/(O69+Q69),1)*(O69*1/I69*60+J69) + if(mod(H69, O69+Q69) > O69, (O69*1/I69*60+J69), mod(H69, O69+Q69)*1/I69*60) -> 27.01 | M69: =floor(H69/(P69+Q69),1)*(P69*1/I69*60+J69) + if(mod(H69, P69+Q69) > P69, (P69*1/I69*60+J69), mod(H69, P69+Q69)*1/I69*60) -> 27.27 | N69: =K69-(O69*1/I69*60) -> 0.02 | O69: =CEILING(K69*I69*1/60,1)-1 -> 3 | P69: =O69+1 -> 4 | Q69: =$Q$68 -> 3 | R69: =$R$68 -> 385 | S69: =S68 -> 2101 | T69: Base Damage, no buffs
B70: 2 | C70: =(O70*R70 + S70) / (K70 + J70) -> 1335.3488 | D70: =(P70*R70 + S70) / (P70*1/I70*60 + J70) -> 1271.875 | F70: =floor(H70/(O70+Q70),1)*(O70*R70+S70) + if(mod(H70, O70+Q70) > O70, (O70*R70+S70), mod(H70, O70+Q70)*R70) -> 37323 | G70: =floor(H70/(P70+Q70),1)*(P70*R70+S70) + if(mod(H70, P70+Q70) > P70, (P70*R70+S70), mod(H70, P70+Q70)*R70) -> 33715 | H70: =$H$68 -> 63 | I70: =$I$68 -> 127.65957 | J70: =$J$68 -> 1.15 | K70: 1 | L70: =floor(H70/(O70+Q70),1)*(O70*1/I70*60+J70) + if(mod(H70, O70+Q70) > O70, (O70*1/I70*60+J70), mod(H70, O70+Q70)*1/I70*60) -> 27.17 | M70: =floor(H70/(P70+Q70),1)*(P70*1/I70*60+J70) + if(mod(H70, P70+Q70) > P70, (P70*1/I70*60+J70), mod(H70, P70+Q70)*1/I70*60) -> 27.01 | N70: =K70-(O70*1/I70*60) -> 0.06 | O70: =CEILING(K70*I70*1/60,1)-1 -> 2 | P70: =O70+1 -> 3 | Q70: =$Q$68 -> 3 | R70: =$R$68 -> 385 | S70: =S68 -> 2101 | T70: Base Damage, no buffs
B71: 3 | C71: =(O71*R71 + S71) / (K71 + J71) -> 1249.2462 | D71: =(P71*R71 + S71) / (P71*1/I71*60 + J71) -> 1373.6842 | F71: =floor(H71/(O71+Q71),1)*(O71*R71+S71) + if(mod(H71, O71+Q71) > O71, (O71*R71+S71), mod(H71, O71+Q71)*R71) -> 39776 | G71: =floor(H71/(P71+Q71),1)*(P71*R71+S71) + if(mod(H71, P71+Q71) > P71, (P71*R71+S71), mod(H71, P71+Q71)*R71) -> 37323 | H71: =$H$68 -> 63 | I71: =$I$68 -> 127.65957 | J71: =$J$68 -> 1.15 | K71: 0.84 | L71: =floor(H71/(O71+Q71),1)*(O71*1/I71*60+J71) + if(mod(H71, O71+Q71) > O71, (O71*1/I71*60+J71), mod(H71, O71+Q71)*1/I71*60) -> 25.92 | M71: =floor(H71/(P71+Q71),1)*(P71*1/I71*60+J71) + if(mod(H71, P71+Q71) > P71, (P71*1/I71*60+J71), mod(H71, P71+Q71)*1/I71*60) -> 27.17 | N71: =K71-(O71*1/I71*60) -> 0.37 | O71: =CEILING(K71*I71*1/60,1)-1 -> 1 | P71: =O71+1 -> 2 | Q71: =$Q$68 -> 3 | R71: =$R$68 -> 385 | S71: =S68 -> 2101 | T71: Base Damage, no buffs
B72: 0 | C72: =(O72*R72 + S72) / (K72 + J72) -> 1693.8309 | D72: =(P72*R72 + S72) / (P72*1/I72*60 + J72) -> 1653.5357 | F72: =floor(H72/(O72+Q72),1)*(O72*R72+S72) + if(mod(H72, O72+Q72) > O72, (O72*R72+S72), mod(H72, O72+Q72)*R72) -> 47105.438 | G72: =floor(H72/(P72+Q72),1)*(P72*R72+S72) + if(mod(H72, P72+Q72) > P72, (P72*R72+S72), mod(H72, P72+Q72)*R72) -> 46299 | H72: =$H$68 -> 63 | I72: =$I$68 -> 127.65957 | J72: =$J$68 -> 1.15 | K72: 1.94 | L72: =floor(H72/(O72+Q72),1)*(O72*1/I72*60+J72) + if(mod(H72, O72+Q72) > O72, (O72*1/I72*60+J72), mod(H72, O72+Q72)*1/I72*60) -> 27.27 | M72: =floor(H72/(P72+Q72),1)*(P72*1/I72*60+J72) + if(mod(H72, P72+Q72) > P72, (P72*1/I72*60+J72), mod(H72, P72+Q72)*1/I72*60) -> 28 | N72: =K72-(O72*1/I72*60) -> 0.06 | O72: =CEILING(K72*I72*1/60,1)-1 -> 4 | P72: =O72+1 -> 5 | Q72: =$Q$68 -> 3 | R72: =$R$68*1.25*1.15 -> 553.4375 | S72: =$S$68*1.25*1.15 -> 3020.1875 | T72: Assumes 100% SitD uptime
B73: 1 | C73: =(O73*R73 + S73) / (K73 + J73) -> 1814.1473 | D73: =(P73*R73 + S73) / (P73*1/I73*60 + J73) -> 1727.3721 | F73: =floor(H73/(O73+Q73),1)*(O73*R73+S73) + if(mod(H73, O73+Q73) > O73, (O73*R73+S73), mod(H73, O73+Q73)*R73) -> 48465.312 | G73: =floor(H73/(P73+Q73),1)*(P73*R73+S73) + if(mod(H73, P73+Q73) > P73, (P73*R73+S73), mod(H73, P73+Q73)*R73) -> 47105.438 | H73: =$H$68 -> 63 | I73: =$I$68 -> 127.65957 | J73: =$J$68 -> 1.15 | K73: 1.43 | L73: =floor(H73/(O73+Q73),1)*(O73*1/I73*60+J73) + if(mod(H73, O73+Q73) > O73, (O73*1/I73*60+J73), mod(H73, O73+Q73)*1/I73*60) -> 27.01 | M73: =floor(H73/(P73+Q73),1)*(P73*1/I73*60+J73) + if(mod(H73, P73+Q73) > P73, (P73*1/I73*60+J73), mod(H73, P73+Q73)*1/I73*60) -> 27.27 | N73: =K73-(O73*1/I73*60) -> 0.02 | O73: =CEILING(K73*I73*1/60,1)-1 -> 3 | P73: =O73+1 -> 4 | Q73: =$Q$68 -> 3 | R73: =$R$68*1.25*1.15 -> 553.4375 | S73: =S72 -> 3020.1875 | T73: Assumes 100% SitD uptime
B74: 2 | C74: =(O74*R74 + S74) / (K74 + J74) -> 1919.564 | D74: =(P74*R74 + S74) / (P74*1/I74*60 + J74) -> 1828.3203 | F74: =floor(H74/(O74+Q74),1)*(O74*R74+S74) + if(mod(H74, O74+Q74) > O74, (O74*R74+S74), mod(H74, O74+Q74)*R74) -> 53651.812 | G74: =floor(H74/(P74+Q74),1)*(P74*R74+S74) + if(mod(H74, P74+Q74) > P74, (P74*R74+S74), mod(H74, P74+Q74)*R74) -> 48465.312 | H74: =$H$68 -> 63 | I74: =$I$68 -> 127.65957 | J74: =$J$68 -> 1.15 | K74: 1 | L74: =floor(H74/(O74+Q74),1)*(O74*1/I74*60+J74) + if(mod(H74, O74+Q74) > O74, (O74*1/I74*60+J74), mod(H74, O74+Q74)*1/I74*60) -> 27.17 | M74: =floor(H74/(P74+Q74),1)*(P74*1/I74*60+J74) + if(mod(H74, P74+Q74) > P74, (P74*1/I74*60+J74), mod(H74, P74+Q74)*1/I74*60) -> 27.01 | N74: =K74-(O74*1/I74*60) -> 0.06 | O74: =CEILING(K74*I74*1/60,1)-1 -> 2 | P74: =O74+1 -> 3 | Q74: =$Q$68 -> 3 | R74: =$R$68*1.25*1.15 -> 553.4375 | S74: =S72 -> 3020.1875 | T74: Assumes 100% SitD uptime
B75: 3 | C75: =(O75*R75 + S75) / (K75 + J75) -> 1795.7915 | D75: =(P75*R75 + S75) / (P75*1/I75*60 + J75) -> 1974.6711 | F75: =floor(H75/(O75+Q75),1)*(O75*R75+S75) + if(mod(H75, O75+Q75) > O75, (O75*R75+S75), mod(H75, O75+Q75)*R75) -> 57178 | G75: =floor(H75/(P75+Q75),1)*(P75*R75+S75) + if(mod(H75, P75+Q75) > P75, (P75*R75+S75), mod(H75, P75+Q75)*R75) -> 53651.812 | H75: =$H$68 -> 63 | I75: =$I$68 -> 127.65957 | J75: =$J$68 -> 1.15 | K75: 0.84 | L75: =floor(H75/(O75+Q75),1)*(O75*1/I75*60+J75) + if(mod(H75, O75+Q75) > O75, (O75*1/I75*60+J75), mod(H75, O75+Q75)*1/I75*60) -> 25.92 | M75: =floor(H75/(P75+Q75),1)*(P75*1/I75*60+J75) + if(mod(H75, P75+Q75) > P75, (P75*1/I75*60+J75), mod(H75, P75+Q75)*1/I75*60) -> 27.17 | N75: =K75-(O75*1/I75*60) -> 0.37 | O75: =CEILING(K75*I75*1/60,1)-1 -> 1 | P75: =O75+1 -> 2 | Q75: =$Q$68 -> 3 | R75: =$R$68*1.25*1.15 -> 553.4375 | S75: =S72 -> 3020.1875 | T75: Assumes 100% SitD uptime
A76: Jump-Heavy | B76: N/A | C76: =(R76+S76)/(0.5+0.46+0.49) -> 470.34483 | D76: =(R76+S76)/(0.5+0.46+0.49) -> 470.34483 | F76: =floor(H76/(1+Q76),1)*(R76+S76) +if(mod(H76, 1+Q76) > 1+Q76, (R76+S76), R76) -> 21463 | G76: =floor(H76/(1+Q76),1)*(R76+S76) +if(mod(H76, 1+Q76) > 1+Q76, (R76+S76), R76) -> 21463 | H76: =$H$68 -> 63 | I76: =(2/(0.05+0.46+0.49))*60 -> 120 | J76: 0.48 | K76: N/A | L76: =H76*1/I76*60 -> 31.5 | M76: =H76*1/I76*60 -> 31.5 | N76: N/A | O76: N/A | P76: N/A | Q76: 1 | R76: 321 | S76: 361
A77: Light Spam | B77: N/A | C77: =R77*I77*1/60 -> 819.14894 | D77: =R77*I77*1/60 -> 819.14894 | F77: =H77*R77 -> 24255 | G77: =H77*R77 -> 24255 | H77: =$H$68 -> 63 | I77: =$I$68 -> 127.65957 | J77: N/A | K77: N/A | L77: N/A | M77: N/A | N77: N/A | O77: N/A | P77: N/A | Q77: N/A | R77: =$R$68 -> 385 | S77: N/A
A79: § «« | LAMENT | »» §
B80: Revved Timings | D80: Normal Timings | F80: Animation Time After... | H80: Recharge Delay | J80: Recharge From Empty | L80: Normal Damage | N80: Rev Light Damage | P80: Rev Heavy Damage
B81: R_Heavy | C81: 0.98 | D81: N_Heavy | E81: 1.08 | F81: N_Light_1 | G81: 0.58 | H81: 0 LB | I81: 0.1 | J81: 0 LB | K81: 4.07 | L81: Light | M81: =$R$9 -> 436 | N81: 1x BW | O81: =436+109*2 -> 654 | P81: 1x BW | Q81: =814+153*2 -> 1120
B82: R_Light_1 | C82: 0.49 | D82: N_Light_1 | E82: 0.46 | F82: N_Light_2 | G82: 0.89 | H82: 1 LB | I82: 0.07 | J82: 1 LB | K82: 2.96 | L82: Heavy | M82: =$S$9 -> 1492 | N82: 4x BW | O82: =582+109*2 -> 800 | P82: 4x BW | Q82: =1163+218*2 -> 1599
B83: R_Light_2 | C83: 0.5 | D83: N_Light_2 | E83: 0.46 | F83: N_Light_3 | G83: 0.85 | H83: 2 LB | I83: 0.05 | J83: 2 LB | K83: 2.12 | N83: 7x BW | O83: =O82 -> 800 | P83: 7x BW | Q83: =1512 + 284*2 -> 2080
B84: R_Light_3 | C84: 0.5 | D84: N_Light_3 | E84: 0.49 | H84: 3 LB | I84: 0.03 | J84: 3 LB | K84: 1.86 | N84: 9x BW | O84: =O82 -> 800 | P84: 9x BW | Q84: =1363 + 273*2 -> 1909
B85: Guard | C85: 0.15 | D85: SPM | E85: =(3)/((E82+E83+E84)*1/60) -> 127.65957
A87: Strat | B87: Lucent Blades Count | C87: Combo DPS | F87: Theoretical Total Damage | G87: Combo damage | H87: Reserves | I87: Revved Light Count | J87: Revved Heavy Count | K87: Normal Light Count | L87: Combo Time | M87: Time to Empty | N87: Combo Ammo Cost
A88: Light Spam | B88: 0 | C88: =M81*E85*1/60 -> 927.65957 | F88: =H88*M81 -> 28340 | G88: =M81+M81+M81 -> 1308 | H88: ='Reserves Data (Reference)'!$D$125 -> 65 | I88: N/A | J88: N/A | K88: N/A | L88: =E82+E83+E84 -> 1.41 | M88: =H88*1/E85*60 -> 30.55 | N88: =3 -> 3
A89: Revved Heavy Spam | B89: 0 | C89: =(G89)/(L89) -> 910.56911 | F89: =ceiling(H89/2,1)*Q81 -> 36960 | G89: =Q81 -> 1120 | H89: =$H$88 -> 65 | I89: N/A | J89: N/A | K89: N/A | L89: =C81+I81+C85 -> 1.23 | M89: =CEILING(H89/N89,1)*L89 -> 40.59 | N89: 2
A90: Normal Heavy Spam | B90: 0 | C90: =(G90)/(L90) -> 1264.4068 | F90: =ceiling(H90/4,1)*M82 -> 25364 | G90: =M82 -> 1492 | H90: =$H$88 -> 65 | I90: N/A | J90: N/A | K90: N/A | L90: =E81+I81 -> 1.18 | M90: =CEILING(H90/N90,1)*L90 -> 20.06 | N90: 4
A91: 1x1x1 | B91: 0 | C91: =(G91)/(L91) -> 1088.664 | F91: =floor(H91/(I91+J91*2+K91),1)*G91 +O81+Q81 -> 44798 | G91: =O81+Q82+M81 -> 2689 | H91: =$H$88 -> 65 | I91: 1 | J91: 1 | K91: 1 | L91: =C85+C82+C81+G83 -> 2.47 | M91: =floor(H91/N91,1)*L91 +C82+C81 -> 40.99 | N91: =I91+J91*2+K91 -> 4
A92: 2x1x1 | B92: 2 | C92: =(G92)/(L92) -> 1336.7003 | F92: =floor(H92/(I92+J92*2+K92),1)*G92 + O81+O82+Q82 -> 54663 | G92: =O81+O82+Q83+M81 -> 3970 | H92: =$H$88 -> 65 | I92: 2 | J92: 1 | K92: 1 | L92: =C85+C82+C83+C81+G83 -> 2.97 | M92: =floor(H92/N92,1)*L92 +C82+C83+C81 -> 40.58 | N92: =I92+J92*2+K92 -> 5
A93: 3x1x1 | B93: 3 | C93: =(G93)/(L93) -> 1288.2353 | F93: =floor(H93/(I93+J93*2+K93),1)*G93 + O81+O82+O83+Q83 -> 50324 | G93: =O81+O82+O83+Q84+M81 -> 4599 | H93: =$H$88 -> 65 | I93: 3 | J93: 1 | K93: 1 | L93: =C85+C82+C83+C84+C81+G83+0.1 -> 3.57 | M93: =floor(H93/N93,1)*L93 +C82+C83+C84+C81 -> 38.17 | N93: =I93+J93*2+K93 -> 6
A94: 1x1x2 | B94: 0 | C94: =(G94)/(L94) -> 1161.71 | F94: =floor(H94/(I94+J94*2+K94),1)*G94 + O81+Q81 -> 42399 | G94: =O81+Q82+M81+M81 -> 3125 | H94: =$H$88 -> 65 | I94: 1 | J94: 1 | K94: 2 | L94: =C85+C82+C81+E84+G81 -> 2.69 | M94: =floor(H94/N94,1)*L94 +C82+C81 -> 36.44 | N94: =I94+J94*2+K94 -> 5
A95: 2x1x2 | B95: 1 | C95: =(G95)/(L95) -> 1381.1912 | F95: =floor(H95/(I95+J95*2+K95),1)*G95 + O81+O82+Q82 -> 47113 | G95: =O81+O82+Q83+M81+M81 -> 4406 | H95: =$H$88 -> 65 | I95: 2 | J95: 1 | K95: 2 | L95: =C85+C82+C83+C81+E84+G81 -> 3.19 | M95: =floor(H95/N95,1)*L95 +C82+C83+C81 -> 33.87 | N95: =I95+J95*2+K95 -> 6
A96: 3x1x2 | B96: 2 | C96: =(G96)/(L96) -> 1364.4986 | F96: =floor(H96/(I96+J96*2+K96),1)*G96 + O81+O82 -> 46769 | G96: =O81+O82+O83+Q84+M81+M81 -> 5035 | H96: =$H$88 -> 65 | I96: 3 | J96: 1 | K96: 2 | L96: =C85+C82+C83+C84+C81+E84+G81 -> 3.69 | M96: =floor(H96/N96,1)*L96 +C82+C83 -> 34.2 | N96: =I96+J96*2+K96 -> 7
A97: 4x1x2 | B97: 3 | C97: =(G97)/(L97) -> 1360.1399 | F97: =floor(H97/(I97+J97*2+K97),1)*G97 + O81+O82 -> 48134 | G97: =O81+O82+O83+O84+Q84+M81+M81 -> 5835 | H97: =$H$88 -> 65 | I97: 4 | J97: 1 | K97: 2 | L97: =C85+C82+C83+C84+C83+C81+E84+G81+0.1 -> 4.29 | M97: =floor(H97/N97,1)*L97 +C82+C83 -> 35.31 | N97: =I97+J97*2+K97 -> 8
A98: 1x1x3 | B98: 0 | C98: =(G98)/(L98) -> 1029.1908 | F98: =floor(H98/(I98+J98*2+K98),1)*G98 + O81+Q81+M81 -> 37820 | G98: =O81+Q82+M81+M81+M81 -> 3561 | H98: =$H$88 -> 65 | I98: 1 | J98: 1 | K98: 3 | L98: =C85+C82+C81+E84+E82+G82 -> 3.46 | M98: =floor(H98/N98,1)*L98 +C82+C81+E84 -> 36.56 | N98: =I98+J98*2+K98 -> 6
A99: 2x1x3 | B99: 0 | C99: =(G99)/(L99) -> 1326.5753 | F99: =floor(H99/(I99+J99*2+K99),1)*G99 + O81+O82 -> 45032 | G99: =O81+O82+Q83+M81+M81+M81 -> 4842 | H99: =$H$88 -> 65 | I99: 2 | J99: 1 | K99: 3 | L99: =C85+C82+C83+C81+E84+E82+G81 -> 3.65 | M99: =floor(H99/N99,1)*L99 +C82+C83 -> 33.84 | N99: =I99+J99*2+K99 -> 7
A100: 3x1x3 | B100: 1 | C100: =(G100)/(L100) -> 1237.7828 | F100: =floor(H100/(I100+J100*2+K100),1)*G100 + O81+O82 -> 45222 | G100: =O81+O82+O83+Q84+M81+M81+M81 -> 5471 | H100: =$H$88 -> 65 | I100: 3 | J100: 1 | K100: 3 | L100: =C85+C82+C83+C84+C81+E84+E82+G83 -> 4.42 | M100: =floor(H100/N100,1)*L100 +C82+C83 -> 36.35 | N100: =I100+J100*2+K100 -> 8
A101: 4x1x3 | B101: 2 | C101: =(G101)/(L101) -> 1264.3145 | F101: =floor(H101/(I101+J101*2+K101),1)*G101 + O81+O82+O83+O84 -> 46951 | G101: =O81+O82+O83+O84+Q84+M81+M81+M81 -> 6271 | H101: =$H$88 -> 65 | I101: 4 | J101: 1 | K101: 3 | L101: =C85+C82+C83+C84+C83+C81+E84+E82+G82 -> 4.96 | M101: =floor(H101/N101,1)*L101 +C82+C83+C84+C83 -> 36.71 | N101: =I101+J101*2+K101 -> 9
A102: 5x1x3 | B102: 3 | C102: =(G102)/(L102) -> 1295.0549 | F102: =floor(H102/(I102+J102*2+K102),1)*G102 + O81+O82+O83+O84+O84+Q84+M81 -> 48625 | G102: =O81+O82+O83+O84+O84+Q84+M81+M81+M81 -> 7071 | H102: =$H$88 -> 65 | I102: 5 | J102: 1 | K102: 3 | L102: =C85+C82+C83+C84+C83+C84+C81+E84+E82+G82 -> 5.46 | M102: =floor(H102/N102,1)*L102 +C82+C83+C84+C83+C84+C81+E84 -> 36.72 | N102: =I102+J102*2+K102 -> 10
...

Sheet All Weapons (Sortable)
A1: All weapon damage is normalized !!! IMPORTANT: ALL SWORDS ASSUME SWORDMASTER'S GUARD + JAGGED EDGE + MASTERWORK + BACKUP MAG UNLESS EXOTIC OR OTHERWISE STATED !!! To see how you can sort this data without downloading a copy of this spreadsheet, see the note attached on this cell; use the formula bar to read any associated notes on weapons Want to contribute? Have questions, comments, or concerns? See Home page for contact information.
A2: Ammo | B2: Weap. Tag | C2: Lucent Blades Count | D2: Frame/Weapon | E2: 1-Mag Burst or "True" DPS | F2: Sustained DPS | G2: Theoretical Total Damage | H2: 1-Mag Damage | I2: Magazine Capacity | J2: Reserves + Magazine | K2: rpm/spm | L2: Reload Speed (s) | M2: Time to Empty (s) | N2: Body/ Light Damage | O2: Precision/ Heavy Damage | P2: Notes
A3: H | B3: Bows | C3: N/A | D3: =Heavies!$B$89 -> Leviathan's Breath | E3: =Heavies!$C$89 -> 1087.6556 | F3: =Heavies!$D$89 -> 1087.6556 | G3: =Heavies!$F$89 -> 18873 | H3: =Heavies!$G$89 -> 2097 | I3: =Heavies!$H$89 -> 1 | J3: =Heavies!$I$89 -> 9 | K3: =Heavies!$J$89 -> 31.120332 | L3: =Heavies!$K$89 -> 0.6 | M3: =Heavies!$L$89 -> 17.352 | N3: =Heavies!$M$89 -> 1779 | O3: =Heavies!$N$89 -> 2097 | P3: W/o catalyst
A4: H | B4: Bows | C4: N/A | D4: =Heavies!$B$90 -> Leviathan's Breath | E4: =Heavies!$C$90 -> 1556.7929 | F4: =Heavies!$D$90 -> 1556.7929 | G4: =Heavies!$F$90 -> 29358 | H4: =Heavies!$G$90 -> 2097 | I4: =Heavies!$H$90 -> 1 | J4: =Heavies!$I$90 -> 14 | K4: =Heavies!$J$90 -> 44.54343 | L4: =Heavies!$K$90 -> 0.6 | M4: =Heavies!$L$90 -> 18.858 | N4: =Heavies!$M$90 -> 1779 | O4: =Heavies!$N$90 -> 2097 | P4: W/ cata; Assumes 100% uptime on Archer's Tempo
A5: H | B5: TrRi | C5: N/A | D5: =Heavies!$B$92 -> Microcosm | E5: =Heavies!$C$92 -> 1407.2727 | F5: =Heavies!$D$92 -> 1201.0863 | G5: =Heavies!$F$92 -> 34102.909 | H5: =Heavies!$G$92 -> 11258.182 | I5: =Heavies!$H$92 -> 120 | J5: =Heavies!$I$92 -> 385 | K5: =Heavies!$J$92 -> 900 | L5: =Heavies!$K$92 -> 1.44 | M5: =Heavies!$L$92 -> 29.72 | N5: =Heavies!$M$92 -> 70.909091 | O5: =Heavies!$N$92 -> 93.818182
A6: H | B6: TrRi | C6: N/A | D6: =Heavies!$B$91 -> Microcosm | E6: =Heavies!$C$91 -> 1172.7273 | F6: =Heavies!$D$91 -> 1000.9052 | G6: =Heavies!$F$91 -> 30100 | H6: =Heavies!$G$91 -> 9381.8182 | I6: =Heavies!$H$91 -> 120 | J6: =Heavies!$I$91 -> 385 | K6: =Heavies!$J$91 -> 900 | L6: =Heavies!$K$91 -> 1.44 | M6: =Heavies!$L$91 -> 29.72 | N6: =Heavies!$M$91 -> 59.090909 | O6: =Heavies!$N$91 -> 78.181818 | P6: Paracausal Imbuement: Grants +20% damage on end of super for 20 seconds
A7: H | B7: FuRi | C7: N/A | D7: =Heavies!$B$88 -> One Thousand Voices | E7: =Heavies!$C$88 -> 1136.612 | F7: =Heavies!$D$88 -> 1009.7087 | G7: =Heavies!$F$88 -> 22880 | H7: =Heavies!$G$88 -> 8320 | I7: =Heavies!$H$88 -> 4 | J7: =Heavies!$I$88 -> 11 | K7: =Heavies!$J$88 -> 32.786885 | L7: =Heavies!$K$88 -> 1.25 | M7: =Heavies!$L$88 -> 20.68 | N7: =Heavies!$M$88 -> 2080 | O7: =Heavies!$N$88 -> N/A | P7: Does not consider Scorch; without ignition
A8: H | B8: FuRi | C8: N/A | D8: =Heavies!$B$87 -> One Thousand Voices | E8: =Heavies!$C$87 -> 1169.3989 | F8: =Heavies!$D$87 -> 1038.835 | G8: =Heavies!$F$87 -> 23540 | H8: =Heavies!$G$87 -> 8560 | I8: =Heavies!$H$87 -> 4 | J8: =Heavies!$I$87 -> 11 | K8: =Heavies!$J$87 -> 32.786885 | L8: =Heavies!$K$87 -> 1.25 | M8: =Heavies!$L$87 -> 20.68 | N8: =Heavies!$M$87 -> 2080 | O8: =Heavies!$N$87 -> N/A | P8: Does not consider Scorch; without ignition; Ember of Ashes
A9: H | B9: FuRi | C9: N/A | D9: =Heavies!$B$86 -> One Thousand Voices | E9: =Heavies!$C$86 -> 1153.0055 | F9: =Heavies!$D$86 -> 1024.2718 | G9: =Heavies!$F$86 -> 23180 | H9: =Heavies!$G$86 -> 8440 | I9: =Heavies!$H$86 -> 4 | J9: =Heavies!$I$86 -> 11 | K9: =Heavies!$J$86 -> 32.786885 | L9: =Heavies!$K$86 -> 1.25 | M9: =Heavies!$L$86 -> 20.68 | N9: =Heavies!$M$86 -> 2080 | O9: =Heavies!$N$86 -> N/A | P9: Does not consider Scorch; with ignition
A10: H | B10: Glai | C10: N/A | D10: =Heavies!$B$76 -> Winterbite | E10: =Heavies!$C$76 -> 253.33333 | F10: =Heavies!$D$76 -> 253.33333 | G10: =Heavies!$F$76 -> inf | H10: =Heavies!$G$76 -> N/A | I10: =Heavies!$H$76 -> N/A | J10: =Heavies!$I$76 -> N/A | K10: =Heavies!$J$76 -> 133.33333 | L10: =Heavies!$K$76 -> N/A | M10: =Heavies!$L$76 -> N/A | N10: =Heavies!$M$76 -> 114 | O10: =Heavies!$N$76 -> N/A | P10: Melee while blocking/ADS w/o ammo
A11: H | B11: Glai | C11: N/A | D11: =Heavies!$B$74 -> Winterbite | E11: =Heavies!$C$74 -> 404.27778 | F11: =Heavies!$D$74 -> 404.27778 | G11: =Heavies!$F$74 -> inf | H11: =Heavies!$G$74 -> N/A | I11: =Heavies!$H$74 -> N/A | J11: =Heavies!$I$74 -> N/A | K11: =Heavies!$J$74 -> 133.33333 | L11: =Heavies!$K$74 -> N/A | M11: =Heavies!$L$74 -> N/A | N11: =Heavies!$M$74 -> 136.8 | O11: =Heavies!$N$74 -> N/A | P11: Melee while blocking/ADS w/ ammo
A12: H | B12: Glai | C12: N/A | D12: =Heavies!$B$75 -> Winterbite | E12: =Heavies!$C$75 -> 306.43548 | F12: =Heavies!$D$75 -> 306.43548 | G12: =Heavies!$F$75 -> inf | H12: =Heavies!$G$75 -> N/A | I12: =Heavies!$H$75 -> N/A | J12: =Heavies!$I$75 -> N/A | K12: =Heavies!$J$75 -> 116.12903 | L12: =Heavies!$K$75 -> N/A | M12: =Heavies!$L$75 -> N/A | N12: =Heavies!$M$75 -> 136.8 | O12: =Heavies!$N$75 -> N/A | P12: Melee without blocking/ADS w/ ammo
A13: H | B13: Glai | C13: N/A | D13: =Heavies!$B$73 -> Winterbite | E13: =Heavies!$C$73 -> 424.875 | F13: =Heavies!$D$73 -> 506.76633 | G13: =Heavies!$F$73 -> 18252 | H13: =Heavies!$G$73 -> 3042 | I13: =Heavies!$H$73 -> 3 | J13: =Heavies!$I$73 -> 18 | K13: =Heavies!$J$73 -> 45 | L13: =Heavies!$K$73 -> 1.57 | M13: =Heavies!$L$73 -> 23.85 | N13: =Heavies!$M$73 -> 1014 | O13: =Heavies!$N$73 -> N/A | P13: This assumes there is a freeze between every shot
A14: H | B14: HeGL | C14: N/A | D14: =Heavies!$B$19 -> Adaptive | E14: =Heavies!$C$19 -> 1444 | F14: =Heavies!$D$19 -> 1035.1254 | G14: =Heavies!$F$19 -> 18772 | H14: =Heavies!$G$19 -> 5776 | I14: =Heavies!$H$19 -> 8 | J14: =Heavies!$I$19 -> 26 | K14: =Heavies!$J$19 -> 120 | L14: =Heavies!$K$19 -> 2.08 | M14: =Heavies!$L$19 -> 17.24 | N14: =Heavies!$M$19 -> 722 | O14: =Heavies!$N$19 -> N/A
A15: H | B15: HeGL | C15: N/A | D15: =Heavies!$B$20 -> Adaptive | E15: =Heavies!$C$20 -> 2406.6667 | F15: =Heavies!$D$20 -> 1381.8182 | G15: =Heavies!$F$20 -> 18772 | H15: =Heavies!$G$20 -> 5776 | I15: =Heavies!$H$20 -> 8 | J15: =Heavies!$I$20 -> 26 | K15: =Heavies!$J$20 -> 200 | L15: =Heavies!$K$20 -> 2.08 | M15: =Heavies!$L$20 -> 12.84 | N15: =Heavies!$M$20 -> 722 | O15: =Heavies!$N$20 -> N/A | P15: Cascade Point
A16: H | B16: HeGL | C16: N/A | D16: =Heavies!$B$25 -> Anarchy | E16: =Heavies!$C$25 -> 145.9 | F16: =Heavies!$D$25 -> 145.9 | G16: =Heavies!$F$25 -> 42311 | H16: =Heavies!$G$25 -> 8754 | I16: =Heavies!$H$25 -> 6 | J16: =Heavies!$I$25 -> 29 | K16: =Heavies!$J$25 -> 150 | L16: =Heavies!$K$25 -> 2.08 | M16: =Heavies!$L$25 -> 290 | N16: =Heavies!$M$25 -> 19 | O16: =Heavies!$N$25 -> N/A | P16: Assumes a single grenade > wait out damage, reloading while waiting
A17: H | B17: HeGL | C17: N/A | D17: =Heavies!$B$26 -> Anarchy | E17: =Heavies!$C$26 -> 963.9 | F17: =Heavies!$D$26 -> 963.9 | G17: =Heavies!$F$26 -> 136671 | H17: =Heavies!$G$26 -> 28974 | I17: =Heavies!$H$26 -> 6 | J17: =Heavies!$I$26 -> 29 | K17: =Heavies!$J$26 -> 150 | L17: =Heavies!$K$26 -> 2.08 | M17: =Heavies!$L$26 -> 150 | N17: =Heavies!$M$26 -> 19 | O17: =Heavies!$N$26 -> N/A | P17: Assumes two grenades > wait out damage, reloading while waiting
A18: H | B18: HeGL | C18: N/A | D18: =Heavies!$B$21 -> Compressed Wave | E18: =Heavies!$C$21 -> 1460 | F18: =Heavies!$D$21 -> 902.82686 | G18: =Heavies!$F$21 -> 18980 | H18: =Heavies!$G$21 -> 5110 | I18: =Heavies!$H$21 -> 7 | J18: =Heavies!$I$21 -> 26 | K18: =Heavies!$J$21 -> 120 | L18: =Heavies!$K$21 -> 2.16 | M18: =Heavies!$L$21 -> 19.48 | N18: =Heavies!$M$21 -> 730 | O18: =Heavies!$N$21 -> N/A
A19: H | B19: HeGL | C19: N/A | D19: =Heavies!$B$22 -> Compressed Wave | E19: =Heavies!$C$22 -> 2433.3333 | F19: =Heavies!$D$22 -> 1199.5305 | G19: =Heavies!$F$22 -> 18980 | H19: =Heavies!$G$22 -> 5110 | I19: =Heavies!$H$22 -> 7 | J19: =Heavies!$I$22 -> 26 | K19: =Heavies!$J$22 -> 200 | L19: =Heavies!$K$22 -> 2.16 | M19: =Heavies!$L$22 -> 14.28 | N19: =Heavies!$M$22 -> 730 | O19: =Heavies!$N$22 -> N/A | P19: Cascade Point
A20: H | B20: HeGL | C20: N/A | D20: =Heavies!$B$28 -> Parasite | E20: =Heavies!$C$28 -> 4064 | F20: =Heavies!$D$28 -> 976.92308 | G20: =Heavies!$F$28 -> 36576 | H20: =Heavies!$G$28 -> 2032 | I20: =Heavies!$H$28 -> 1 | J20: =Heavies!$I$28 -> 18 | K20: =Heavies!$J$28 -> 120 | L20: =Heavies!$K$28 -> 2.08 | M20: =Heavies!$L$28 -> 35.36 | N20: =Heavies!$M$28 -> 2032 | O20: =Heavies!$N$28 -> N/A
A21: H | B21: HeGL | C21: N/A | D21: =Heavies!$B$29 -> Parasite | E21: =Heavies!$C$29 -> 4064 | F21: =Heavies!$D$29 -> 1149.3213 | G21: =Heavies!$F$29 -> 40640 | H21: =Heavies!$G$29 -> 6096 | I21: =Heavies!$H$29 -> 1 | J21: =Heavies!$I$29 -> 18 | K21: =Heavies!$J$29 -> 120 | L21: =Heavies!$K$29 -> 2.08 | M21: =Heavies!$L$29 -> 35.36 | N21: =Heavies!$M$29 -> 2032 | O21: =Heavies!$N$29 -> N/A | P21: Assumes first shot is x20 Worm's Hunger, rest are 0x Worm's Hunger; average DPS
A22: H | B22: HeGL | C22: N/A | D22: =Heavies!$B$17 -> Rapid-Fire | E22: =Heavies!$C$17 -> 1535 | F22: =Heavies!$D$17 -> 1040.678 | G22: =Heavies!$F$17 -> 18420 | H22: =Heavies!$G$17 -> 4912 | I22: =Heavies!$H$17 -> 8 | J22: =Heavies!$I$17 -> 30 | K22: =Heavies!$J$17 -> 150 | L22: =Heavies!$K$17 -> 1.92 | M22: =Heavies!$L$17 -> 16.16 | N22: =Heavies!$M$17 -> 614 | O22: =Heavies!$N$17 -> N/A
A23: H | B23: HeGL | C23: N/A | D23: =Heavies!$B$18 -> Rapid-Fire | E23: =Heavies!$C$18 -> 2558.3333 | F23: =Heavies!$D$18 -> 1364.4444 | G23: =Heavies!$F$18 -> 18420 | H23: =Heavies!$G$18 -> 4912 | I23: =Heavies!$H$18 -> 8 | J23: =Heavies!$I$18 -> 30 | K23: =Heavies!$J$18 -> 250 | L23: =Heavies!$K$18 -> 1.92 | M23: =Heavies!$L$18 -> 12 | N23: =Heavies!$M$18 -> 614 | O23: =Heavies!$N$18 -> N/A | P23: Cascade Point
A24: H | B24: HeGL | C24: N/A | D24: =Heavies!$B$36 -> Salvation's Grip | E24: =Heavies!$C$36 -> 970.8 | F24: =Heavies!$D$36 -> 970.8 | G24: =Heavies!$F$36 -> 30560 | H24: =Heavies!$G$36 -> N/A | I24: =Heavies!$H$36 -> 8 | J24: =Heavies!$I$36 -> 25 | K24: =Heavies!$J$36 -> 60 | L24: =Heavies!$K$36 -> 2.2 | M24: =Heavies!$L$36 -> 12.5 | N24: =Heavies!$M$36 -> 991 | O24: =Heavies!$N$36 -> N/A | P24: Whisper of Fissures; Full charge > normal shot > repeat; assumes no reloading due to Shatter Shot
A25: H | B25: HeGL | C25: N/A | D25: =Heavies!$B$30 -> Salvation's Grip | E25: =Heavies!$C$30 -> 1522 | F25: =Heavies!$D$30 -> 1068.0702 | G25: =Heavies!$F$30 -> 19025 | H25: =Heavies!$G$30 -> 6088 | I25: =Heavies!$H$30 -> 8 | J25: =Heavies!$I$30 -> 25 | K25: =Heavies!$J$30 -> 120 | L25: =Heavies!$K$30 -> 2.2 | M25: =Heavies!$L$30 -> 17.1 | N25: =Heavies!$M$30 -> 761 | O25: =Heavies!$N$30 -> N/A | P25: No charge, spamming
A26: H | B26: HeGL | C26: N/A | D26: =Heavies!$B$33 -> Salvation's Grip | E26: =Heavies!$C$33 -> 1156 | F26: =Heavies!$D$33 -> 1156 | G26: =Heavies!$F$33 -> 29065 | H26: =Heavies!$G$33 -> N/A | I26: =Heavies!$H$33 -> 8 | J26: =Heavies!$I$33 -> 25 | K26: =Heavies!$J$33 -> 60 | L26: =Heavies!$K$33 -> 2.2 | M26: =Heavies!$L$33 -> 16.666667 | N26: =Heavies!$M$33 -> 991 | O26: =Heavies!$N$33 -> N/A | P26: Full charge > normal shot > repeat; assumes no reloading due to Shatter Shot
A27: H | B27: HeGL | C27: N/A | D27: =Heavies!$B$32 -> Salvation's Grip | E27: =Heavies!$C$32 -> 390.66667 | F27: =Heavies!$D$32 -> 390.66667 | G27: =Heavies!$F$32 -> 14650 | H27: =Heavies!$G$32 -> N/A | I27: =Heavies!$H$32 -> 8 | J27: =Heavies!$I$32 -> 25 | K27: =Heavies!$J$32 -> 60 | L27: =Heavies!$K$32 -> 2.2 | M27: =Heavies!$L$32 -> 27.6 | N27: =Heavies!$M$32 -> 158 | O27: =Heavies!$N$32 -> N/A | P27: Spamming full charges; assumes boss is big enough that it shatters the entire wave instantly
A28: H | B28: HeGL | C28: N/A | D28: =Heavies!$B$31 -> Salvation's Grip | E28: =Heavies!$C$31 -> 672 | F28: =Heavies!$D$31 -> 672 | G28: =Heavies!$F$31 -> 25609 | H28: =Heavies!$G$31 -> N/A | I28: =Heavies!$H$31 -> 8 | J28: =Heavies!$I$31 -> 25 | K28: =Heavies!$J$31 -> 60 | L28: =Heavies!$K$31 -> 2.2 | M28: =Heavies!$L$31 -> 27.6 | N28: =Heavies!$M$31 -> 158 | O28: =Heavies!$N$31 -> N/A | P28: Spamming full charges; Assumes boss naturally shatters on its own (no additional damage done from any other source)
A29: H | B29: HeGL | C29: N/A | D29: =Heavies!$B$34 -> Salvation's Grip | E29: =Heavies!$C$34 -> 869 | F29: =Heavies!$D$34 -> 869 | G29: =Heavies!$F$34 -> 32816 | H29: =Heavies!$G$34 -> N/A | I29: =Heavies!$H$34 -> 8 | J29: =Heavies!$I$34 -> 25 | K29: =Heavies!$J$34 -> 60 | L29: =Heavies!$K$34 -> 2.2 | M29: =Heavies!$L$34 -> 27.6 | N29: =Heavies!$M$34 -> 158 | O29: =Heavies!$N$34 -> N/A | P29: Whisper of Fissures; Spamming full charges; Assumes boss naturally shatters on its own (no additional damage done from any other source)
